Workbook
Name SegmentaciónDeDatos_Año: #N/A
Name SegmentaciónDeDatos_AÑO1: #N/A
Name SegmentaciónDeDatos_AÑO2: #N/A
Name SegmentaciónDeDatos_Factura: #N/A
Name SegmentaciónDeDatos_Factura1: #N/A
Name SegmentaciónDeDatos_Mes: #N/A
Name SegmentaciónDeDatos_MES1: #N/A

Sheet Inmuebles
B2: CONTRATO DE OBRA No PAF-ANI-O-118-2022-01 CON CONSORCIO CTSA - INGERAL - ARRENDAMIENTO DE INMUEBLES
B3: FACTURACIÓN | Q3: PAGO
B4: Año | C4: Mes | D4: Fecha | E4: # Factura CTSA - INGERAL | F4: NC | G4: Fact | H4: Corredor | I4: Tercero | J4: Periodo | K4: Inmueble - concepto | L4: Valor Facturado | M4: IVA | N4: Valor bruto | O4: 4 X 1000 | P4: Valor a Consignar a la ANI | Q4: Valor Pagado | R4: Año. | S4: Mes. | T4: Fecha. | U4: Valor Por Cobrar | V4: Observaciones
B5: =+YEAR(D5) -> 2023 | C5: =UPPER(TEXT(D5,"MMM")) -> MAY | D5: 45055 | E5: 3 | F5: NA | G5: NA | H5: Bogotá - Belencito | I5: MAQUISERVICOS | J5: 1/02/2023 - 15/04/2023 | K5: ARRIENDO DE BODEGA Y OFICINAS DE 99,11 m2, UBICADO EN EL KM5 | L5: 4465171.5 | M5: 712926.55 | N5: =L5-M5 -> 3752245 | O5: =ROUND(N5*0.004,0) -> 15009 | P5: =N5-O5 -> 3737236 | Q5: 3737236 | R5: =+YEAR(T5) -> 2023 | S5: =+MONTH(T5) -> 7 | T5: 45135 | U5: =+P5-Q5 -> 0
B6: =+YEAR(D6) -> 2023 | C6: =UPPER(TEXT(D6,"MMM")) -> MAY | D6: 45057 | E6: 4 | F6: NA | G6: NA | H6: Bogotá - Belencito | I6: CIRO | J6: 1/02/2023 - 13/03/2023 | K6: ARRIENDO DE BODEGA DE 72 M2, UBICADO EN KM 5 | L6: 1859767.7 | M6: 296937.7 | N6: =L6-M6 -> 1562830 | O6: =ROUND(N6*0.004,0) -> 6251 | P6: =N6-O6 -> 1556579 | Q6: 1556579 | R6: =+YEAR(T6) -> 2023 | S6: =+MONTH(T6) -> 7 | T6: 45135 | U6: =+P6-Q6 -> 0
B7: =+YEAR(D7) -> 2023 | C7: =UPPER(TEXT(D7,"MMM")) -> MAY | D7: 45057 | E7: 5 | F7: NA | G7: NA | H7: Bogotá - Belencito | I7: CIRO | J7: 14/03/2023 - 30/03/2023 | K7: ARRIENDO DE BODEGA DE 72 M2, UBICADO EN KM 5 | L7: 735256.97 | M7: 117393.97 | N7: =L7-M7 -> 617863 | O7: =ROUND(N7*0.004,0) -> 2471 | P7: =N7-O7 -> 615392 | Q7: 615392 | R7: =+YEAR(T7) -> 2023 | S7: =+MONTH(T7) -> 7 | T7: 45135 | U7: =+P7-Q7 -> 0
B8: =+YEAR(D8) -> 2023 | C8: =UPPER(TEXT(D8,"MMM")) -> MAY | D8: 45057 | E8: 6 | F8: NA | G8: NA | H8: Bogotá - Belencito | I8: CIRO | J8: 01/04/2023 - 30/04/2023 | K8: ARRIENDO DE BODEGA DE 72 M2, UBICADO EN KM 5 | L8: 1297511.7 | M8: 207165.74 | N8: =L8-M8 -> 1090346 | O8: =ROUND(N8*0.004,0) -> 4361 | P8: =N8-O8 -> 1085985 | Q8: 1085985 | R8: =+YEAR(T8) -> 2023 | S8: =+MONTH(T8) -> 7 | T8: 45135 | U8: =+P8-Q8 -> 0
B9: =+YEAR(D9) -> 2023 | C9: =UPPER(TEXT(D9,"MMM")) -> MAY | D9: 45057 | E9: 7 | F9: NA | G9: NA | H9: Bogotá - Belencito | I9: CIRO | J9: 01/05/2023 - 31/05/2023 | K9: ARRIENDO DE BODEGA DE 72 M2, UBICADO EN KM 5 | L9: 1297511.7 | M9: 207165.74 | N9: =L9-M9 -> 1090346 | O9: =ROUND(N9*0.004,0) -> 4361 | P9: =N9-O9 -> 1085985 | Q9: 1085985 | R9: =+YEAR(T9) -> 2023 | S9: =+MONTH(T9) -> 7 | T9: 45135 | U9: =+P9-Q9 -> 0
B10: =+YEAR(D10) -> 2023 | C10: =UPPER(TEXT(D10,"MMM")) -> MAY | D10: 45077 | E10: 9 | F10: 19 | G10: 9 | H10: Bogotá - Belencito | I10: CEMENTOS ARGOS | J10: 1/02/2023 - 13/03/2023 | K10: ARRIENDO BODEGA CON UNA ÁREA DE 2.234 M2 UBICADA EN KM5 | L10: 64206895 | M10: 10251521 | N10: =L10-M10 -> 53955374 | O10: =ROUND(N10*0.004,0) -> 215821 | P10: =N10-O10 -> 53739553 | U10: =+P10-Q10 -> 53739553
B11: =+YEAR(D11) -> 2023 | C11: =UPPER(TEXT(D11,"MMM")) -> MAY | D11: 45077 | E11: 10 | F11: 20 | G11: 10 | H11: Bogotá - Belencito | I11: CEMENTOS ARGOS | J11: 14/03/2023 - 30/03/2023 | K11: ARRIENDO BODEGA CON UNA ÁREA DE 2.234 M2 UBICADA EN KM5 | L11: 25384111 | M11: 4052925.3 | N11: =L11-M11 -> 21331186 | O11: =ROUND(N11*0.004,0) -> 85325 | P11: =N11-O11 -> 21245861 | U11: =+P11-Q11 -> 21245861
B12: =+YEAR(D12) -> 2023 | C12: =UPPER(TEXT(D12,"MMM")) -> MAY | D12: 45077 | E12: 11 | F12: 21 | G12: 11 | H12: Bogotá - Belencito | I12: CEMENTOS ARGOS | J12: 01/04/2023 - 30/04/2023 | K12: ARRIENDO BODEGA CON UNA ÁREA DE 2.234 M2 UBICADA EN KM5 | L12: 44795503 | M12: 7152223.2 | N12: =L12-M12 -> 37643280 | O12: =ROUND(N12*0.004,0) -> 150573 | P12: =N12-O12 -> 37492707 | U12: =+P12-Q12 -> 37492707
B13: =+YEAR(D13) -> 2023 | C13: =UPPER(TEXT(D13,"MMM")) -> MAY | D13: 45077 | E13: 12 | F13: 22 | G13: 12 | H13: Bogotá - Belencito | I13: CEMENTOS ARGOS | J13: 01/05/2023 - 31/05/2023 | K13: ARRIENDO BODEGA CON UNA ÁREA DE 2.234 M2 UBICADA EN KM5 | L13: 44795503 | M13: 7152223.2 | N13: =L13-M13 -> 37643280 | O13: =ROUND(N13*0.004,0) -> 150573 | P13: =N13-O13 -> 37492707 | U13: =+P13-Q13 -> 37492707
B14: =+YEAR(D14) -> 2023 | C14: =UPPER(TEXT(D14,"MMM")) -> JUN | D14: 45084 | E14: 16 | F14: NA | G14: NA | H14: Bogotá - Belencito | I14: CIRO | J14: 01/06/2023 - 30/06/2023 | K14: ARRIENDO DE BODEGA DE 72 M2, UBICADO EN KM 5 | L14: 1297511.7 | M14: 207165.74 | N14: =L14-M14 -> 1090346 | O14: =ROUND(N14*0.004,0) -> 4361 | P14: =N14-O14 -> 1085985 | Q14: 1085985 | R14: =+YEAR(T14) -> 2023 | S14: =+MONTH(T14) -> 7 | T14: 45135 | U14: =+P14-Q14 -> 0
B15: =+YEAR(D15) -> 2023 | C15: =UPPER(TEXT(D15,"MMM")) -> JUN | D15: 45084 | E15: 17 | F15: NA | G15: NA | H15: Bogotá - Belencito | I15: CEMENTOS ARGOS | J15: 01/06/2023 - 30/06/2023 | K15: ARRIENDO BODEGA CON UNA ÁREA DE 2.234 M2 UBICADA EN KM5 | L15: 44795503 | M15: 7152223.2 | N15: =L15-M15 -> 37643280 | O15: =ROUND(N15*0.004,0) -> 150573 | P15: =N15-O15 -> 37492707 | Q15: 37492707 | R15: 2023 | S15: 10 | T15: 45204 | U15: =+P15-Q15 -> 0.28
B16: =+YEAR(D16) -> 2023 | C16: =UPPER(TEXT(D16,"MMM")) -> JUN | D16: 45084 | E16: 17 | F16: NA | G16: NA | H16: Bogotá - Belencito | I16: CEMENTOS ARGOS | J16: 01/06/2023 - 30/06/2023 | K16: ARRIENDO BODEGA CON UNA ÁREA DE 2.234 M2 UBICADA EN KM6 | Q16: 0.28 | R16: 2023 | S16: 11 | T16: 45233 | U16: =P16-Q16 -> -0.28
B17: =+YEAR(D17) -> 2023 | C17: =UPPER(TEXT(D17,"MMM")) -> JUN | D17: 45103 | E17: 25 | F17: 8 | G17: 25 | H17: Bogotá - Belencito | I17: Fideicomiso Sociedad Fiduciaria de occidente | J17: 1/02/2023 - 13/03/2023 | K17: ARRIENDO DE BODEGA DE 128,2 M2, UBICADO EN KM 5 | L17: 4053414.9 | M17: 647183.89 | N17: =L17-M17 -> 3406231 | O17: =ROUND(N17*0.004,0) -> 13625 | P17: =N17-O17 -> 3392606 | U17: =+P17-Q17 -> 3392606 | V17: Como la factura 25 se anulo, se reemplaza por la factura 41
B18: =+YEAR(D18) -> 2023 | C18: =UPPER(TEXT(D18,"MMM")) -> JUN | D18: 45103 | E18: 26 | F18: 9 | G18: 26 | H18: Bogotá - Belencito | I18: Fideicomiso Sociedad Fiduciaria de occidente | J18: 14/03/2023 - 30/03/2023 | K18: ARRIENDO DE BODEGA DE 128,2 M2, UBICADO EN KM 5 | L18: 1602512.3 | M18: 255863.31 | N18: =L18-M18 -> 1346649 | O18: =ROUND(N18*0.004,0) -> 5387 | P18: =N18-O18 -> 1341262 | U18: =+P18-Q18 -> 1341262 | V18: Como la factura 26 se anulo, se reemplaza por la factura 42
B19: =+YEAR(D19) -> 2023 | C19: =UPPER(TEXT(D19,"MMM")) -> JUN | D19: 45103 | E19: 27 | F19: 10 | G19: 27 | H19: Bogotá - Belencito | I19: Fideicomiso Sociedad Fiduciaria de occidente | J19: 01/04/2023 - 30/04/2023 | K19: ARRIENDO DE BODEGA DE 128,2 M2, UBICADO EN KM 5 | L19: 2827963.6 | M19: 451523.6 | N19: =L19-M19 -> 2376440 | O19: =ROUND(N19*0.004,0) -> 9506 | P19: =N19-O19 -> 2366934 | U19: =+P19-Q19 -> 2366934 | V19: Como la factura 27 se anulo, se reemplaza por la factura 43
B20: =+YEAR(D20) -> 2023 | C20: =UPPER(TEXT(D20,"MMM")) -> JUN | D20: 45103 | E20: 28 | F20: NA | G20: NA | H20: Bogotá - Belencito | I20: Fideicomiso Sociedad Fiduciaria de occidente | J20: 01/05/2023 - 30/05/2023 | K20: ARRIENDO DE BODEGA DE 128,2 M2, UBICADO EN KM 5 | L20: 2827963.6 | M20: 451523.6 | N20: =+L20-M20 -> 2376440 | O20: =ROUND(N20*0.004,0) -> 9506 | P20: =N20-O20 -> 2366934 | U20: =+P20-Q20 -> 2366934 | V20: Como la factura 28 se anulo, se reemplaza por la factura 44
B21: =+YEAR(D21) -> 2023 | C21: =UPPER(TEXT(D21,"MMM")) -> JUN | D21: 45103 | E21: 29 | F21: NA | G21: NA | H21: Bogotá - Belencito | I21: Fideicomiso Sociedad Fiduciaria de occidente | J21: 01/06/2023 - 30/06/2023 | K21: ARRIENDO DE BODEGA DE 128,2 M2, UBICADO EN KM 5 | L21: 2827963.6 | M21: 451523.6 | N21: =+L21-M21 -> 2376440 | O21: =ROUND(N21*0.004,0) -> 9506 | P21: =N21-O21 -> 2366934 | U21: =+P21-Q21 -> 2366934 | V21: Como la factura 29 se anulo, se reemplaza por la factura 45
B22: =+YEAR(D22) -> 2023 | C22: =UPPER(TEXT(D22,"MMM")) -> JUL | D22: 45112 | E22: 31 | F22: NA | G22: NA | H22: Bogotá - Belencito | I22: CEMENTOS ARGOS | J22: 45125 | K22: ARRIENDO BODEGA CON UNA ÁREA DE 2.234 M2 UBICADA EN KM5 | L22: 44795503 | M22: 7152223.2 | N22: =L22-M22 -> 37643280 | O22: =ROUND(N22*0.004,0) -> 150573 | P22: =N22-O22 -> 37492707 | Q22: 37492707 | R22: 2023 | S22: 10 | T22: 45204 | U22: =+P22-Q22 -> 0.28
B23: =+YEAR(D23) -> 2023 | C23: =UPPER(TEXT(D23,"MMM")) -> JUL | D23: 45112 | E23: 31 | F23: NA | G23: NA | H23: Bogotá - Belencito | I23: CEMENTOS ARGOS | J23: 45125 | K23: ARRIENDO BODEGA CON UNA ÁREA DE 2.234 M2 UBICADA EN KM6 | Q23: 0.28 | R23: 2023 | S23: 11 | T23: 45233 | U23: =P23-Q23 -> -0.28
B24: =+YEAR(D24) -> 2023 | C24: =UPPER(TEXT(D24,"MMM")) -> JUL | D24: 45112 | E24: 32 | F24: NA | G24: NA | H24: Bogotá - Belencito | I24: CIRO | J24: 45130 | K24: ARRIENDO DE BODEGA DE 72 M2, UBICADO EN KM 5 | L24: 1297511.7 | M24: 207165.74 | N24: =+L24-M24 -> 1090346 | O24: =ROUND(N24*0.004,0) -> 4361 | P24: =N24-O24 -> 1085985 | Q24: 1085985 | R24: =+YEAR(T24) -> 2023 | S24: =+MONTH(T24) -> 7 | T24: 45135 | U24: =+P24-Q24 -> 0
B25: =+YEAR(D25) -> 2023 | C25: =UPPER(TEXT(D25,"MMM")) -> JUL | D25: 45108 | E25: Nota crédito No.2-8 del 28 de junio de 2023 | F25: 8 | G25: 25 | H25: Bogotá - Belencito | I25: Fideicomiso Sociedad Fiduciaria de occidente | J25: 1/02/2023 - 13/03/2023 | K25: Nota de Crédito No. 8 para anular factura 25 ARRIENDO DE BODEGA DE 128,2 M2, UBICADO EN KM 5 porque la legalización del contrato de arrendamiento se realizo en el periodo 1/02/2023 al 13/03/2023 | L25: -4053414.9 | M25: -647183.89 | N25: =L25-M25 -> -3406231 | O25: =ROUND(N25*0.004,0) -> -13625 | P25: =N25-O25 -> -3392606 | U25: =+P25-Q25 -> -3392606
B26: =+YEAR(D26) -> 2023 | C26: =UPPER(TEXT(D26,"MMM")) -> JUL | D26: 45108 | E26: Nota crédito No.2-9 del 28 de junio de 2023 | F26: 9 | G26: 26 | H26: Bogotá - Belencito | I26: Fideicomiso Sociedad Fiduciaria de occidente | J26: 14/03/2023 - 30/03/2023 | K26: Nota de Crédito No.9 para anular factura No. 26 ARRIENDO DE BODEGA DE 128,2 M2, UBICADO EN KM 5 porque la legalización del contrato de arrendamiento se realizo en el periodo del 14 al 30 marzo de 2023. | L26: -1602512.3 | M26: -255863.31 | N26: -1346649 | O26: =ROUND(N26*0.004,0) -> -5387 | P26: =N26-O26 -> -1341262 | U26: =+P26-Q26 -> -1341262
B27: =+YEAR(D27) -> 2023 | C27: =UPPER(TEXT(D27,"MMM")) -> JUL | D27: 45108 | E27: Nota crédito No.2-10 del 28 de junio de 2023 | F27: 10 | G27: 27 | H27: Bogotá - Belencito | I27: Fideicomiso Sociedad Fiduciaria de occidente | J27: 01/04/2023 - 30/04/2023 | K27: Nota Crédito No. 10 para analuar Factura 27. ARRIENDO DE BODEGA DE 128,2 M2, UBICADO EN KM 5 porque la legalización del contrato de arrendamiento se realizo en el mes de abril de 2023 | L27: -2827963.6 | M27: -451523.6 | N27: =+L27-M27 -> -2376440 | O27: =ROUND(N27*0.004,0) -> -9506 | P27: =N27-O27 -> -2366934 | U27: =+P27-Q27 -> -2366934
B28: =+YEAR(D28) -> 2023 | C28: =UPPER(TEXT(D28,"MMM")) -> JUL | D28: 45108 | E28: Nota credito No.2-11 del 28 de junio de 2023 | F28: 11 | G28: 28 | H28: Bogotá - Belencito | I28: Fideicomiso Sociedad Fiduciaria de occidente | J28: 01/05/2023 - 31/05/2023 | K28: Nota Crédito No, 11 para anular factura 28 ARRIENDO DE BODEGA DE 128,2 M2, UBICADO EN KM 5 porque la legalización del contrato de arrendamiento se realizo en el mes de mayo de 2023 | L28: -2827963.6 | M28: -451523.6 | N28: =L28-M28 -> -2376440 | O28: =ROUND(N28*0.004,0) -> -9506 | P28: =N28-O28 -> -2366934 | U28: =+P28-Q28 -> -2366934
B29: =+YEAR(D29) -> 2023 | C29: =UPPER(TEXT(D29,"MMM")) -> JUL | D29: 45108 | E29: Nota credito No.2-12 del 28 de junio de 2023 | F29: 12 | G29: 29 | H29: Bogotá - Belencito | I29: Fideicomiso Sociedad Fiduciaria de occidente | J29: 01/06/2023 - 30/06/2023 | K29: Nota Crédito No.12 para anular factura 29 ARRIENDO DE BODEGA DE 128,2 M2, UBICADO EN KM 5 porque la legalización del contrato de arrendamiento se realizo en el mes de junio de 2023 | L29: -2827963.6 | M29: -451523.6 | N29: =L29-M29 -> -2376440 | O29: =ROUND(N29*0.004,0) -> -9506 | P29: =N29-O29 -> -2366934 | U29: =+P29-Q29 -> -2366934
B30: 2023 | C30: =UPPER(TEXT(D30,"MMM")) -> JUL | D30: 45125 | E30: 41 | F30: NA | G30: NA | H30: Bogotá - Belencito | I30: Fideicomiso Sociedad Fiduciaria de occidente | J30: 1/02/2023 - 13/03/2023 | K30: ARRIENDO DE BODEGA DE 128,2 M2, UBICADO EN KM 5 | L30: 4053414.9 | M30: 647183.89 | N30: 3406231 | O30: =ROUND(N30*0.004,0) -> 13625 | P30: =N30-O30 -> 3392606 | Q30: 3392606 | R30: 2023 | S30: 8 | T30: 45168 | U30: =+P30-Q30 -> 0 | V30: La factura 19 y 25 son reemplazadas porla factura 41. Como se anularon las facturas 19 y 25, por lo cual se carga la consigancion a la factura 41
B31: 2023 | C31: =UPPER(TEXT(D31,"MMM")) -> JUL | D31: 45125 | E31: 42 | F31: NA | G31: NA | H31: Bogotá - Belencito | I31: Fideicomiso Sociedad Fiduciaria de occidente | J31: 14/03/2023 - 30/03/2023 | K31: ARRIENDO DE BODEGA DE 128,2 M2, UBICADO EN KM 5 | L31: 1602512.3 | M31: 255863.31 | N31: 1346649 | O31: =ROUND(N31*0.004,0) -> 5387 | P31: =N31-O31 -> 1341262 | Q31: 1341262 | R31: 2023 | S31: 8 | T31: 45168 | U31: =+P31-Q31 -> 0 | V31: La factura 20 y 26 son reemplazadas porla factura 42. Como se anularon las facturas 20 y 26, por lo cual se carga la consigancion a la factura 42
B32: 2023 | C32: =UPPER(TEXT(D32,"MMM")) -> JUL | D32: 45125 | E32: 43 | F32: NA | G32: NA | H32: Bogotá - Belencito | I32: Fideicomiso Sociedad Fiduciaria de occidente | J32: 01/04/2023 - 30/04/2023 | K32: ARRIENDO DE BODEGA DE 128,2 M2, UBICADO EN KM 5 | L32: 2827963.6 | M32: 451523.6 | N32: 2376440 | O32: =ROUND(N32*0.004,0) -> 9506 | P32: =N32-O32 -> 2366934 | Q32: 2366934 | R32: 2023 | S32: 8 | T32: 45168 | U32: =+P32-Q32 -> 0 | V32: La factura 21 y 27 son reemplazadas porla factura 43. Como se anularon las facturas 21 y 27, por lo cual se carga la consigancion a la factura 43
B33: 2023 | C33: =UPPER(TEXT(D33,"MMM")) -> JUL | D33: 45125 | E33: 44 | F33: NA | G33: NA | H33: Bogotá - Belencito | I33: Fideicomiso Sociedad Fiduciaria de occidente | J33: 01/05/2023 - 30/05/2023 | K33: ARRIENDO DE BODEGA DE 128,2 M2, UBICADO EN KM 5 | L33: 2827963.6 | M33: 451523.6 | N33: 2376440 | O33: =ROUND(N33*0.004,0) -> 9506 | P33: =N33-O33 -> 2366934 | Q33: 2366934 | R33: =+YEAR(T33) -> 2023 | S33: =+MONTH(T33) -> 8 | T33: 45168 | U33: =+P33-Q33 -> 0 | V33: La factura 22 y 28 son reemplazadas porla factura 44. Como se anularon las facturas 22 y 28, por lo cual se carga la consigancion a la factura 44
B34: 2023 | C34: =UPPER(TEXT(D34,"MMM")) -> JUL | D34: 45125 | E34: 45 | F34: NA | G34: NA | H34: Bogotá - Belencito | I34: Fideicomiso Sociedad Fiduciaria de occidente | J34: 01/06/2023 - 30/06/2023 | K34: ARRIENDO DE BODEGA DE 128,2 M2, UBICADO EN KM 5 | L34: 2827963.6 | M34: 451523.6 | N34: 2376440 | O34: =ROUND(N34*0.004,0) -> 9506 | P34: =N34-O34 -> 2366934 | Q34: 2366934 | R34: 2023 | S34: 8 | T34: 45168 | U34: =+P34-Q34 -> 0 | V34: La factura 18 y 29 son reemplazadas porla factura 45. Como se anularon las facturas 18 y 29, por lo cual se carga la consigancion a la factura 45
B35: =+YEAR(D35) -> 2023 | C35: =UPPER(TEXT(D35,"MMM")) -> JUL | D35: 45125 | E35: 46 | F35: NA | G35: NA | H35: Bogotá - Belencito | I35: Fideicomiso Sociedad Fiduciaria de occidente | J35: 1/07/2023 - 30/07/2023 | K35: ARRIENDO DE BODEGA DE 128,2 M2, UBICADO EN KM 5 | L35: 2827963.6 | M35: 451523.6 | N35: =L35-M35 -> 2376440 | O35: =ROUND(N35*0.004,0) -> 9506 | P35: =N35-O35 -> 2366934 | Q35: 2366934 | R35: =+YEAR(T35) -> 2023 | S35: =+MONTH(T35) -> 8 | T35: 45168 | U35: =+P35-Q35 -> 0
B36: =+YEAR(D36) -> 2023 | C36: =UPPER(TEXT(D36,"MMM")) -> JUL | D36: 45132 | E36: Nota credito No.2-19 | F36: 19 | G36: 9 | H36: Bogotá - Belencito | I36: CEMENTOS ARGOS | J36: 1/02/2023 - 13/03/2023 | K36: Nota Crédito No. 19 para anular factura 9 ARRIENDO BODEGA CON UNA AREA DE 2.234 M2 UBICADA EN KM5, porque la legalización del contrati de arrendamiento se realizo en el periodo 1/02/2023 al 13/03/2023 | L36: -64206895 | M36: -10251521 | N36: =L36-M36 -> -53955374 | O36: =ROUND(N36*0.004,0) -> -215821 | P36: =N36-O36 -> -53739553 | U36: =+P36-Q36 -> -53739553
B37: =+YEAR(D37) -> 2023 | C37: =UPPER(TEXT(D37,"MMM")) -> JUL | D37: 45132 | E37: Nota credito No.2-20 | F37: 20 | G37: 10 | H37: Bogotá - Belencito | I37: CEMENTOS ARGOS | J37: 14/03/2023 - 30/03/2023 | K37: Nota Crédicto No.20 para anular factura 10 ARRIENDO BODEGA CON UNA AREA DE 2.234 M2 UBICADA EN KM5, porque la legalización del contrati de arrendamiento se realizo en el mes de marzo de 2023 | L37: -25384111 | M37: -4052925.3 | N37: =L37-M37 -> -21331186 | O37: =ROUND(N37*0.004,0) -> -85325 | P37: =N37-O37 -> -21245861 | U37: =+P37-Q37 -> -21245861
B38: =+YEAR(D38) -> 2023 | C38: =UPPER(TEXT(D38,"MMM")) -> JUL | D38: 45132 | E38: Nota credito No.2-21 | F38: 21 | G38: 11 | H38: Bogotá - Belencito | I38: CEMENTOS ARGOS | J38: 01/04/2023 - 30/04/2023 | K38: Nota Crédito No.21 para anular factura 11 ARRIENDO BODEGA CON UNA AREA DE 2.234 M2 UBICADA EN KM5, porque la legalización del contrati de arrendamiento se realizo en el mes de abril de 2023 | L38: -44795503 | M38: -7152223.2 | N38: =L38-M38 -> -37643280 | O38: =ROUND(N38*0.004,0) -> -150573 | P38: =N38-O38 -> -37492707 | U38: =+P38-Q38 -> -37492707
B39: =+YEAR(D39) -> 2023 | C39: =UPPER(TEXT(D39,"MMM")) -> JUL | D39: 45132 | E39: Nota credito No.2-22 | F39: 22 | G39: 12 | H39: Bogotá - Belencito | I39: CEMENTOS ARGOS | J39: 01/05/2023 - 31/05/2023 | K39: Nota de Crédito No.22 para anular factura 12 ARRIENDO BODEGA CON UNA AREA DE 2.234 M2 UBICADA EN KM5, porque la legalización del contrati de arrendamiento se realizo en el mes de mayo de 2023 | L39: -44795503 | M39: -7152223.2 | N39: =L39-M39 -> -37643280 | O39: =ROUND(N39*0.004,0) -> -150573 | P39: =N39-O39 -> -37492707 | U39: =+P39-Q39 -> -37492707
B40: 2023 | C40: =UPPER(TEXT(D40,"MMM")) -> JUL | D40: 45132 | E40: 48 | F40: NA | G40: NA | H40: Bogotá - Belencito | I40: CEMENTOS ARGOS | J40: 1/02/2023 - 13/03/2023 | K40: ARRIENDO BODEGA CON UNA AREA DE 2.234 M2 UBICADA EN KM5 | L40: 64206895 | M40: 10251521 | N40: 53955374 | O40: =ROUND(N40*0.004,0) -> 215821 | P40: =N40-O40 -> 53739553 | Q40: 53739553 | R40: =+YEAR(T40) -> 2023 | S40: =+MONTH(T40) -> 8 | T40: 45168 | U40: =+P40-Q40 -> 0 | V40: Como se anulo la factura 9, por lo cual se carga la consigancion a la factura 48
B41: 2023 | C41: =UPPER(TEXT(D41,"MMM")) -> JUL | D41: 45132 | E41: 49 | F41: NA | G41: NA | H41: Bogotá - Belencito | I41: CEMENTOS ARGOS | J41: 14/03/2023 - 30/03/2023 | K41: ARRIENDO BODEGA CON UNA AREA DE 2.234 M2 UBICADA EN KM5 | L41: 25384111 | M41: 4052925.3 | N41: 21331186 | O41: =ROUND(N41*0.004,0) -> 85325 | P41: =N41-O41 -> 21245861 | Q41: 21245861 | R41: 2023 | S41: 8 | T41: 45168 | U41: =+P41-Q41 -> 0 | V41: Como se anulo la factura 10, por lo cual se carga la consigancion a la factura 49
B42: 2023 | C42: =UPPER(TEXT(D42,"MMM")) -> JUL | D42: 45132 | E42: 50 | F42: NA | G42: NA | H42: Bogotá - Belencito | I42: CEMENTOS ARGOS | J42: 01/04/2023 - 30/04/2023 | K42: ARRIENDO BODEGA CON UNA AREA DE 2.234 M2 UBICADA EN KM5 | L42: 44795503 | M42: 7152223.2 | N42: 37643280 | O42: =ROUND(N42*0.004,0) -> 150573 | P42: =N42-O42 -> 37492707 | Q42: 37492707 | R42: 2023 | S42: 8 | T42: 45168 | U42: =+P42-Q42 -> 0 | V42: Como se anulo la factura 11, por lo cual se carga la consigancion a la factura 50
B43: 2023 | C43: =UPPER(TEXT(D43,"MMM")) -> JUL | D43: 45132 | E43: 51 | F43: NA | G43: NA | H43: Bogotá - Belencito | I43: CEMENTOS ARGOS | J43: 01/05/2023 - 31/05/2023 | K43: ARRIENDO BODEGA CON UNA AREA DE 2.234 M2 UBICADA EN KM5 | L43: 44795503 | M43: 7152223.2 | N43: 37643280 | O43: =ROUND(N43*0.004,0) -> 150573 | P43: =N43-O43 -> 37492707 | Q43: 37492707 | R43: 2023 | S43: 8 | T43: 45168 | U43: =+P43-Q43 -> 0 | V43: Como se anulo la factura 12, por lo cual se carga la consigancion a la factura 51
B44: =+YEAR(D44) -> 2023 | C44: =UPPER(TEXT(D44,"MMM")) -> AGO | D44: 45152 | E44: 57 | F44: NA | G44: NA | H44: Bogotá - Belencito | I44: CIRO | J44: 01/08/2023 - 31/08/2023 | K44: ARRIENDO DE BODEGA DE 72 M2, UBICADO EN KM 5 | L44: 1297512 | M44: 207165.78 | N44: =+L44-M44 -> 1090346.2 | O44: =ROUND(N44*0.004,0) -> 4361 | P44: =N44-O44 -> 1085985.2 | Q44: 1085985 | R44: =+YEAR(T44) -> 2023 | S44: =+MONTH(T44) -> 8 | T44: 45168 | U44: =+P44-Q44 -> 0.22
B45: =+YEAR(D45) -> 2023 | C45: =UPPER(TEXT(D45,"MMM")) -> AGO | D45: 45152 | E45: 57 | F45: NA | G45: NA | H45: Bogotá - Belencito | I45: CIRO | J45: 01/08/2023 - 31/08/2023 | K45: ARRIENDO DE BODEGA DE 72 M2, UBICADO EN KM 6 | Q45: 0.22 | R45: =+YEAR(T45) -> 2023 | S45: 11 | T45: 45233 | U45: =P45-Q45 -> -0.22
B46: =+YEAR(D46) -> 2023 | C46: =UPPER(TEXT(D46,"MMM")) -> AGO | D46: 45152 | E46: 58 | F46: 28 | G46: 58 | H46: Bogotá - Belencito | I46: CEMENTOS ARGOS | J46: 01/08/2023 - 31/08/2023 | K46: ARRIENDO BODEGA CON UNA AREA DE 2.234 M2 UBICADA EN KM5 | L46: 44795251 | M46: 7152182.9 | N46: =L46-M46 -> 37643068 | O46: =ROUND(N46*0.004,0) -> 150572 | P46: =N46-O46 -> 37492496 | U46: =+P46-Q46 -> 37492496
B47: =+YEAR(D47) -> 2023 | C47: =UPPER(TEXT(D47,"MMM")) -> AGO | D47: 45152 | E47: 59 | F47: NA | G47: NA | H47: Bogotá - Belencito | I47: Fideicomiso Sociedad Fiduciaria de occidente | J47: 01/08/2023 - 31/08/2023 | K47: ARRIENDO DE BODEGA DE 128,2 M2, UBICADO EN KM 5 | L47: 2827964 | M47: 451523.66 | N47: =L47-M47 -> 2376440.3 | O47: =ROUND(N47*0.004,0) -> 9506 | P47: =N47-O47 -> 2366934.3 | Q47: 2366934.3 | R47: 2023 | S47: 10 | T47: 45204 | U47: =+P47-Q47 -> 0
B48: 2023 | C48: =UPPER(TEXT(D48,"MMM")) -> AGO | D48: 45139 | E48: Nota credito No.2-3 del 16 de junio de 2023 | F48: 3 | G48: 18 | H48: Bogotá - Belencito | I48: Fideicomiso Sociedad Fiduciaria de occidente | J48: 01/06/2023 - 30/06/2023 | K48: Nota de Credito No. 3 para anular factura 18 ARRIENDO DE BODEGA DE 128,2 M2, UBICADO EN KM 5 porque la legalización del contrato de arrendamiento se realizo en el mes de junio de 2023 | L48: -2827963.6 | M48: -451523.6 | N48: -2376440 | O48: =ROUND(N48*0.004,0) -> -9506 | P48: =N48-O48 -> -2366934 | U48: =+P48-Q48 -> -2366934 | V48: Por trazabillidad se incluye nota credito y factura anulada
B49: =+YEAR(D49) -> 2023 | C49: =UPPER(TEXT(D49,"MMM")) -> AGO | D49: 45139 | E49: 18 | F49: 3 | G49: 18 | H49: Bogotá - Belencito | I49: Fideicomiso Sociedad Fiduciaria de occidente | J49: 01/06/2023 - 30/06/2023 | K49: ARRIENDO DE BODEGA DE 128,2 M2, UBICADO EN KM 5 | L49: 2827963.6 | M49: 451523.6 | N49: =L49-M49 -> 2376440 | O49: =ROUND(N49*0.004,0) -> 9506 | P49: =N49-O49 -> 2366934 | U49: =+P49-Q49 -> 2366934 | V49: Como la factura 18 se anulo, se reemplaza por la factura 29
B50: 2023 | C50: =UPPER(TEXT(D50,"MMM")) -> AGO | D50: 45139 | E50: Nota credito No.2-4 del 16 de junio de 2023 | F50: 4 | G50: 19 | H50: Bogotá - Belencito | I50: Fideicomiso Sociedad Fiduciaria de occidente | J50: 1/02/2023 - 13/03/2023 | K50: Nota de Crédito No.4 para anular factura No. 19 ARRIENDO DE BODEGA DE 128,2 M2, UBICADO EN KM 5 porque la legalización del contrato de arrendamiento se realizo en el periodo 1/02/2023 al 13/03/2023 | L50: -4053414.9 | M50: -647183.89 | N50: -3406231 | O50: =ROUND(N50*0.004,0) -> -13625 | P50: =N50-O50 -> -3392606 | U50: =+P50-Q50 -> -3392606 | V50: Por trazabillidad se incluye nota credito y factura anulada
B51: =+YEAR(D51) -> 2023 | C51: =UPPER(TEXT(D51,"MMM")) -> AGO | D51: 45139 | E51: 19 | F51: 4 | G51: 19 | H51: Bogotá - Belencito | I51: Fideicomiso Sociedad Fiduciaria de occidente | J51: 1/02/2023 - 13/03/2023 | K51: ARRIENDO DE BODEGA DE 128,2 M2, UBICADO EN KM 5 | L51: 4053414.9 | M51: 647183.89 | N51: 3406231 | O51: =ROUND(N51*0.004,0) -> 13625 | P51: =N51-O51 -> 3392606 | U51: =+P51-Q51 -> 3392606 | V51: Como la factura 19 se anulo, se reemplaza por la factura 25
B52: 2023 | C52: =UPPER(TEXT(D52,"MMM")) -> AGO | D52: 45139 | E52: Nota credito No.2-5 del 16 de junio de 2023 | F52: 5 | G52: 20 | H52: Bogotá - Belencito | I52: Fideicomiso Sociedad Fiduciaria de occidente | J52: 14/03/2023 - 30/03/2023 | K52: Nota Crédito No. 5 para analuar Factura 20. ARRIENDO DE BODEGA DE 128,2 M2, UBICADO EN KM 5 porque la legalización del contrato de arrendamiento se realizo en el periodo del 14 al 30 marzo de 2023. | L52: -1602512.3 | M52: -255863.31 | N52: -1346649 | O52: =ROUND(N52*0.004,0) -> -5387 | P52: =N52-O52 -> -1341262 | U52: =+P52-Q52 -> -1341262 | V52: Por trazabillidad se incluye nota credito y factura anulada
B53: =+YEAR(D53) -> 2023 | C53: =UPPER(TEXT(D53,"MMM")) -> AGO | D53: 45139 | E53: 20 | F53: 5 | G53: 20 | H53: Bogotá - Belencito | I53: Fideicomiso Sociedad Fiduciaria de occidente | J53: 14/03/2023 - 30/03/2023 | K53: ARRIENDO DE BODEGA DE 128,2 M2, UBICADO EN KM 5 | L53: 1602512.3 | M53: 255863.31 | N53: 1346649 | O53: =ROUND(N53*0.004,0) -> 5387 | P53: =N53-O53 -> 1341262 | U53: =+P53-Q53 -> 1341262 | V53: Como la factura 20 se anulo, se reemplaza por la factura 26
B54: 2023 | C54: =UPPER(TEXT(D54,"MMM")) -> AGO | D54: 45139 | E54: Nota credito No.2-6 del 16 de junio de 2023 | F54: 6 | G54: 21 | H54: Bogotá - Belencito | I54: Fideicomiso Sociedad Fiduciaria de occidente | J54: 01/04/2023 - 30/04/2023 | K54: Nota Crédito No, 6 para anular factura 21 ARRIENDO DE BODEGA DE 128,2 M2, UBICADO EN KM 5 porque la legalización del contrato de arrendamiento se realizo en el mes de abril de 2023 | L54: -2827963.6 | M54: -451523.6 | N54: -2376440 | O54: =ROUND(N54*0.004,0) -> -9506 | P54: =N54-O54 -> -2366934 | U54: =+P54-Q54 -> -2366934 | V54: Por trazabillidad se incluye nota credito y factura anulada
B55: =+YEAR(D55) -> 2023 | C55: =UPPER(TEXT(D55,"MMM")) -> AGO | D55: 45139 | E55: 21 | F55: 6 | G55: 21 | H55: Bogotá - Belencito | I55: Fideicomiso Sociedad Fiduciaria de occidente | J55: 01/04/2023 - 30/04/2023 | K55: ARRIENDO DE BODEGA DE 128,2 M2, UBICADO EN KM 5 | L55: 2827963.6 | M55: 451523.6 | N55: 2376440 | O55: =ROUND(N55*0.004,0) -> 9506 | P55: =N55-O55 -> 2366934 | U55: =+P55-Q55 -> 2366934 | V55: Como la factura 21 se anulo, se reemplaza por la factura 27
B56: 2023 | C56: =UPPER(TEXT(D56,"MMM")) -> AGO | D56: 45139 | E56: Nota credito No.2-7 del 16 de junio de 2023 | F56: 7 | G56: 22 | H56: Bogotá - Belencito | I56: Fideicomiso Sociedad Fiduciaria de occidente | J56: 01/05/2023 - 30/05/2023 | K56: Nota Crédito No.7 para anular factura 22 ARRIENDO DE BODEGA DE 128,2 M2, UBICADO EN KM 5 porque la legalización del contrato de arrendamiento se realizo en el mes de mayo de 2023 | L56: -2827963.6 | M56: -451523.6 | N56: -2376440 | O56: =ROUND(N56*0.004,0) -> -9506 | P56: =N56-O56 -> -2366934 | U56: =+P56-Q56 -> -2366934 | V56: Por trazabillidad se incluye nota credito y factura anulada
B57: =+YEAR(D57) -> 2023 | C57: =UPPER(TEXT(D57,"MMM")) -> AGO | D57: 45139 | E57: 22 | F57: 7 | G57: 22 | H57: Bogotá - Belencito | I57: Fideicomiso Sociedad Fiduciaria de occidente | J57: 01/05/2023 - 30/05/2023 | K57: ARRIENDO DE BODEGA DE 128,2 M2, UBICADO EN KM 5 | L57: 2827963.6 | M57: 451523.6 | N57: =+L57-M57 -> 2376440 | O57: =ROUND(N57*0.004,0) -> 9506 | P57: =N57-O57 -> 2366934 | U57: =+P57-Q57 -> 2366934 | V57: Como la factura 22 se anulo, se reemplaza por la factura 28
B58: =+YEAR(D58) -> 2023 | C58: =UPPER(TEXT(D58,"MMM")) -> SEP | D58: 45175 | E58: 64 | F58: NA | G58: NA | H58: Bogotá - Belencito | I58: CEMENTOS ARGOS | J58: 01/09/2023 - 30/09/2023 | K58: ARRIENDO BODEGA CON UNA AREA DE 2.234 M2 UBICADA EN KM5 | L58: 44795251 | M58: 7152182.9 | N58: =L58-M58 -> 37643068 | O58: =ROUND(N58*0.004,0) -> 150572 | P58: =N58-O58 -> 37492496 | U58: =+P58-Q58 -> 37492496
B59: =+YEAR(D59) -> 2023 | C59: =UPPER(TEXT(D59,"MMM")) -> SEP | D59: 45174 | E59: 68 | F59: NA | G59: NA | H59: Bogotá - Belencito | I59: Fideicomiso Sociedad Fiduciaria de occidente | J59: 01/09/2023 - 30/09/2023 | K59: ARRIENDO DE BODEGA DE 128,2 M2, UBICADO EN KM 5 | L59: 2827964 | M59: 451523.66 | N59: =L59-M59 -> 2376440.3 | O59: =ROUND(N59*0.004,0) -> 9506 | P59: =N59-O59 -> 2366934.3 | Q59: 2366934.3 | R59: 2023 | S59: 10 | T59: 45204 | U59: =+P59-Q59 -> 0
B60: =+YEAR(D60) -> 2023 | C60: =UPPER(TEXT(D60,"MMM")) -> SEP | D60: 45174 | E60: 69 | F60: NA | G60: NA | H60: Bogotá - Belencito | I60: CIRO | J60: 01/09/2023 - 30/09/2023 | K60: ARRIENDO DE BODEGA DE 72 M2, UBICADO EN KM 5 | L60: 1297512 | M60: 207165.78 | N60: =+L60-M60 -> 1090346.2 | O60: =ROUND(N60*0.004,0) -> 4361 | P60: =N60-O60 -> 1085985.2 | Q60: 1085985.2 | R60: 2023 | S60: 10 | T60: 45204 | U60: =+P60-Q60 -> 0
B61: =+YEAR(D61) -> 2023 | C61: =UPPER(TEXT(D61,"MMM")) -> OCT | D61: 45225 | E61: Nota credito No.2-29 | F61: 29 | G61: 58 | H61: Bogotá - Belencito | I61: CEMENTOS ARGOS | J61: 1/08/2023-30/08/2023 | K61: Nota de credito 29 para anular la factura 58 para el ARRIENDO BODEGA CON UNA AREA DE 2.234 M2 UBICADA EN KM5 porque Argos no la recibio en el sistema. | L61: -44795251 | M61: -7152182.9 | N61: =+L61-M61 -> -37643068 | O61: =ROUND(N61*0.004,0) -> -150572 | P61: =N61-O61 -> -37492496 | U61: =+P61-Q61 -> -37492496 | V61: Como la factura 58 se anulo, se reemplaza por la factura 88
B62: =+YEAR(D62) -> 2023 | C62: =UPPER(TEXT(D62,"MMM")) -> OCT | D62: 45225 | E62: Nota credito No.2-30 | F62: 30 | G62: 64 | H62: Bogotá - Belencito | I62: CEMENTOS ARGOS | J62: 1/09/2023-30/09/2023 | K62: Nota de credito 30 para anular la factura 64 para el ARRIENDO BODEGA CON UNA AREA DE 2.234 M2 UBICADA EN KM6 porque Argos la rechazo en el sistema. | L62: -44795251 | M62: -7152182.9 | N62: =+L62-M62 -> -37643068 | O62: =ROUND(N62*0.004,0) -> -150572 | P62: =N62-O62 -> -37492496 | U62: =+P62-Q62 -> -37492496 | V62: Como la factura 64 se anulo, se reemplaza por la factura 89
B63: =+YEAR(D63) -> 2023 | C63: =UPPER(TEXT(D63,"MMM")) -> OCT | D63: 45225 | E63: 88 | F63: NA | G63: NA | H63: Bogotá - Belencito | I63: CEMENTOS ARGOS | J63: 1/08/2023-30/08/2023 | K63: ARRIENDO BODEGA CON UNA AREA DE 2.234 M2 UBICADA EN KM5 | L63: 44795251 | M63: 7152182.9 | N63: =+L63-M63 -> 37643068 | O63: =ROUND(N63*0.004,0) -> 150572 | P63: =N63-O63 -> 37492496 | Q63: 37492496 | R63: =+YEAR(T63) -> 2023 | S63: 11 | T63: 45233 | U63: =+P63-Q63 -> 0
B64: =+YEAR(D64) -> 2023 | C64: =UPPER(TEXT(D64,"MMM")) -> OCT | D64: 45225 | E64: 89 | F64: NA | G64: NA | H64: Bogotá - Belencito | I64: CEMENTOS ARGOS | J64: 1/09/2023-30/09/2023 | K64: ARRIENDO BODEGA CON UNA AREA DE 2.234 M2 UBICADA EN KM5 | L64: 44795251 | M64: 7152182.9 | N64: =+L64-M64 -> 37643068 | O64: =ROUND(N64*0.004,0) -> 150572 | P64: =N64-O64 -> 37492496 | Q64: 37492496 | R64: 2023 | S64: 11 | T64: 45260 | U64: =+P64-Q64 -> 0
B65: 2023 | C65: =UPPER(TEXT(D65,"MMM")) -> OCT | D65: 45202 | E65: 76 | F65: NA | G65: NA | H65: Bogotá - Belencito | I65: CEMENTOS ARGOS | J65: 01/10/2023 - 30/10/2023 | K65: ARRIENDO BODEGA CON UNA AREA DE 2.234 M2 UBICADA EN KM5 | L65: 44795251 | M65: 7152182.9 | N65: =+L65-M65 -> 37643068 | O65: =ROUND(N65*0.004,0) -> 150572 | P65: =N65-O65 -> 37492496 | Q65: 37492496 | R65: =+YEAR(T65) -> 2023 | S65: 11 | T65: 45233 | U65: =+P65-Q65 -> 0
B66: 2023 | C66: =UPPER(TEXT(D66,"MMM")) -> OCT | D66: 45202 | E66: 78 | F66: NA | G66: NA | H66: Bogotá - Belencito | I66: Fideicomiso Sociedad Fiduciaria de occidente | J66: 01/10/2023 - 30/10/2023 | K66: ARRIENDO DE BODEGA DE 128,2 M2, UBICADO EN KM 5 | L66: 2827964 | M66: 451523.66 | N66: =+L66-M66 -> 2376440.3 | O66: =ROUND(N66*0.004,0) -> 9506 | P66: =N66-O66 -> 2366934.3 | Q66: 2366934.3 | R66: =+YEAR(T66) -> 2023 | S66: 11 | T66: 45233 | U66: =+P66-Q66 -> 0
B67: 2023 | C67: =UPPER(TEXT(D67,"MMM")) -> OCT | D67: 45219 | E67: 86 | F67: NA | G67: NA | H67: Bogotá - Belencito | I67: CIRO | J67: 01/10/2023 - 30/10/2023 | K67: ARRIENDO DE BODEGA DE 72 M2, UBICADO EN KM 5 | L67: 1297512 | M67: 207165.78 | N67: =+L67-M67 -> 1090346.2 | O67: =ROUND(N67*0.004,0) -> 4361 | P67: =N67-O67 -> 1085985.2 | Q67: 1085985.2 | R67: =+YEAR(T67) -> 2023 | S67: 11 | T67: 45233 | U67: =+P67-Q67 -> 0
B68: 2023 | C68: =UPPER(TEXT(D68,"MMM")) -> NOV | D68: 45246 | E68: 95 | F68: NA | G68: NA | H68: Bogotá - Belencito | I68: CEMENTOS ARGOS | J68: 01/11/2023 - 30/11/2023 | K68: ARRIENDO BODEGA CON UNA AREA DE 1,117 M2 UBICADA EN KM5 | L68: 26877150 | M68: 4291309.7 | N68: =+L68-M68 -> 22585840 | O68: =ROUND(N68*0.004,0) -> 90343 | P68: =N68-O68 -> 22495497 | U68: =P68-Q68 -> 22495497
B69: 2023 | C69: =UPPER(TEXT(D69,"MMM")) -> NOV | D69: 45246 | E69: 94 | F69: NA | G69: NA | H69: Bogotá - Belencito | I69: Fideicomiso Sociedad Fiduciaria de occidente | J69: 01/11/2023 - 30/11/2023 | K69: ARRIENDO DE BODEGA DE 128,2 M2, UBICADO EN KM 5 | L69: 2827964 | M69: 451523.66 | N69: =+L69-M69 -> 2376440.3 | O69: =ROUND(N69*0.004,0) -> 9506 | P69: =N69-O69 -> 2366934.3 | U69: =P69-Q69 -> 2366934.3
B70: 2023 | C70: =UPPER(TEXT(D70,"MMM")) -> NOV | D70: 45246 | E70: 93 | F70: NA | G70: NA | H70: Bogotá - Belencito | I70: CIRO | J70: 01/11/2023 - 30/11/2023 | K70: ARRIENDO DE BODEGA DE 72 M2, UBICADO EN KM 5 | L70: 1297512 | M70: 207165.78 | N70: =+L70-M70 -> 1090346.2 | O70: =ROUND(N70*0.004,0) -> 4361 | P70: =N70-O70 -> 1085985.2 | U70: =P70-Q70 -> 1085985.2
B71: 2023 | C71: =UPPER(TEXT(D71,"MMM")) -> DIC | D71: 45265 | E71: Nota credito No 2-34 | F71: 34 | G71: 93 | H71: Bogotá - Belencito | I71: CIRO | J71: 01/11/2023 - 30/11/2023 | K71: ARRIENDO DE BODEGA DE 72 M2, UBICADO EN KM 5 | L71: -1297512 | M71: -207165.78 | N71: =+L71-M71 -> -1090346.2 | O71: =ROUND(N71*0.004,0) -> -4361 | P71: =N71-O71 -> -1085985.2 | U71: =P71 -> -1085985.2 | V71: Como la factura 93 se anulo, se reemplaza por la factura 115
B72: 2023 | C72: =UPPER(TEXT(D72,"MMM")) -> DIC | D72: 45265 | E72: Nota credito No 2-35 | F72: 35 | G72: 94 | H72: Bogotá - Belencito | I72: Fideicomiso Sociedad Fiduciaria de occidente | J72: 01/11/2023 - 30/11/2023 | K72: ARRIENDO DE BODEGA DE 128,2 M2, UBICADO EN KM 5 | L72: -2827964 | M72: -451523.66 | N72: -2376440.3 | O72: =ROUND(N72*0.004,0) -> -9506 | P72: =N72-O72 -> -2366934.3 | U72: =P72 -> -2366934.3 | V72: Como la factura 94 se anulo, se reemplaza por la factura 114
B73: 2023 | C73: =UPPER(TEXT(D73,"MMM")) -> DIC | D73: 45265 | E73: 115 | F73: NA | G73: NA | H73: Bogotá - Belencito | I73: CIRO | J73: 01/11/2023 - 30/11/2023 | K73: ARRIENDO DE BODEGA DE 72 M2, UBICADO EN KM 5 | L73: 1297512 | M73: 207165.78 | N73: =+L73-M73 -> 1090346.2 | O73: =ROUND(N73*0.004,0) -> 4361 | P73: =N73-O73 -> 1085985.2 | Q73: 1085985.2 | R73: 2024 | S73: 1 | T73: 45322 | U73: =P73-Q73 -> 0
B74: 2023 | C74: =UPPER(TEXT(D74,"MMM")) -> DIC | D74: 45265 | E74: 114 | F74: NA | G74: NA | H74: Bogotá - Belencito | I74: Fideicomiso Sociedad Fiduciaria de occidente | J74: 01/11/2023 - 30/11/2023 | K74: ARRIENDO DE BODEGA DE 128,2 M2, UBICADO EN KM 5 | L74: 2827964 | M74: 451523.66 | N74: =+L74-M74 -> 2376440.3 | O74: =ROUND(N74*0.004,0) -> 9506 | P74: =N74-O74 -> 2366934.3 | Q74: 2366934.3 | R74: 2024 | S74: 1 | T74: 45322 | U74: =P74-Q74 -> 0
B75: 2023 | C75: =UPPER(TEXT(D75,"MMM")) -> DIC | D75: 45265 | E75: 110 | F75: NA | G75: NA | H75: Bogotá - Belencito | I75: CEMENTOS ARGOS | J75: 01/12/2023 - 31/12/2023 | K75: ARRIENDO BODEGA CON UNA AREA DE 1,117 M2 UBICADA EN KM5 | L75: 26877150 | M75: 4291309.7 | N75: =+L75-M75 -> 22585840 | O75: =ROUND(N75*0.004,0) -> 90343 | P75: =N75-O75 -> 22495497 | Q75: 22495497 | R75: 2024 | S75: 1 | T75: 45322 | U75: =P75-Q75 -> 0
B76: 2023 | C76: =UPPER(TEXT(D76,"MMM")) -> DIC | D76: 45265 | E76: 111 | F76: NA | G76: NA | H76: Bogotá - Belencito | I76: Fideicomiso Sociedad Fiduciaria de occidente | J76: 01/12/2023 - 31/12/2023 | K76: ARRIENDO DE BODEGA DE 128,2 M2, UBICADO EN KM 5 | L76: 2827964 | M76: 451523.66 | N76: =+L76-M76 -> 2376440.3 | O76: =ROUND(N76*0.004,0) -> 9506 | P76: =N76-O76 -> 2366934.3 | Q76: 2366934.3 | R76: 2024 | S76: 1 | T76: 45322 | U76: =P76-Q76 -> 0
B77: 2023 | C77: =UPPER(TEXT(D77,"MMM")) -> DIC | D77: 45265 | E77: 113 | F77: NA | G77: NA | H77: Bogotá - Belencito | I77: Fideicomiso Sociedad Fiduciaria de occidente | J77: 01/12/2023 - 31/12/2023 | K77: ARRIENDDO AREA 500 M2 UNBICADA EN EL KM5 | L77: 4760000 | M77: 760000 | N77: =+L77-M77 -> 4000000 | O77: =ROUND(N77*0.004,0) -> 16000 | P77: =N77-O77 -> 3984000 | Q77: 3984000 | R77: 2024 | S77: 1 | T77: 45322 | U77: =P77-Q77 -> 0
B78: 2023 | C78: =UPPER(TEXT(D78,"MMM")) -> DIC | D78: 45287 | E78: Nota credito No 2-39 | F78: 39 | G78: 95 | H78: Bogotá - Belencito | I78: CEMENTOS ARGOS | J78: 01/11/2023 - 30/11/2023 | K78: ARRIENDO BODEGA CON UNA AREA DE 1,117 M2 UBICADA EN KM5 | L78: -26877150 | M78: -4291309.7 | N78: =+L78-M78 -> -22585840 | O78: =ROUND(N78*0.004,0) -> -90343 | P78: =N78-O78 -> -22495497 | U78: =P78-Q78 -> -22495497 | V78: Como la factura 95 se anulo, se reemplaza por la factura 123
B79: 2023 | C79: =UPPER(TEXT(D79,"MMM")) -> DIC | D79: 45287 | E79: 123 | F79: NA | G79: NA | H79: Bogotá - Belencito | I79: CEMENTOS ARGOS | J79: 01/11/2023 - 30/11/2023 | K79: ARRIENDO BODEGA CON UNA AREA DE 1,117 M2 UBICADA EN KM5 | L79: 26877150 | M79: 4291309.7 | N79: =+L79-M79 -> 22585840 | O79: =ROUND(N79*0.004,0) -> 90343 | P79: =N79-O79 -> 22495497 | Q79: 22495497 | R79: 2024 | S79: 1 | T79: 45322 | U79: =P79-Q79 -> 0
B80: 2024 | C80: =UPPER(TEXT(D80,"MMM")) -> ENE | D80: 45296 | E80: 133 | F80: NA | G80: NA | H80: Bogotá - Belencito | I80: CEMENTOS ARGOS | J80: 01/1/2024- 31/1/2024 | K80: ARRIENDO BODEGA CON UNA AREA DE 1,117 M2 UBICADA EN KM5 | L80: 26877150 | M80: 4291309.7 | N80: =+L80-M80 -> 22585840 | O80: =ROUND(N80*0.004,0) -> 90343 | P80: =N80-O80 -> 22495497 | Q80: 22495497 | R80: 2024 | S80: 1 | T80: 45322 | U80: =P80-Q80 -> 0
B81: 2024 | C81: =UPPER(TEXT(D81,"MMM")) -> ENE | D81: 45296 | E81: 134 | F81: NA | G81: NA | H81: Bogotá - Belencito | I81: Fideicomiso Sociedad Fiduciaria de occidente | J81: 01/1/2024- 31/1/2024 | K81: ARRIENDO DE BODEGA DE 128,2 M2, UBICADO EN KM 5 | L81: 2827964 | M81: 451523.66 | N81: =+L81-M81 -> 2376440.3 | O81: =ROUND(N81*0.004,0) -> 9506 | P81: =N81-O81 -> 2366934.3 | Q81: 2366934.3 | R81: 2024 | S81: 2 | T81: 45348 | U81: =P81-Q81 -> 0
B82: 2024 | C82: =UPPER(TEXT(D82,"MMM")) -> ENE | D82: 45296 | E82: 135 | F82: NA | G82: NA | H82: Bogotá - Belencito | I82: Fideicomiso Sociedad Fiduciaria de occidente | J82: 01/1/2024- 31/1/2024 | K82: ARRIENDO DE AREA DE 500 M2, UBICADA EN EL KM5 | L82: 4760000 | M82: 760000 | N82: =+L82-M82 -> 4000000 | O82: =ROUND(N82*0.004,0) -> 16000 | P82: =N82-O82 -> 3984000 | Q82: 3984000 | R82: 2024 | S82: 2 | T82: 45348 | U82: =P82-Q82 -> 0
B83: 2024 | C83: =UPPER(TEXT(D83,"MMM")) -> ENE | D83: 45296 | E83: 136 | F83: NA | G83: NA | H83: Bogotá - Belencito | I83: Fideicomiso Sociedad Fiduciaria de occidente | J83: 01/1/2024- 31/1/2024 | K83: ARRIENDO DE ESPACIO DE 241.42 M2, UBICADA EN EL KM5 | L83: 5325504 | M83: 850290.56 | N83: =+L83-M83 -> 4475213.4 | O83: =ROUND(N83*0.004,0) -> 17901 | P83: =N83-O83 -> 4457312.4 | Q83: 4457312.5 | R83: 2024 | S83: 2 | T83: 45348 | U83: =P83-Q83 -> 0
B84: 2024 | C84: =UPPER(TEXT(D84,"MMM")) -> ENE | D84: 45315 | E84: 140 | F84: NA | G84: NA | H84: Bogotá - Belencito | I84: Turistren | J84: 01/1/2024- 31/1/2024 | K84: ARRIENDO ESPACIO CUBIERTO AL INTERIOR DEL NUEVO TALLER ANI, UBICADO EN LAS INSTALACIONES DEL KILÓMETRO 5, CON UN AREA DE 1.986.8 METROS CUADRADOS | L84: 40192964 | M84: 6417364 | N84: =+L84-M84 -> 33775600 | O84: =ROUND(N84*0.004,0) -> 135102 | P84: =N84-O84 -> 33640498 | Q84: 33640498 | R84: 2024 | S84: 2 | T84: 45349 | U84: =P84-Q84 -> 0
B85: 2024 | C85: =UPPER(TEXT(D85,"MMM")) -> FEB | D85: 45327 | E85: 148 | F85: NA | G85: NA | H85: Bogotá - Belencito | I85: Turistren | J85: 01/2/2024- 29/2/2024 | K85: ARRIENDO ESPACIO CUBIERTO AL INTERIOR DEL NUEVO TALLER ANI, UBICADO EN LAS INSTALACIONES DEL KILÓMETRO 5, CON UN AREA DE 1.986.8 METROS CUADRADOS | L85: 40192964 | M85: 6417364 | N85: =+L85-M85 -> 33775600 | O85: =ROUND(N85*0.004,0) -> 135102 | P85: =N85-O85 -> 33640498 | Q85: 33640498 | R85: 2024 | S85: 2 | T85: 45349 | U85: =P85-Q85 -> 0
B86: 2024 | C86: =UPPER(TEXT(D86,"MMM")) -> FEB | D86: 45327 | E86: 149 | F86: NA | G86: NA | H86: Bogotá - Belencito | I86: Fideicomiso Sociedad Fiduciaria de occidente | J86: 01/2/2024- 29/2/2024 | K86: ARRIENDO DE BODEGA DE 128,2 M2, UBICADO EN KM 5 | L86: 2827964 | M86: 451523.66 | N86: =+L86-M86 -> 2376440.3 | O86: =ROUND(N86*0.004,0) -> 9506 | P86: =N86-O86 -> 2366934.3 | Q86: 2366934.3 | R86: 2024 | S86: 4 | T86: 45383 | U86: =P86-Q86 -> 0
B87: 2024 | C87: =UPPER(TEXT(D87,"MMM")) -> FEB | D87: 45327 | E87: 150 | F87: NA | G87: NA | H87: Bogotá - Belencito | I87: Fideicomiso Sociedad Fiduciaria de occidente | J87: 01/2/2024- 29/2/2024 | K87: ARRIENDO DE AREA DE 500 M2, UBICADA EN EL KM5 | L87: 4760000 | M87: 760000 | N87: =+L87-M87 -> 4000000 | O87: =ROUND(N87*0.004,0) -> 16000 | P87: =N87-O87 -> 3984000 | U87: =P87-Q87 -> 3984000 | V87: Como la factura 150 se anulo, se reemplaza por la factura 211
B88: 2024 | C88: =UPPER(TEXT(D88,"MMM")) -> FEB | D88: 45327 | E88: 151 | F88: NA | G88: NA | H88: Bogotá - Belencito | I88: Fideicomiso Sociedad Fiduciaria de occidente | J88: 01/2/2024- 29/2/2024 | K88: ARRIENDO DE ESPACIO DE 241.42 M2, UBICADA EN EL KM5 | L88: 5325504 | M88: 850290.56 | N88: =+L88-M88 -> 4475213.4 | O88: =ROUND(N88*0.004,0) -> 17901 | P88: =N88-O88 -> 4457312.4 | Q88: 4457312.5 | R88: 2024 | S88: 4 | T88: 45383 | U88: =P88-Q88 -> 0
B89: 2024 | C89: =UPPER(TEXT(D89,"MMM")) -> FEB | D89: 45348 | E89: 163 | F89: NA | G89: NA | H89: Bogotá - Belencito | I89: CEMENTOS ARGOS | J89: 01/2/2024- 29/2/2024 | K89: ARRIENDO BODEGA CON UNA AREA DE 1,117 M2 UBICADA EN KM5 | L89: 26877150 | M89: 4291309.7 | N89: =+L89-M89 -> 22585840 | O89: =ROUND(N89*0.004,0) -> 90343 | P89: =N89-O89 -> 22495497 | Q89: 22495497 | R89: 2024 | S89: 4 | T89: 45383 | U89: =P89-Q89 -> 0
B90: 2024 | C90: =UPPER(TEXT(D90,"MMM")) -> MAR | D90: 45366 | E90: 170 | F90: NA | G90: NA | H90: Bogotá - Belencito | I90: CEMENTOS ARGOS | J90: 01/3/2024- 31/3/2024 | K90: ARRIENDO BODEGA CON UNA AREA DE 1,117 M2 UBICADA EN KM5 | L90: 26877150 | M90: 4291309.7 | N90: =+L90-M90 -> 22585840 | O90: =ROUND(N90*0.004,0) -> 90343 | P90: =N90-O90 -> 22495497 | Q90: 22495497 | R90: 2024 | S90: 4 | T90: 45412 | U90: =P90-Q90 -> 0
B91: 2024 | C91: =UPPER(TEXT(D91,"MMM")) -> MAR | D91: 45366 | E91: 171 | F91: NA | G91: NA | H91: Bogotá - Belencito | I91: Turistren | J91: 01/3/2024- 31/3/2024 | K91: ARRIENDO ESPACIO CUBIERTO AL INTERIOR DEL NUEVO TALLER ANI, UBICADO EN LAS INSTALACIONES DEL KILÓMETRO 5, CON UN AREA DE 1.986.8 METROS CUADRADOS | L91: 40192964 | M91: 6417364 | N91: =+L91-M91 -> 33775600 | O91: =ROUND(N91*0.004,0) -> 135102 | P91: =N91-O91 -> 33640498 | Q91: 33640498 | R91: 2024 | S91: 4 | T91: 45412 | U91: =P91-Q91 -> 0
B92: 2024 | C92: =UPPER(TEXT(D92,"MMM")) -> MAR | D92: 45366 | E92: 172 | F92: NA | G92: NA | H92: Bogotá - Belencito | I92: Fideicomiso Sociedad Fiduciaria de occidente | J92: 01/3/2024- 31/3/2024 | K92: ARRIENDO DE BODEGA DE 128,2 M2, UBICADO EN KM 5 | L92: 2827964 | M92: 451523.66 | N92: =+L92-M92 -> 2376440.3 | O92: =ROUND(N92*0.004,0) -> 9506 | P92: =N92-O92 -> 2366934.3 | Q92: =Tabla1[[#This Row],[Valor a Consignar a la ANI]] -> 2366934.3 | R92: 2024 | S92: 5 | T92: 45440 | U92: =P92-Q92 -> 0
B93: 2024 | C93: =UPPER(TEXT(D93,"MMM")) -> MAR | D93: 45366 | E93: 173 | F93: NA | G93: NA | H93: Bogotá - Belencito | I93: Fideicomiso Sociedad Fiduciaria de occidente | J93: 01/3/2024- 31/3/2024 | K93: ARRIENDO DE AREA DE 500 M2, UBICADA EN EL KM5 | L93: 4760000 | M93: 760000 | N93: =+L93-M93 -> 4000000 | O93: =ROUND(N93*0.004,0) -> 16000 | P93: =N93-O93 -> 3984000 | U93: =P93-Q93 -> 3984000 | V93: Como la factura 173 se anulo, se reemplaza por la factura 212
B94: 2024 | C94: =UPPER(TEXT(D94,"MMM")) -> MAR | D94: 45366 | E94: 174 | F94: NA | G94: NA | H94: Bogotá - Belencito | I94: Fideicomiso Sociedad Fiduciaria de occidente | J94: 01/3/2024- 31/3/2024 | K94: ARRIENDO DE ESPACIO DE 241.42 M2, UBICADA EN EL KM5 | L94: 5325504 | M94: 850290.56 | N94: =+L94-M94 -> 4475213.4 | O94: =ROUND(N94*0.004,0) -> 17901 | P94: =N94-O94 -> 4457312.4 | Q94: =Tabla1[[#This Row],[Valor a Consignar a la ANI]] -> 4457312.4 | R94: 2024 | S94: 5 | T94: 45440 | U94: =P94-Q94 -> 0
B95: 2024 | C95: =UPPER(TEXT(D95,"MMM")) -> ABR | D95: 45391 | E95: 184 | F95: NA | G95: NA | H95: Bogotá - Belencito | I95: CEMENTOS ARGOS | J95: 01/4/2024- 30/4/2024 | K95: ARRIENDO BODEGA CON UNA AREA DE 1,117 M2 UBICADA EN KM5 | L95: 26877150 | M95: 4291309.7 | N95: =+L95-M95 -> 22585840 | O95: =ROUND(N95*0.004,0) -> 90343 | P95: =N95-O95 -> 22495497 | Q95: =Tabla1[[#This Row],[Valor a Consignar a la ANI]] -> 22495497 | R95: 2024 | S95: 5 | T95: 45440 | U95: =P95-Q95 -> 0
B96: 2024 | C96: =UPPER(TEXT(D96,"MMM")) -> ABR | D96: 45391 | E96: 185 | F96: NA | G96: NA | H96: Bogotá - Belencito | I96: Turistren | J96: 01/4/2024- 30/4/2024 | K96: ARRIENDO ESPACIO CUBIERTO AL INTERIOR DEL NUEVO TALLER ANI, UBICADO EN LAS INSTALACIONES DEL KILÓMETRO 5, CON UN AREA DE 1.986.8 METROS CUADRADOS | L96: 40192964 | M96: 6417364 | N96: =+L96-M96 -> 33775600 | O96: =ROUND(N96*0.004,0) -> 135102 | P96: =N96-O96 -> 33640498 | Q96: =Tabla1[[#This Row],[Valor a Consignar a la ANI]] -> 33640498 | R96: 2024 | S96: 5 | T96: 45440 | U96: =P96-Q96 -> 0
B97: 2024 | C97: =UPPER(TEXT(D97,"MMM")) -> ABR | D97: 45391 | E97: 186 | F97: NA | G97: NA | H97: Bogotá - Belencito | I97: Fideicomiso Sociedad Fiduciaria de occidente | J97: 01/4/2024- 30/4/2024 | K97: ARRIENDO DE BODEGA DE 128,2 M2, UBICADO EN KM 5 | L97: 2827964 | M97: 451523.66 | N97: =+L97-M97 -> 2376440.3 | O97: =ROUND(N97*0.004,0) -> 9506 | P97: =N97-O97 -> 2366934.3 | Q97: =Tabla1[[#This Row],[Valor a Consignar a la ANI]] -> 2366934.3 | R97: 2024 | S97: 5 | T97: 45440 | U97: =P97-Q97 -> 0
B98: 2024 | C98: =UPPER(TEXT(D98,"MMM")) -> ABR | D98: 45391 | E98: 187 | F98: NA | G98: NA | H98: Bogotá - Belencito | I98: Fideicomiso Sociedad Fiduciaria de occidente | J98: 01/4/2024- 30/4/2024 | K98: ARRIENDO DE AREA DE 500 M2, UBICADA EN EL KM5 | L98: 4760000 | M98: 760000 | N98: =+L98-M98 -> 4000000 | O98: =ROUND(N98*0.004,0) -> 16000 | P98: =N98-O98 -> 3984000 | Q98: =Tabla1[[#This Row],[Valor a Consignar a la ANI]] -> 3984000 | R98: 2024 | S98: 5 | T98: 45440 | U98: =P98-Q98 -> 0
B99: 2024 | C99: =UPPER(TEXT(D99,"MMM")) -> ABR | D99: 45391 | E99: 188 | F99: NA | G99: NA | H99: Bogotá - Belencito | I99: Fideicomiso Sociedad Fiduciaria de occidente | J99: 01/4/2024- 30/4/2024 | K99: ARRIENDO DE ESPACIO DE 241.42 M2, UBICADA EN EL KM5 | L99: 5325504 | M99: 850290.56 | N99: =+L99-M99 -> 4475213.4 | O99: =ROUND(N99*0.004,0) -> 17901 | P99: =N99-O99 -> 4457312.4 | Q99: =Tabla1[[#This Row],[Valor a Consignar a la ANI]] -> 4457312.4 | R99: 2024 | S99: 5 | T99: 45440 | U99: =P99-Q99 -> 0
B100: 2024 | C100: =UPPER(TEXT(D100,"MMM")) -> MAY | D100: 45415 | E100: 207 | F100: NA | G100: NA | H100: Bogotá - Belencito | I100: CEMENTOS ARGOS | J100: 01/5/2024- 31/5/2024 | K100: ARRIENDO BODEGA CON UNA AREA DE 1,117 M2 UBICADA EN KM5 | L100: 26877150 | M100: 4291309.7 | N100: =+L100-M100 -> 22585840 | O100: =ROUND(N100*0.004,0) -> 90343 | P100: =N100-O100 -> 22495497 | Q100: =Tabla1[[#This Row],[Valor a Consignar a la ANI]] -> 22495497 | R100: 2024 | S100: 5 | T100: 45440 | U100: =P100-Q100 -> 0
B101: 2024 | C101: =UPPER(TEXT(D101,"MMM")) -> MAY | D101: 45415 | E101: 206 | F101: NA | G101: NA | H101: Bogotá - Belencito | I101: Turistren | J101: 01/5/2024- 31/5/2024 | K101: ARRIENDO ESPACIO CUBIERTO AL INTERIOR DEL NUEVO TALLER ANI, UBICADO EN LAS INSTALACIONES DEL KILÓMETRO 5, CON UN AREA DE 1.986.8 METROS CUADRADOS | L101: 40192964 | M101: 6417364 | N101: =+L101-M101 -> 33775600 | O101: =ROUND(N101*0.004,0) -> 135102 | P101: =N101-O101 -> 33640498 | Q101: =Tabla1[[#This Row],[Valor a Consignar a la ANI]] -> 33640498 | R101: 2024 | S101: 5 | T101: 45440 | U101: =P101-Q101 -> 0
...

Sheet Tabla Inm.
K1: Inmuebles
A2: Etiquetas de fila | B2: Suma de Valor a Consignar a la ANI | C2: Suma de Valor Pagado | F2: Etiquetas de fila | G2: Suma de Valor a Consignar a la ANI | H2: Suma de Valor Pagado | K2: Etiquetas de fila | L2: Suma de Valor Pagado
A3: ENE | B3: 71784134 | C3: 71385121 | F3: CEMENTOS ARGOS | G3: 2.2964201e+08 | H3: 74473617 | K3: ENE | L3: 1.3872838e+08
A4: 2025 | B4: 71784134 | C4: 71385121 | F4: 2025 | G4: 2.2964201e+08 | H4: 74473617 | K4: 2024 | L4: 66944242
A5: FEB | B5: 71784134 | C5: 71784134 | F5: Fideicomiso Sociedad Fiduciaria de occidente | G5: 95007126 | H5: 45546709 | K5: 2025 | L5: 71385121
A6: 2025 | B6: 71784134 | C6: 71784134 | F6: 2025 | G6: 95007126 | H6: 45546709 | K6: 2026 | L6: 399013.4
A7: MAR | B7: 85107637 | C7: 72584734 | F7: Turistren | G7: 3.1850823e+08 | H7: 1.0616941e+08 | K7: FEB | L7: 1.3474438e+08
A8: 2025 | B8: 85107637 | C8: 72584734 | F8: 2025 | G8: 3.1850823e+08 | H8: 1.0616941e+08 | K8: 2024 | L8: 62960242
A9: ABR | B9: 79067067 | C9: 10435748 | F9: JE JAIMES Ingenieros S.A.S | G9: 25516994 | K9: 2025 | L9: 71784134
A10: 2025 | B10: 79067067 | C10: 10435748 | F10: 2025 | G10: 25516994 | K10: MAR | L10: 1.3554498e+08
A11: MAY | B11: 79067067 | F11: Total general | G11: 6.6867436e+08 | H11: 2.2618974e+08 | K11: 2024 | L11: 62960242
A12: 2025 | B12: 79067067 | K12: 2025 | L12: 72584734
A13: JUN | B13: 73510424 | K13: ABR | L13: 77379990
A14: 2025 | B14: 73510424 | K14: 2024 | L14: 66944242
A15: JUL | B15: 71074948 | K15: 2025 | L15: 10435748
A16: 2025 | B16: 71074948 | K16: MAY | L16: 82993419
A17: AGO | B17: 68639473 | K17: 2023 | L17: 8081177
A18: 2025 | B18: 68639473 | K18: 2024 | L18: 74912242
A19: SEP | B19: 68639473 | K19: 2025
A20: 2025 | B20: 68639473 | K20: JUN | L20: 1.0552293e+08
A21: Total general | B21: 6.6867436e+08 | C21: 2.2618974e+08 | K21: 2023 | L21: 38578692
K22: 2024 | L22: 66944242
K23: 2025
K24: JUL | L24: 2.720026e+08
K25: 2023 | L25: 2.0275112e+08
K26: 2024 | L26: 69251475
K27: 2025
K28: AGO | L28: 72843567
K29: 2023 | L29: 3452919.6
K30: 2024 | L30: 69390647
K31: 2025
K32: SEP | L32: 72704394
K33: 2023 | L33: 3452919.6
K34: 2024 | L34: 69251475
K35: 2025
K36: OCT | L36: 1.8558028e+08
K37: 2023 | L37: 1.1593041e+08
K38: 2024 | L38: 69649875
K39: NOV | L39: 74646572
K40: 2023
K41: 2024 | L41: 74646572
K42: DIC | L42: 1.2677809e+08
K43: 2023 | L43: 54794849
K44: 2024 | L44: 71983238
K45: Total general | L45: 1.4794696e+09

Sheet Imuebles 2

Sheet Uso de Via
A1: CONTRATO DE OBRA No PAF-ANI-O-118-2022-01 CON CONSORCIO CTSA - INGERAL - USO DE VIA
A2: FACTURACIÓN | Q2: PAGO
A3: Año | B3: Mes | C3: Fecha | D3: # Factura | E3: Corredor | F3: Tercero | G3: Periodo | H3: Concepto | I3: # Toneladas -kilometro | J3: # coche-kilómetros | K3: Tarifas $/ton-km y/o tarifa $/coche-km | L3: Valor Facturado | M3: IVA | N3: Valor bruto | O3: 4X1000 | P3: Valor a Consignar a la ANI | Q3: Valor Pagado | R3: Año2 | S3: Mes3 | T3: Fecha4 | U3: Valor Por Cobrar
A4: =+YEAR(C4) -> 2023 | B4: =UPPER(TEXT(C4,"MMM")) -> MAY | C4: 45055 | D4: 2 | E4: Bogotá - Belencito | F4: TURISTREN | G4: 17/03/2023 - 31/03/2023 | H4: USO DE VÍA PASAJEROS | J4: =+L4/K4 -> 11190 | K4: 850.96 | L4: 9522242 | N4: =L4-M4 -> 9522242 | O4: =ROUND(N4*0.004,0) -> 38089 | P4: =(N4-O4) -> 9484153 | Q4: 9484153 | R4: 2023 | S4: =UPPER(TEXT(T4,"MMM")) -> JUN | T4: 45085 | U4: =+P4-Q4 -> 0
A5: =+YEAR(C5) -> 2023 | B5: =UPPER(TEXT(C5,"MMM")) -> MAY | C5: 45070 | D5: 8 | E5: Bogotá - Belencito | F5: TURISTREN | G5: 01/04/2023 - 30/04/2023 | H5: USO DE VÍA PASAJEROS | J5: =+L5/K5 -> 43724 | K5: 850.96 | L5: 37207375 | N5: =L5-M5 -> 37207375 | O5: =ROUND(N5*0.004,0) -> 148830 | P5: =(N5-O5) -> 37058545 | Q5: 37058545 | R5: 2023 | S5: =UPPER(TEXT(T5,"MMM")) -> JUN | T5: 45085 | U5: =+P5-Q5 -> 0
A6: =+YEAR(C6) -> 2023 | B6: =UPPER(TEXT(C6,"MMM")) -> JUN | C6: 45078 | D6: 13 | E6: Bogotá - Belencito | F6: TURISTREN | G6: 01/05/2023 - 31/05/2023 | H6: USO DE VÍA PASAJEROS | J6: =+L6/K6 -> 46998 | K6: 850.96 | L6: 39993418 | N6: =L6-M6 -> 39993418 | O6: =ROUND(N6*0.004,0) -> 159974 | P6: =(N6-O6) -> 39833444 | Q6: 39833444 | R6: =+YEAR(T6) -> 2023 | S6: =UPPER(TEXT(T6,"MMM")) -> JUL | T6: 45135 | U6: =+P6-Q6 -> 0
A7: =+YEAR(C7) -> 2023 | B7: =UPPER(TEXT(C7,"MMM")) -> JUN | C7: 45107 | D7: OC001 | E7: Bogotá - Belencito | F7: CTSA-INGERAL | G7: 01/06/2023 - 30/06/2023 | H7: USO DE VÍA CARGA | I7: =ROUND(+L7/K7,0) -> 800917 | K7: 8 | L7: 6407339 | M7: 0 | N7: =L7-M7 -> 6407339 | O7: =ROUND(N7*0.004,0) -> 25629 | P7: =(N7-O7) -> 6381710 | Q7: 6381710 | R7: =+YEAR(T7) -> 2023 | S7: =UPPER(TEXT(T7,"MMM")) -> JUL | T7: 45135 | U7: =+P7-Q7 -> 0
A8: =+YEAR(C8) -> 2023 | B8: =UPPER(TEXT(C8,"MMM")) -> JUL | C8: 45111 | D8: 30 | E8: Bogotá - Belencito | F8: TURISTREN | G8: 01/06/2023 - 30/06/2023 | H8: USO DE VÍA PASAJEROS | J8: =+L8/K8 -> 20328 | K8: 850.96 | L8: 17298315 | N8: =L8-M8 -> 17298315 | O8: =ROUND(N8*0.004,0) -> 69193 | P8: =(N8-O8) -> 17229122 | Q8: 17229122 | R8: =+YEAR(T8) -> 2023 | S8: =UPPER(TEXT(T8,"MMM")) -> JUL | T8: 45135 | U8: =+P8-Q8 -> 0
A9: =+YEAR(C9) -> 2023 | B9: =UPPER(TEXT(C9,"MMM")) -> JUL | C9: 45138 | D9: OC002 | E9: Bogotá - Belencito | F9: CTSA-INGERAL | G9: 01/07/2023 - 30/07/2023 | H9: USO DE VÍA CARGA | I9: =ROUND(+L9/K9,0) -> 1003665 | K9: 8 | L9: 8029317 | N9: =L9-M9 -> 8029317 | O9: =ROUND(N9*0.004,0) -> 32117 | P9: =(N9-O9) -> 7997200 | Q9: 4001104 | R9: =+YEAR(T9) -> 2023 | S9: =UPPER(TEXT(T9,"MMM")) -> JUL | T9: 45135 | U9: =+P9-Q9 -> 3996096
A10: =+YEAR(C10) -> 2023 | B10: =UPPER(TEXT(C10,"MMM")) -> JUL | C10: 45138 | D10: OC002 | E10: Bogotá - Belencito | F10: CTSA-INGERAL | G10: 01/07/2023 - 30/07/2023 | H10: USO DE VÍA CARGA | I10: =ROUND(+L10/K10,0) -> 0 | K10: 8 | L10: 0 | N10: =L10-M10 -> 0 | O10: =ROUND(N10*0.004,0) -> 0 | P10: =(N10-O10) -> 0 | Q10: 3996096 | R10: =+YEAR(T10) -> 2023 | S10: =UPPER(TEXT(T10,"MMM")) -> AGO | T10: 45142 | U10: =+P10-Q10 -> -3996096
A11: =+YEAR(C11) -> 2023 | B11: =UPPER(TEXT(C11,"MMM")) -> AGO | C11: 45140 | D11: 53 | E11: Bogotá - Belencito | F11: TURISTREN | G11: 01/07/2023 - 30/07/2023 | H11: USO DE VÍA PASAJEROS | J11: =+L11/K11 -> 27108 | K11: 850.96 | L11: 23067824 | N11: =L11-M11 -> 23067824 | O11: =ROUND(N11*0.004,0) -> 92271 | P11: =(N11-O11) -> 22975553 | Q11: 22975553 | R11: =+YEAR(T11) -> 2023 | S11: =UPPER(TEXT(T11,"MMM")) -> AGO | T11: 45168 | U11: =+P11-Q11 -> 0
A12: =+YEAR(C12) -> 2023 | B12: =UPPER(TEXT(C12,"MMM")) -> AGO | C12: 45169 | D12: OC003 | E12: Bogotá - Belencito | F12: CTSA-INGERAL | G12: 01/07/2023 - 30/07/2023 | H12: USO DE VÍA CARGA | I12: =ROUND(+L12/K12,0) -> 801545 | K12: 8 | L12: 6412356 | N12: =L12-M12 -> 6412356 | O12: =ROUND(N12*0.004,0) -> 25649 | P12: =(N12-O12) -> 6386707 | Q12: 3996096 | R12: =+YEAR(T12) -> 2023 | S12: =UPPER(TEXT(T12,"MMM")) -> AGO | T12: 45168 | U12: =+P12-Q12 -> 2390611
A13: =+YEAR(C13) -> 2023 | B13: =UPPER(TEXT(C13,"MMM")) -> AGO | C13: 45169 | D13: 60 | E13: Bogotá - Belencito | F13: TURISTREN | G13: 01/08/2023 - 30/08/2023 | H13: USO DE VÍA PASAJEROS | J13: =+L13/K13 -> 41113.999 | K13: 850.96 | L13: 34986369 | N13: =L13-M13 -> 34986369 | O13: =ROUND(N13*0.004,0) -> 139945 | P13: =(N13-O13) -> 34846424 | Q13: 34846424 | R13: 2023 | S13: =UPPER(TEXT(T13,"MMM")) -> OCT | T13: 45204 | U13: =+P13-Q13 -> 0
A14: =+YEAR(C14) -> 2023 | B14: =UPPER(TEXT(C14,"MMM")) -> AGO | C14: 45169 | D14: OC003 | E14: Bogotá - Belencito | F14: CTSA-INGERAL | G14: 01/07/2023 - 30/07/2023 | H14: USO DE VÍA CARGA | I14: =ROUND(+L14/K14,0) -> 0 | K14: 8 | Q14: 2390611 | R14: =+YEAR(T14) -> 2023 | S14: =UPPER(TEXT(T14,"MMM")) -> NOV | T14: 45233 | U14: =P14-Q14 -> -2390611
A15: =+YEAR(C15) -> 2023 | B15: =UPPER(TEXT(C15,"MMM")) -> SEP | C15: 45199 | D15: OC004 | E15: Bogotá - Belencito | F15: CTSA-INGERAL | G15: 01/09/2023 - 30/09/2023 | H15: USO DE VÍA CARGA | I15: =ROUND(+L15/K15,0) -> 901672 | K15: 8 | L15: 7213373 | N15: =L15-M15 -> 7213373 | O15: =ROUND(N15*0.004,0) -> 28853 | P15: =(N15-O15) -> 7184520 | Q15: 7184520 | R15: =+YEAR(T15) -> 2023 | S15: =UPPER(TEXT(T15,"MMM")) -> NOV | T15: 45233 | U15: =+P15-Q15 -> 0
A16: =+YEAR(C16) -> 2023 | B16: =UPPER(TEXT(C16,"MMM")) -> SEP | C16: 45199 | D16: 73 | E16: Bogotá - Belencito | F16: TURISTREN | G16: 01/09/2023 - 30/09/2023 | H16: USO DE VÍA PASAJEROS | J16: =+L16/K16 -> 37822 | K16: 850.96 | L16: 32185009 | N16: =L16-M16 -> 32185009 | O16: =ROUND(N16*0.004,0) -> 128740 | P16: =(N16-O16) -> 32056269 | Q16: 32056269 | R16: =+YEAR(T16) -> 2023 | S16: =UPPER(TEXT(T16,"MMM")) -> NOV | T16: 45233 | U16: =+P16-Q16 -> 0
A17: =+YEAR(C17) -> 2023 | B17: =UPPER(TEXT(C17,"MMM")) -> OCT | C17: 45230 | D17: 90 | E17: Bogotá - Belencito | F17: TURISTREN | G17: 01/10/2023 - 31/10/2023 | H17: USO DE VÍA PASAJEROS | J17: 36570 | K17: 850.96 | L17: =J17*K17 -> 31119607 | N17: =L17-M17 -> 31119607 | O17: =ROUND(N17*0.004,0) -> 124478 | P17: =(N17-O17) -> 30995129 | Q17: =P17 -> 30995129 | R17: 2023 | S17: =UPPER(TEXT(T17,"MMM")) -> NOV | T17: 45260 | U17: =+P17-Q17 -> 0
A18: =+YEAR(C18) -> 2023 | B18: =UPPER(TEXT(C18,"MMM")) -> OCT | C18: 45230 | D18: OC005 | E18: Bogotá - Belencito | F18: CTSA-INGERAL | G18: 01/10/2023 - 31/10/2023 | H18: USO DE VÍA CARGA | I18: 802914 | K18: 8 | L18: 6423314.1 | N18: =L18-M18 -> 6423314.1 | O18: =ROUND(N18*0.004,0) -> 25693 | P18: =(N18-O18) -> 6397621.1 | Q18: =P18 -> 6397621.1 | R18: 2023 | S18: =UPPER(TEXT(T18,"MMM")) -> NOV | T18: 45260 | U18: =+P18-Q18 -> 0
A19: =+YEAR(C19) -> 2023 | B19: =UPPER(TEXT(C19,"MMM")) -> NOV | C19: 45260 | D19: OC006 | E19: Bogotá - Belencito | F19: CTSA-INGERAL | G19: 01/11/2023 - 30/11/2023 | H19: USO DE VÍA CARGA | I19: 815841 | K19: 8 | L19: 6526731 | N19: =L19-M19 -> 6526731 | O19: =ROUND(N19*0.004,0) -> 26107 | P19: =(N19-O19) -> 6500624 | Q19: =P19 -> 6500624 | R19: 2024 | S19: =UPPER(TEXT(T19,"MMM")) -> ENE | T19: 45322 | U19: =+P19-Q19 -> 0
A20: 2023 | B20: =UPPER(TEXT(C20,"MMM")) -> NOV | C20: 45260 | D20: 107 | E20: Bogotá - Belencito | F20: TURISTREN | G20: 01/11/2023 - 30/11/2023 | H20: USO VIA PASAJEROS | J20: 35066 | K20: 850.96 | L20: 29839763 | N20: =L20-M20 -> 29839763 | O20: =ROUND(N20*0.004,0) -> 119359 | P20: =(N20-O20) -> 29720404 | Q20: =P20 -> 29720404 | R20: 2024 | S20: =UPPER(TEXT(T20,"MMM")) -> ENE | T20: 45322 | U20: =+P20-Q20 -> 0
A21: 2023 | B21: =UPPER(TEXT(C21,"MMM")) -> DIC | C21: 45280 | D21: 118 | E21: Bogotá - Belencito | F21: ACERIAS PAZ DEL RIO | G21: 45250 | H21: TREN ESPECIAL | J21: 514 | K21: 850.96 | L21: =J21*K21 -> 437393.44 | N21: =L21-M21 -> 437393.44 | O21: =ROUND(N21*0.004,0) -> 1750 | P21: =(N21-O21) -> 435643.44 | Q21: 435643.44 | R21: 2024 | S21: =UPPER(TEXT(T21,"MMM")) -> FEB | T21: 45348 | U21: =+P21-Q21 -> 0
A22: 2023 | B22: =UPPER(TEXT(C22,"MMM")) -> DIC | C22: 45290 | D22: 128 | E22: Bogotá - Belencito | F22: TURISTREN | G22: 01/12/2023 - 30/12/2023 | H22: USO VIA PASAJEROS | J22: 44115 | K22: 850.96 | L22: =J22*K22 -> 37540100 | N22: =L22-M22 -> 37540100 | O22: =ROUND(N22*0.004,0) -> 150160 | P22: =(N22-O22) -> 37389940 | Q22: =P22 -> 37389940 | R22: 2024 | S22: =UPPER(TEXT(T22,"MMM")) -> ENE | T22: 45322 | U22: =+P22-Q22 -> 0
A23: 2023 | B23: =UPPER(TEXT(C23,"MMM")) -> DIC | C23: 45290 | D23: OC007 | E23: Bogotá - Belencito | F23: CTSA-INGERAL | G23: 01/12/2023 - 31/12/2023 | H23: USO DE VÍA CARGA | I23: 856208 | K23: 8 | L23: 6849667 | N23: =L23-M23 -> 6849667 | O23: =ROUND(N23*0.004,0) -> 27399 | P23: =(N23-O23) -> 6822268 | Q23: =P23 -> 6822268 | R23: 2024 | S23: =UPPER(TEXT(T23,"MMM")) -> ENE | T23: 45322 | U23: =+P23-Q23 -> 0
A24: 2024 | B24: =UPPER(TEXT(C24,"MMM")) -> ENE | C24: 45322 | D24: 0C008 | E24: Bogotá - Belencito | F24: CTSA-INGERAL | G24: 01/1/2024 - 31/1/2024 | H24: USO DE VÍA CARGA | I24: 806159 | K24: =8*1.0928 -> 8.7424 | L24: 7047765 | N24: =L24-M24 -> 7047765 | O24: =ROUND(N24*0.004,0) -> 28191 | P24: =(N24-O24) -> 7019574 | Q24: 7019574 | R24: 2024 | S24: =UPPER(TEXT(T24,"MMM")) -> FEB | T24: 45348 | U24: =+P24-Q24 -> 0
A25: 2024 | B25: =UPPER(TEXT(C25,"MMM")) -> ENE | C25: 45322 | D25: 142 | E25: Bogotá - Belencito | F25: TURISTREN | G25: 01/1/2024 - 31/1/2024 | H25: USO VIA PASAJEROS | J25: 23406 | K25: =850.96*1.0928 -> 929.92909 | L25: 21765942 | N25: =L25-M25 -> 21765942 | O25: =ROUND(N25*0.004,0) -> 87064 | P25: =(N25-O25) -> 21678878 | Q25: 21678878 | R25: 2024 | S25: =UPPER(TEXT(T25,"MMM")) -> FEB | T25: 45348 | U25: =+P25-Q25 -> 0
A26: 2024 | B26: =UPPER(TEXT(C26,"MMM")) -> FEB | C26: 45351 | D26: OC009 | E26: Bogotá - Belencito | F26: CTSA-INGERAL | G26: 01/02/2024 - 29/02/2024 | H26: USO DE VÍA CARGA | I26: 1243965 | K26: =8*1.0928 -> 8.7424 | L26: 10875237 | N26: =L26-M26 -> 10875237 | O26: =ROUND(N26*0.004,0) -> 43501 | P26: =(N26-O26) -> 10831736 | Q26: 10831736 | R26: 2024 | S26: =UPPER(TEXT(T26,"MMM")) -> ABR | T26: 45383 | U26: =+P26-Q26 -> 0
A27: 2024 | B27: =UPPER(TEXT(C27,"MMM")) -> FEB | C27: 45351 | D27: OC009 | E27: Bogotá - Belencito | F27: CTSA-INGERAL | G27: 01/02/2024 - 29/02/2024 | H27: USO DE VÍA CARGA | P27: 0.19 | Q27: 0.19 | R27: 2024 | S27: =UPPER(TEXT(T27,"MMM")) -> ABR | T27: 45412 | U27: =+P27-Q27 -> 0
A28: 2024 | B28: =UPPER(TEXT(C28,"MMM")) -> FEB | C28: 45351 | D28: 160 | E28: Bogotá - Belencito | F28: TURISTREN | G28: 01/02/2024 - 29/02/2024 | H28: USO VIA PASAJEROS | J28: 34356 | K28: =850.96*1.0928 -> 929.92909 | L28: 31948675 | N28: =L28-M28 -> 31948675 | O28: =ROUND(N28*0.004,0) -> 127795 | P28: =(N28-O28) -> 31820880 | Q28: 31820880 | R28: 2024 | S28: =UPPER(TEXT(T28,"MMM")) -> ABR | T28: 45412 | U28: =+P28-Q28 -> 0
A29: 2024 | B29: =UPPER(TEXT(C29,"MMM")) -> MAR | C29: 45382 | D29: OC010 | E29: Bogotá - Belencito | F29: CTSA-INGERAL | G29: 01/03/2024 - 31/03/2024 | H29: USO DE VÍA CARGA | I29: 1217128 | K29: =8*1.0928 -> 8.7424 | L29: 10640620 | N29: =L29-M29 -> 10640620 | O29: =ROUND(N29*0.004,0) -> 42562 | P29: =(N29-O29) -> 10598058 | Q29: 10598058 | R29: 2024 | S29: =UPPER(TEXT(T29,"MMM")) -> ABR | T29: 45412 | U29: =+P29-Q29 -> 0
A30: 2024 | B30: =UPPER(TEXT(C30,"MMM")) -> MAR | C30: 45382 | D30: 177 | E30: Bogotá - Belencito | F30: TURISTREN | G30: 01/03/2024 - 31/03/2024 | H30: USO VIA PASAJEROS | J30: 43418 | K30: =850.96*1.0928 -> 929.92909 | L30: 40375701 | N30: 40375701 | O30: =ROUND(N30*0.004,0) -> 161503 | P30: =(N30-O30) -> 40214198 | Q30: =P30 -> 40214198 | R30: 2024 | S30: =UPPER(TEXT(T30,"MMM")) -> MAY | T30: 45440 | U30: =+P30-Q30 -> 0
A31: 2024 | B31: =UPPER(TEXT(C31,"MMM")) -> ABR | C31: 45412 | D31: OC011 | E31: Bogotá - Belencito | F31: CTSA-INGERAL | G31: 01/04/2024 - 30/04/2024 | H31: USO DE VÍA CARGA | I31: 1619942.2 | K31: 8.74 | L31: 14162182 | N31: 14162182 | O31: =ROUND(N31*0.004,0) -> 56649 | P31: =(N31-O31) -> 14105533 | Q31: =P31 -> 14105533 | R31: 2024 | S31: =UPPER(TEXT(T31,"MMM")) -> MAY | T31: 45440 | U31: =+P31-Q31 -> 0
A32: 2024 | B32: =UPPER(TEXT(C32,"MMM")) -> ABR | C32: 45412 | D32: 201 | E32: Bogotá - Belencito | F32: TURISTREN | G32: 01/04/2024 - 30/04/2024 | H32: USO DE VÍA PASAJEROS | J32: 35262 | K32: =850.96*1.0928 -> 929.92909 | L32: 32791192 | N32: 32791192 | O32: =ROUND(N32*0.004,0) -> 131165 | P32: =(N32-O32) -> 32660027 | Q32: =P32 -> 32660027 | R32: 2024 | S32: =UPPER(TEXT(T32,"MMM")) -> MAY | T32: 45440 | U32: =+P32-Q32 -> 0
A33: 2024 | B33: =UPPER(TEXT(C33,"MMM")) -> MAY | C33: 45443 | D33: OC012 | E33: Bogotá - Belencito | F33: CTSA-INGERAL | G33: 01/05/2024 - 31/05/2024 | H33: USO DE VÍA CARGA | I33: 1218151 | K33: 8.74 | L33: 10649561 | N33: 10649561 | O33: =ROUND(N33*0.004,0) -> 42598 | P33: =(N33-O33) -> 10606963 | Q33: 10606963 | R33: 2024 | S33: =UPPER(TEXT(T33,"MMM")) -> JUN | T33: 45469 | U33: =+P33-Q33 -> 0
A34: 2024 | B34: =UPPER(TEXT(C34,"MMM")) -> MAY | C34: 45443 | D34: 215 | E34: Bogotá - Belencito | F34: TURISTREN | G34: 01/05/2024 - 31/05/2024 | H34: USO DE VÍA PASAJEROS | J34: 32964 | K34: =850.96*1.0928 -> 929.92909 | L34: 30654213 | N34: 30654213 | O34: =ROUND(N34*0.004,0) -> 122617 | P34: =(N34-O34) -> 30531596 | Q34: 30531596 | R34: 2024 | S34: =UPPER(TEXT(T34,"MMM")) -> JUN | T34: 45469 | U34: =+P34-Q34 -> 0
A35: 2024 | B35: =UPPER(TEXT(C35,"MMM")) -> JUN | C35: 45473 | D35: OC013 | E35: Bogotá - Belencito | F35: CTSA-INGERAL | G35: 01/06/2024 - 30/06/2024 | H35: USO DE VÍA CARGA | I35: 1319475 | K35: 8.74 | L35: 11535378 | N35: =L35 -> 11535378 | O35: =ROUND(N35*0.004,0) -> 46142 | P35: 11489236 | Q35: 11489236 | R35: 2024 | S35: =UPPER(TEXT(T35,"MMM")) -> JUL | T35: 45504 | U35: =+P35-Q35 -> 0
A36: 2024 | B36: =UPPER(TEXT(C36,"MMM")) -> JUN | C36: 45473 | D36: 237 | E36: Bogotá - Belencito | F36: TURISTREN | G36: 01/06/2024 - 30/06/2024 | H36: USO DE VÍA PASAJEROS | J36: 19428 | K36: =850.96*1.0928 -> 929.92909 | L36: 18066680 | N36: =L36 -> 18066680 | O36: =ROUND(N36*0.004,0) -> 72267 | P36: =(N36-O36) -> 17994413 | Q36: 17994413 | R36: 2024 | S36: =UPPER(TEXT(T36,"MMM")) -> JUL | T36: 45504 | U36: =+P36-Q36 -> 0
A37: 2024 | B37: =UPPER(TEXT(C37,"MMM")) -> JUL | C37: 45504 | D37: OC014 | E37: Bogotá - Belencito | F37: CTSA-INGERAL | G37: 01/07/2024 - 31/07/2024 | H37: USO DE VÍA CARGA | I37: 1341466.9 | K37: 8.74 | L37: 11727640 | N37: 11727640 | O37: =ROUND(N37*0.004,0) -> 46911 | P37: =(N37-O37) -> 11680729 | Q37: =P37 -> 11680729 | R37: 2024 | S37: =UPPER(TEXT(T37,"MMM")) -> AGO | T37: 45533 | U37: =+P37-Q37 -> 0
A38: 2024 | B38: =UPPER(TEXT(C38,"MMM")) -> JUL | C38: 45504 | D38: 247 | E38: Bogotá - Belencito | F38: TURISTREN | G38: 01/07/2024 - 31/07/2024 | H38: USO DE VÍA PASAJEROS | J38: 26264 | K38: =850.96*1.0928 -> 929.92909 | L38: 24423682 | N38: 24423682 | O38: =ROUND(N38*0.004,0) -> 97695 | P38: =(N38-O38) -> 24325987 | Q38: 24325987 | R38: 2024 | S38: =UPPER(TEXT(T38,"MMM")) -> SEP | T38: 45565 | U38: =+P38-Q38 -> 0
A39: 2024 | B39: =UPPER(TEXT(C39,"MMM")) -> AGO | C39: 45535 | D39: OC015 | E39: Bogotá - Belencito | F39: CTSA-INGERAL | G39: 01/08/2024 - 31/08/2024 | H39: USO DE VÍA CARGA | I39: 1068577.4 | K39: 8.74 | L39: 9341931.2 | N39: =L39 -> 9341931.2 | O39: =ROUND(N39*0.004,0) -> 37368 | P39: =(N39-O39) -> 9304563.2 | Q39: 9304563.2 | R39: 2024 | S39: =UPPER(TEXT(T39,"MMM")) -> SEP | T39: 45565 | U39: =+P39-Q39 -> 0
A40: 2024 | B40: =UPPER(TEXT(C40,"MMM")) -> AGO | C40: 45535 | D40: 267 | E40: Bogotá - Belencito | F40: TURISTREN | G40: 01/08/2024 - 31/08/2024 | H40: USO DE VÍA PASAJEROS | J40: 43540 | K40: =850.96*1.0928 -> 929.92909 | L40: 40489152 | N40: =L40 -> 40489152 | O40: =ROUND(N40*0.004,0) -> 161957 | P40: =(N40-O40) -> 40327195 | Q40: 40327195 | R40: 2024 | S40: =UPPER(TEXT(T40,"MMM")) -> NOV | T40: 45623 | U40: =+P40-Q40 -> 0
A41: 2024 | B41: =UPPER(TEXT(C41,"MMM")) -> SEP | C41: 45565 | D41: OC016 | E41: Bogotá - Belencito | F41: CTSA-INGERAL | G41: 01/09/2024 - 30/09/2024 | H41: USO DE VÍA CARGA | I41: 1386927.4 | K41: 8.74 | L41: 12125074 | N41: =L41 -> 12125074 | O41: =ROUND(N41*0.004,0) -> 48500 | P41: =(N41-O41) -> 12076574 | Q41: 12076574 | R41: 2024 | S41: =UPPER(TEXT(T41,"MMM")) -> OCT | T41: 45596 | U41: =+P41-Q41 -> 0
A42: 2024 | B42: =UPPER(TEXT(C42,"MMM")) -> SEP | C42: 45565 | D42: 287 | E42: Bogotá - Belencito | F42: TURISTREN | G42: 01/09/2024 - 30/09/2024 | H42: USO DE VÍA PASAJEROS | J42: 34638 | K42: =850.96*1.0928 -> 929.92909 | L42: 32210915 | N42: =L42 -> 32210915 | O42: =ROUND(N42*0.004,0) -> 128844 | P42: =(N42-O42) -> 32082071 | Q42: 32082071 | R42: 2024 | S42: =UPPER(TEXT(T42,"MMM")) -> OCT | T42: 45596 | U42: =+P42-Q42 -> 0
A43: 2024 | B43: =UPPER(TEXT(C43,"MMM")) -> OCT | C43: 45596 | D43: OC017 | E43: Bogotá - Belencito | F43: CTSA-INGERAL | G43: 01/10/2024-31/10/2024 | H43: USO DE VÍA CARGA | I43: 1333535.3 | K43: 8.74 | L43: 11658299 | N43: 11658299 | O43: =ROUND(N43*0.004,0) -> 46633 | P43: =(N43-O43) -> 11611666 | Q43: 11611666 | R43: 2024 | S43: =UPPER(TEXT(T43,"MMM")) -> NOV | T43: 45623 | U43: =+P43-Q43 -> 0
A44: 2024 | B44: =UPPER(TEXT(C44,"MMM")) -> OCT | C44: 45596 | D44: 308 | E44: Bogotá - Belencito | F44: TURISTREN | G44: 01/10/2024-31/10/2024 | H44: USO DE VÍA PASAJEROS | J44: 36820 | K44: 929.93 | L44: 34240023 | N44: 34240023 | O44: =ROUND(N44*0.004,0) -> 136960 | P44: =(N44-O44) -> 34103063 | Q44: 34103063 | R44: 2025 | S44: =UPPER(TEXT(T44,"MMM")) -> FEB | T44: 45714 | U44: =+P44-Q44 -> 0
A45: 2024 | B45: =UPPER(TEXT(C45,"MMM")) -> NOV | C45: 45626 | D45: OC018 | E45: Bogotá - Belencito | F45: CTSA-INGERAL | G45: 01/11/2024-30/11/2024 | H45: USO DE VÍA CARGA | I45: 699824.52 | K45: 8.74 | L45: 6118145.9 | N45: 6118145.9 | O45: =ROUND(N45*0.004,0) -> 24473 | P45: =(N45-O45) -> 6093672.9 | Q45: 6093672.9 | R45: 2025 | S45: =UPPER(TEXT(T45,"MMM")) -> FEB | T45: 45714 | U45: =+P45-Q45 -> 0
A46: 2024 | B46: =UPPER(TEXT(C46,"MMM")) -> NOV | C46: 45626 | D46: 324 | E46: Bogotá - Belencito | F46: TURISTREN | G46: 01/11/2024-30/11/2024 | H46: USO DE VÍA PASAJEROS | J46: 37392 | K46: 929.93 | L46: 34771943 | N46: 34771943 | O46: =ROUND(N46*0.004,0) -> 139088 | P46: =(N46-O46) -> 34632855 | Q46: =Tabla4[[#This Row],[Valor a Consignar a la ANI]] -> 34632855 | R46: 2025 | S46: =UPPER(TEXT(T46,"MMM")) -> ABR | T46: 45770 | U46: =+P46-Q46 -> 0
A47: 2024 | B47: =UPPER(TEXT(C47,"MMM")) -> DIC | C47: 45657 | D47: OC019 | E47: Bogotá - Belencito | F47: CTSA-INGERAL | G47: 01/12/2024-31/12/2024 | H47: USO DE VÍA CARGA | I47: 808621.71 | K47: 8.74 | L47: 7069294.5 | N47: 7069294.5 | O47: =ROUND(N47*0.004,0) -> 28277 | P47: =(N47-O47) -> 7041017.5 | Q47: 7041017.5 | R47: 2025 | S47: =UPPER(TEXT(T47,"MMM")) -> FEB | T47: 45714 | U47: =+P47-Q47 -> 0
A48: 2024 | B48: =UPPER(TEXT(C48,"MMM")) -> DIC | C48: 45657 | D48: 344 | E48: Bogotá - Belencito | F48: TURISTREN | G48: 01/12/2024-31/12/2024 | H48: USO DE VÍA PASAJEROS | J48: 55184 | K48: 929.93 | L48: =J48*K48 -> 51317257 | N48: =L48 -> 51317257 | O48: =ROUND(N48*0.004,0) -> 205269 | P48: =(N48-O48) -> 51111988 | Q48: =Tabla4[[#This Row],[Valor a Consignar a la ANI]] -> 51111988 | R48: 2025 | S48: =UPPER(TEXT(T48,"MMM")) -> MAY | T48: 45805 | U48: =+P48-Q48 -> 0
A49: 2025 | B49: =UPPER(TEXT(C49,"MMM")) -> ENE | C49: 45688 | D49: OC020 | E49: Bogotá - Belencito | F49: CTSA-INGERAL | G49: 01/1/2025-31/1/2025 | H49: USO DE VÍA CARGA | I49: 692265.48 | K49: =K47*1.052 -> 9.19448 | L49: 6366768.9 | N49: =L49 -> 6366768.9 | O49: =ROUND(N49*0.004,0) -> 25467 | P49: =(N49-O49) -> 6341301.9 | Q49: =Tabla4[[#This Row],[Valor a Consignar a la ANI]] -> 6341301.9 | R49: 2025 | S49: =UPPER(TEXT(T49,"MMM")) -> JUL | T49: 45845 | U49: =+P49-Q49 -> 0
A50: 2025 | B50: =UPPER(TEXT(C50,"MMM")) -> ENE | C50: 45688 | D50: 361 | E50: Bogotá - Belencito | F50: TURISTREN | G50: 01/1/2025-31/1/2025 | H50: USO DE VÍA PASAJEROS | J50: 25602 | K50: 978.29 | L50: =J50*K50 -> 25046181 | N50: =L50 -> 25046181 | O50: =ROUND(N50*0.004,0) -> 100185 | P50: =(N50-O50) -> 24945996 | Q50: =Tabla4[[#This Row],[Valor a Consignar a la ANI]] -> 24945996 | R50: 2025 | S50: =UPPER(TEXT(T50,"MMM")) -> JUL | T50: 45845 | U50: =+P50-Q50 -> 0
A51: 2025 | B51: =UPPER(TEXT(C51,"MMM")) -> FEB | C51: 45716 | D51: OC021 | E51: Bogotá - Belencito | F51: CTSA-INGERAL | G51: 01/2/2025-28/2/2025 | H51: USO DE VÍA CARGA | I51: 733974.79 | K51: =K47*1.052 -> 9.19448 | L51: 6750369.6 | N51: =L51 -> 6750369.6 | O51: =ROUND(N51*0.004,0) -> 27001 | P51: =(N51-O51) -> 6723368.6 | Q51: =Tabla4[[#This Row],[Valor a Consignar a la ANI]] -> 6723368.6 | R51: 2025 | S51: =UPPER(TEXT(T51,"MMM")) -> AGO | T51: 45873 | U51: =+P51-Q51 -> 0
A52: 2025 | B52: =UPPER(TEXT(C52,"MMM")) -> FEB | C52: 45716 | D52: 378 | E52: Bogotá - Belencito | F52: TURISTREN | G52: 01/2/2025-28/2/2025 | H52: USO DE VÍA PASAJEROS | J52: 30368 | K52: 978.29 | L52: =J52*K52 -> 29708711 | N52: =L52 -> 29708711 | O52: =ROUND(N52*0.004,0) -> 118835 | P52: =(N52-O52) -> 29589876 | Q52: =Tabla4[[#This Row],[Valor a Consignar a la ANI]] -> 29589876 | R52: 2025 | S52: =UPPER(TEXT(T52,"MMM")) -> AGO | T52: 45873 | U52: =+P52-Q52 -> 0
A53: 2025 | B53: =UPPER(TEXT(C53,"MMM")) -> MAR | C53: 45747 | D53: OC022 | E53: Bogotá - Belencito | F53: CTSA-INGERAL | G53: 01/3/2025-31/3/2025 | H53: USO DE VÍA CARGA | I53: 996792.49 | K53: 9.19448 | L53: 9167505.3 | N53: =L53 -> 9167505.3 | O53: =ROUND(N53*0.004,0) -> 36670 | P53: =(N53-O53) -> 9130835.3 | Q53: 9130835.3 | R53: 2025 | S53: =UPPER(TEXT(T53,"MMM")) -> SEP | T53: 45904 | U53: =+P53-Q53 -> 0
A54: 2025 | B54: =UPPER(TEXT(C54,"MMM")) -> MAR | C54: 45747 | D54: 396 | E54: Bogotá - Belencito | F54: TURISTREN | G54: 01/3/2025-31/3/2025 | H54: USO DE VÍA PASAJEROS | J54: 37864 | K54: 978.29 | L54: 37041973 | N54: =L54 -> 37041973 | O54: =ROUND(N54*0.004,0) -> 148168 | P54: =(N54-O54) -> 36893805 | Q54: =Tabla4[[#This Row],[Valor a Consignar a la ANI]] -> 36893805 | R54: 2025 | S54: OCT | T54: 45932 | U54: =+P54-Q54 -> 0
A55: 2025 | B55: =UPPER(TEXT(C55,"MMM")) -> ABR | C55: 45777 | D55: OC023 | E55: Bogotá - Belencito | F55: CTSA-INGERAL | G55: 01/4/2025-30/4/2025 | H55: USO DE VÍA CARGA | I55: 797190.87 | K55: 9.19448 | L55: 7331768.3 | N55: =L55 -> 7331768.3 | O55: =ROUND(N55*0.004,0) -> 29327 | P55: =(N55-O55) -> 7302441.3 | Q55: =Tabla4[[#This Row],[Valor a Consignar a la ANI]] -> 7302441.3 | R55: 2025 | S55: OCT | T55: 45932 | U55: =+P55-Q55 -> 0
A56: 2025 | B56: =UPPER(TEXT(C56,"MMM")) -> ABR | C56: 45777 | D56: 419 | E56: Bogotá - Belencito | F56: TURISTREN | G56: 01/4/2025-30/4/2025 | H56: USO DE VÍA PASAJEROS | J56: 35748 | K56: 978.29 | L56: =Tabla4[[#This Row],[Valor bruto]] -> 34971911 | N56: 34971911 | O56: =ROUND(N56*0.004,0) -> 139888 | P56: =(N56-O56) -> 34832023 | Q56: =Tabla4[[#This Row],[Valor a Consignar a la ANI]] -> 34832023 | R56: 2025 | S56: OCT | T56: 45938 | U56: =+P56-Q56 -> 0
A57: 2025 | B57: =UPPER(TEXT(C57,"MMM")) -> MAY | C57: 45808 | D57: OC024 | E57: Bogotá - Belencito | F57: CTSA-INGERAL | G57: 01/5/2025-31/5/2025 | H57: USO DE VÍA CARGA | I57: 1001291.8 | K57: 9.19448 | L57: 9208885.2 | N57: 9208885.2 | O57: =ROUND(N57*0.004,0) -> 36836 | P57: =(N57-O57) -> 9172049.2 | Q57: =Tabla4[[#This Row],[Valor a Consignar a la ANI]] -> 9172049.2 | R57: 2025 | S57: OCT | T57: 45938 | U57: =+P57-Q57 -> 0
A58: 2025 | B58: =UPPER(TEXT(C58,"MMM")) -> MAY | C58: 45808 | D58: 443 | E58: Bogotá - Belencito | F58: TURISTREN | G58: 01/5/2025-31/5/2025 | H58: USO DE VÍA PASAJEROS | J58: 35792 | K58: 978.29 | L58: 35014956 | N58: 35014956 | O58: =ROUND(N58*0.004,0) -> 140060 | P58: =(N58-O58) -> 34874896 | Q58: =Tabla4[[#This Row],[Valor a Consignar a la ANI]] -> 34874896 | R58: 2025 | S58: OCT | T58: 45938 | U58: =+P58-Q58 -> 0
A59: 2025 | B59: =UPPER(TEXT(C59,"MMM")) -> JUN | C59: 45838 | D59: OC025 | E59: Bogotá - Belencito | F59: CTSA-INGERAL | G59: 01/06/2025-30/06/2025 | H59: USO DE VÍA CARGA | I59: 884138.71 | K59: 9.19448 | L59: 8131428 | N59: 8131428 | O59: =ROUND(N59*0.004,0) -> 32526 | P59: =(N59-O59) -> 8098902 | Q59: =Tabla4[[#This Row],[Valor a Consignar a la ANI]] -> 8098902 | R59: 2025 | S59: OCT | T59: 45938 | U59: =+P59-Q59 -> 0
A60: 2025 | B60: =UPPER(TEXT(C60,"MMM")) -> JUL | C60: 45839 | D60: 458 | E60: Bogotá - Belencito | F60: TURISTREN | G60: 01/06/2025-30/06/2025 | H60: USO DE VÍA PASAJEROS | J60: 18732 | K60: 978.29 | L60: 18325328 | N60: 18325328 | O60: =ROUND(N60*0.004,0) -> 73301 | P60: =(N60-O60) -> 18252027 | U60: =+P60-Q60 -> 18252027
A61: 2025 | B61: =UPPER(TEXT(C61,"MMM")) -> JUL | C61: 45869 | D61: OC026 | E61: Bogotá - Belencito | F61: CTSA-INGERAL | G61: 01/07/2025-31/07/2025 | H61: USO DE VÍA CARGA | I61: 978468.71 | K61: 9.19448 | L61: 8998981.4 | N61: 8998981.4 | O61: =ROUND(N61*0.004,0) -> 35996 | P61: =(N61-O61) -> 8962985.4 | Q61: =Tabla4[[#This Row],[Valor a Consignar a la ANI]] -> 8962985.4 | R61: 2025 | S61: OCT | T61: 45961 | U61: =+P61-Q61 -> 0
A62: 2025 | B62: =UPPER(TEXT(C62,"MMM")) -> JUL | C62: 45869 | D62: 474 | E62: Bogotá - Belencito | F62: TURISTREN | G62: 01/07/2025-31/07/2025 | H62: USO DE VÍA PASAJEROS | J62: 23558 | K62: 978.29 | L62: 23046556 | N62: 23046556 | O62: =ROUND(N62*0.004,0) -> 92186 | P62: =(N62-O62) -> 22954370 | Q62: =Tabla4[[#This Row],[Valor a Consignar a la ANI]] -> 22954370 | R62: 2025 | S62: OCT | T62: 45961 | U62: =+P62-Q62 -> 0
A63: 2025 | B63: =UPPER(TEXT(C63,"MMM")) -> JUL | C63: 45869 | D63: 475 | E63: Bogotá - Belencito | F63: ACERIAS PAZ DEL RIO | G63: 01/07/2025-31/07/2025 | H63: USO DE VÍA PASAJEROS | J63: 416 | K63: 978.29 | L63: 406968.64 | N63: 406968.64 | O63: =ROUND(N63*0.004,0) -> 1628 | P63: =(N63-O63) -> 405340.64 | U63: =+P63-Q63 -> 405340.64
A64: 2025 | B64: =UPPER(TEXT(C64,"MMM")) -> AGO | C64: 45900 | D64: OC027 | E64: Bogotá - Belencito | F64: CTSA-INGERAL | G64: 01/08/2025-31/08/2025 | H64: USO DE VÍA CARGA | I64: 980537.4 | K64: 9.19448 | L64: 9018007.2 | N64: 9018007.2 | O64: =ROUND(N64*0.004,0) -> 36072 | P64: =(N64-O64) -> 8981935.2 | U64: =+P64-Q64 -> 8981935.2
A65: 2025 | B65: =UPPER(TEXT(C65,"MMM")) -> AGO | C65: 45900 | D65: OC027 | E65: Bogotá - Belencito | F65: CTSA-INGERAL | G65: 01/08/2025-31/08/2025 | H65: USO DE VÍA CARGA | I65: 980537.4 | K65: 9.19448 | O65: =ROUND(N65*0.004,0) -> 0 | P65: =(N65-O65) -> 0 | Q65: 1981352.8 | R65: 2025 | S65: OCT | T65: 45961 | U65: =+P65-Q65 -> -1981352.8
A66: 2025 | B66: =UPPER(TEXT(C66,"MMM")) -> AGO | C66: 45900 | D66: 508 | E66: Bogotá - Belencito | F66: TURISTREN | G66: 01/08/2025-31/08/2025 | H66: USO DE VÍA PASAJEROS | J66: 40892 | K66: 978.29 | L66: 40004235 | N66: 40004235 | O66: =ROUND(N66*0.004,0) -> 160017 | P66: =(N66-O66) -> 39844218 | Q66: =Tabla4[[#This Row],[Valor a Consignar a la ANI]] -> 39844218 | R66: 2025 | S66: OCT | T66: 45961 | U66: =+P66-Q66 -> 0
A67: 2025 | B67: =UPPER(TEXT(C67,"MMM")) -> AGO | C67: 45900 | D67: 509 | E67: Bogotá - Belencito | F67: ACERIAS PAZ DEL RIO | G67: 01/08/2025-31/08/2025 | H67: USO DE VÍA PASAJEROS | J67: 96 | K67: 978.29 | L67: 93915.84 | N67: 93915.84 | O67: =ROUND(N67*0.004,0) -> 376 | P67: =(N67-O67) -> 93539.84 | U67: =+P67-Q67 -> 93539.84
A68: 2025 | B68: =UPPER(TEXT(C68,"MMM")) -> SEP | C68: 45930 | D68: OC028 | E68: Bogotá - Belencito | F68: CTSA-INGERAL | G68: 01/09/2025-30/09/2025 | H68: USO DE VÍA CARGA | I68: 717230.05 | K68: 9.19448 | L68: 6596368.2 | N68: 6596368.2 | O68: =ROUND(N68*0.004,0) -> 26385 | P68: =(N68-O68) -> 6569983.2 | U68: =+P68-Q68 -> 6569983.2
A69: 2025 | B69: =UPPER(TEXT(C69,"MMM")) -> SEP | C69: 45930 | D69: 526 | E69: Bogotá - Belencito | F69: TURISTREN | G69: 01/09/2025-30/09/2025 | H69: USO DE VÍA PASAJEROS | J69: 35406 | K69: 978.29 | L69: 34637336 | N69: 34637336 | O69: =ROUND(N69*0.004,0) -> 138549 | P69: =(N69-O69) -> 34498787 | U69: =+P69-Q69 -> 34498787
A70: 2025 | B70: =UPPER(TEXT(C70,"MMM")) -> SEP | C70: 45930 | D70: 525 | E70: Bogotá - Belencito | F70: ACERIAS PAZ DEL RIO | G70: 01/09/2025-30/09/2025 | H70: USO DE VÍA PASAJEROS | J70: 392 | K70: 978.29 | L70: 383489.68 | N70: 383489.68 | O70: =ROUND(N70*0.004,0) -> 1534 | P70: =(N70-O70) -> 381955.68 | U70: =+P70-Q70 -> 381955.68
P71: =SUBTOTAL(109,Tabla4[Valor a Consignar a la ANI]) -> 3.4885063e+08 | Q71: =SUBTOTAL(109,Tabla4[Valor Pagado]) -> 2.8164842e+08 | U71: =SUBTOTAL(109,Tabla4[Valor Por Cobrar]) -> 67202216
A72: De acuerdo al Apéndice Técnico numeral 3.2.1 Otros Gastos "(..) En caso de incurrir en costos financieros, tasas y tributos a que haya lugar por el recaudo de los ingresos provenientes de bienes inmuebles o bienes muebles (equipos), estos costos se decantarán de los arriendos a consignar a la ANI, previa revisión de la Interventoría. (..)"
E73: Usuario de vía | F73: Facturado por CTSA INGERAL | G73: Recaudado por CTSA-INGERAL | H73: Consignado a la ANI | I73: Pendiente por pagar por terceros | J73: Observación
E74: =F16 -> TURISTREN | F74: =P69 -> 34498787 | I74: =U62+U54+U56+U58+U60+U66+U69 -> 52750814 | J74: 1. El saldo pendiente de pago está asociado a las facturas 396, 419, 443, 458 ,474, 508 y 526
E75: CTSA | F75: =P68 -> 6569983.2 | G75: =Q53 -> 9130835.3 | H75: =Q53 -> 9130835.3 | I75: =+U61+U55+U57+U59+U64+U68 -> 15551918 | J75: 1. Los fondos aún por cobrar están asociados a las facturas OC023 del mes de abril y OC024 del mes de mayo, OC025 del mes de junio de 2025, OC026 del mes de julio de 2025 ; OC027 de mes de agosto del 2025 y OC028 del mes de septiembre. 2.El importe consignado a la ANI corresponde a la factura OC022 del mes de marzo de 2025
E76: APDR | F76: =P70 -> 381955.68 | I76: =U63+U67+U70 -> 880836.16 | J76: 1. Los fondos aún por cobrar están asociados a la factura 475 del mes de julio del 2025; 509 del mes de agosto del 2025 y 525 del mes de septiembre
E77: Total | F77: =SUBTOTAL(9,F74:F76) -> 41450726 | G77: =SUBTOTAL(9,G74:G76) -> 9130835.3 | H77: =SUM(H74:H76) -> 9130835.3 | I77: =SUM(I74:I76) -> 69183569

Sheet Material rodante base
F2: Material rodante
A3: Etiquetas de fila | B3: Suma de Valor a Consignar a la ANI | C3: Suma de Valor Pagado | F3: Etiquetas de fila | G3: Suma de Valor Pagado
A4: 2023 | B4: 1.0680164e+08 | C4: 1.0680164e+08 | F4: 2023 | G4: 1.0680164e+08
A5: Consorcio CTSA-INGERAL | B5: 1.0680164e+08 | C5: 1.0680164e+08 | F5: JUN | G5: 14759305
A6: 2024 | B6: 1.8635279e+08 | C6: 1.5170825e+08 | F6: JUL | G6: 18449131
A7: Consorcio CTSA-INGERAL | B7: 1.8635279e+08 | C7: 1.5170825e+08 | F7: AGO | G7: 14759305
A8: 2025 | B8: 19178664 | F8: SEP | G8: 16604217
A9: Consorcio CTSA-INGERAL | B9: 19178664 | F9: OCT | G9: 14759305
A10: Total general | B10: 3.123331e+08 | C10: 2.5850989e+08 | F10: NOV | G10: 15150166
F11: DIC | G11: 12320214
F12: 2024 | G12: 1.5170825e+08
F13: ENE | G13: 16813221
F14: FEB | G14: 14389891
F15: MAR | G15: 11655292
F16: ABR | G16: 14805698
F17: MAY | G17: 13178594
F18: JUN | G18: 13812201
F19: JUL | G19: 14322432
F20: AGO | G20: 18432270
F21: SEP | G21: 17979918
F22: OCT | G22: 16318729
F23: NOV
F24: DIC
F25: 2025
F26: ENE
F27: Total general | G27: 2.5850989e+08

Sheet Uso de vía
A3: Etiquetas de fila | B3: Suma de Valor Pagado
A4: ENE | B4: 80433237
A5: 2024 | B5: 80433237
A6: FEB | B6: 29134095
A7: 2024 | B7: 29134095
A8: ABR | B8: 53250675
A9: 2024 | B9: 53250675
A10: MAY | B10: 86979758
A11: 2024 | B11: 86979758
A12: JUN | B12: 87681256
A13: 2023 | B13: 46542698
A14: 2024 | B14: 41138558
A15: JUL | B15: 96929029
A16: 2023 | B16: 67445380
A17: 2024 | B17: 29483649
A18: AGO | B18: 42648474
A19: 2023 | B19: 30967745
A20: 2024 | B20: 11680729
A21: SEP | B21: 33630550
A22: 2024 | B22: 33630550
A23: OCT | B23: 79005069
A24: 2023 | B24: 34846424
A25: 2024 | B25: 44158645
A26: NOV | B26: 1.3096301e+08
A27: 2023 | B27: 79024150
A28: 2024 | B28: 51938861
A29: Total general | B29: 7.2065515e+08

Sheet Materal rodante
A1: Año | B1: Mes | C1: Fecha | D1: # Factura | E1: Corredor | F1: Tercero | G1: Periodo | H1: Concepto | I1: # Toneladas | J1: Valor Facturado | K1: IVA | L1: Valor bruto | M1: 4 X 1000 | N1: Valor a Consignar a la ANI | O1: Valor consignado | P1: Valor Pagado | Q1: Año2 | R1: Mes3 | S1: Fecha4 | T1: Valor Por Cobrar
A2: =+YEAR(C2) -> 2023 | B2: =UPPER(TEXT(C2,"MMM")) -> JUN | C2: 45107 | D2: OC001 | E2: Bogotá - Belencito | F2: Consorcio CTSA-INGERAL | G2: 01/06/2023 - 30/06/2023 | H2: Arriendo material rodante informe OC001 | I2: 3117 | J2: 17634109 | K2: 2815530 | L2: 14818579 | M2: =ROUND(L2*0.004,0) -> 59274 | N2: 14759305 | O2: 14759305 | P2: 14759305 | Q2: =+YEAR(S2) -> 2023 | R2: =+MONTH(S2) -> 7 | S2: 45135 | T2: =N2-P2 -> 0
A3: =+YEAR(C3) -> 2023 | B3: =UPPER(TEXT(C3,"MMM")) -> JUL | C3: 45138 | D3: OC002 | E3: Bogotá - Belencito | F3: Consorcio CTSA-INGERAL | G3: 01/07/2023 - 30/07/2023 | H3: Arriendo material rodante informe OC002 | I3: 3905 | J3: 22042636 | K3: 3519412 | L3: 18523224 | M3: =ROUND(L3*0.004,0) -> 74093 | N3: =L3-M3 -> 18449131 | O3: 9224564 | P3: 9224564 | Q3: =+YEAR(S3) -> 2023 | R3: =+MONTH(S3) -> 7 | S3: 45135 | T3: =N3-P3 -> 9224567
A4: =+YEAR(C4) -> 2023 | B4: =UPPER(TEXT(C4,"MMM")) -> JUL | C4: 45138 | D4: OC002 | E4: Bogotá - Belencito | F4: Consorcio CTSA-INGERAL | G4: 01/07/2023 - 30/07/2023 | H4: Arriendo material rodante informe OC002 | J4: 0 | K4: 0 | L4: 0 | M4: =ROUND(L4*0.004,0) -> 0 | N4: =L4-M4 -> 0 | O4: 9224567 | P4: 9224567 | Q4: =+YEAR(S4) -> 2023 | R4: =+MONTH(S4) -> 8 | S4: 45142 | T4: =N4-P4 -> -9224567
A5: =+YEAR(C5) -> 2023 | B5: =UPPER(TEXT(C5,"MMM")) -> AGO | C5: 45169 | D5: OC003 | E5: Bogotá - Belencito | F5: Consorcio CTSA-INGERAL | G5: 01/08/2023 - 30/08/2023 | H5: Arriendo material rodante informe OC003 | I5: 3119 | J5: 17634109 | K5: 2815130 | L5: 14818579 | M5: =ROUND(L5*0.004,0) -> 59274 | N5: =L5-M5 -> 14759305 | O5: 9224564 | P5: 9224564 | Q5: =+YEAR(S5) -> 2023 | R5: =+MONTH(S5) -> 8 | S5: 45142 | T5: =N5-P5 -> 5534741
A6: =+YEAR(C6) -> 2023 | B6: =UPPER(TEXT(C6,"MMM")) -> AGO | C6: 45169 | D6: OC003 | E6: Bogotá - Belencito | F6: Consorcio CTSA-INGERAL | G6: 01/08/2023 - 30/08/2023 | H6: Arriendo material rodante informe OC003 | O6: 5534741 | P6: 5534741 | Q6: =+YEAR(S6) -> 2023 | R6: 11 | S6: 45233 | T6: =N6-P6 -> -5534741
A7: =+YEAR(C7) -> 2023 | B7: =UPPER(TEXT(C7,"MMM")) -> SEP | C7: 45199 | D7: OC004 | E7: Bogotá - Belencito | F7: Consorcio CTSA-INGERAL | G7: 01/092023 - 30/09/2023 | H7: Arriendo material rodante informe OC004 | I7: 3508 | J7: 19838372 | K7: 3167471 | L7: 16670901 | M7: =ROUND(L7*0.004,0) -> 66684 | N7: =L7-M7 -> 16604217 | O7: 16604217 | P7: 16604217 | Q7: =+YEAR(S7) -> 2023 | R7: 11 | S7: 45233 | T7: =N7-P7 -> 0
A8: =+YEAR(C8) -> 2023 | B8: =UPPER(TEXT(C8,"MMM")) -> OCT | C8: 45230 | D8: OC005 | E8: Bogotá - Belencito | F8: Consorcio CTSA-INGERAL | G8: 01/10/2023 - 30/10/2023 | H8: Arriendo material rodante informe OC005 | I8: 3124 | J8: 17634109 | K8: 2815530 | L8: 14818579 | M8: =ROUND(L8*0.004,0) -> 59274 | N8: =L8-M8 -> 14759305 | O8: =N8 -> 14759305 | P8: =O8 -> 14759305 | Q8: =+YEAR(S8) -> 2023 | R8: 11 | S8: 45260 | T8: =N8-P8 -> 0
A9: 2023 | B9: =UPPER(TEXT(C9,"MMM")) -> NOV | C9: 45260 | D9: OC006 | E9: Bogotá - Belencito | F9: Consorcio CTSA-INGERAL | G9: 01/11/2023 - 30/11/2023 | H9: Arriendo material rodante informe OC006 | I9: 3174 | J9: 18101102 | K9: 2890092 | L9: 15211010 | M9: =ROUND(L9*0.004,0) -> 60844 | N9: =L9-M9 -> 15150166 | O9: =N9 -> 15150166 | P9: =O9 -> 15150166 | Q9: 2024 | R9: 1 | S9: 45322 | T9: =N9-P9 -> 0
A10: 2023 | B10: =UPPER(TEXT(C10,"MMM")) -> DIC | C10: 45291 | D10: OC007 | E10: Bogotá - Belencito | F10: Consorcio CTSA-INGERAL | G10: 01/12/2023 - 30/12/2023 | H10: Arriendo material rodante informe OC007 | I10: 3332 | J10: 14720054 | K10: 2350361 | L10: =J10-K10 -> 12369693 | M10: =ROUND(L10*0.004,0) -> 49479 | N10: =L10-M10 -> 12320214 | O10: =N10 -> 12320214 | P10: =O10 -> 12320214 | Q10: 2024 | R10: 1 | S10: 45322 | T10: =N10-P10 -> 0
A11: 2024 | B11: =UPPER(TEXT(C11,"MMM")) -> ENE | C11: 45322 | D11: OC008 | E11: Bogotá - Belencito | F11: Consorcio CTSA-INGERAL | G11: 01/1/2024 - 30/1/2024 | H11: Arriendo material rodante informe OC008 | I11: 3415.66 | J11: 20088086 | K11: 3207341 | L11: 16880744 | M11: =ROUND(L11*0.004,0) -> 67523 | N11: =L11-M11 -> 16813221 | O11: =N11 -> 16813221 | P11: =O11 -> 16813221 | Q11: 2024 | R11: 2 | S11: 45348 | T11: =N11-P11 -> 0
A12: 2024 | B12: =UPPER(TEXT(C12,"MMM")) -> FEB | C12: 45351 | D12: OC009 | E12: Bogotá - Belencito | F12: Consorcio CTSA-INGERAL | G12: 01/2/2024 - 29/2/2024 | H12: Arriendo material rodante informe OC009 | I12: 5200.31 | J12: 17192742 | K12: 2745060 | L12: 14447682 | M12: =ROUND(L12*0.004,0) -> 57791 | N12: =L12-M12 -> 14389891 | O12: 14389891 | P12: 14389891 | Q12: 2024 | R12: 4 | S12: 45383 | T12: =N12-P12 -> 0
A13: 2024 | B13: =UPPER(TEXT(C13,"MMM")) -> MAR | C13: 45382 | D13: OC010 | E13: Bogotá - Belencito | F13: Consorcio CTSA-INGERAL | G13: 01/3/2024 - 31/3/2024 | H13: Arriendo material rodante informe OC010 | I13: 5074.38 | J13: 13925499 | K13: 2223399 | L13: 11702100 | M13: =ROUND(L13*0.004,0) -> 46808 | N13: =L13-M13 -> 11655292 | O13: 11655292 | P13: 11655292 | Q13: 2024 | R13: 4 | S13: 45412 | T13: =N13-P13 -> 0
A14: 2024 | B14: =UPPER(TEXT(C14,"MMM")) -> ABR | C14: 45412 | D14: OC011 | E14: Bogotá - Belencito | F14: Consorcio CTSA-INGERAL | G14: 01/4/2024 - 30/4/2024 | H14: Arriendo material rodante informe OC011 | I14: 6888.5 | J14: 17689540 | K14: 2824830.3 | L14: 14865159 | M14: =ROUND(L14*0.004,0) -> 59461 | N14: =L14-M14 -> 14805698 | O14: =N14 -> 14805698 | P14: =O14 -> 14805698 | Q14: 2024 | R14: 5 | S14: 45440 | T14: =N14-P14 -> 0
A15: 2024 | B15: =UPPER(TEXT(C15,"MMM")) -> MAY | C15: 45443 | D15: OC012 | E15: Bogotá - Belencito | F15: Consorcio CTSA-INGERAL | G15: 01/5/2024 - 31/5/2024 | H15: Arriendo material rodante informe OC012 | I15: 5026.58 | J15: 15745509 | K15: 2513988.9 | L15: 13231520 | M15: =ROUND(L15*0.004,0) -> 52926 | N15: =L15-M15 -> 13178594 | O15: 13178594 | P15: 13178594 | Q15: 2024 | R15: 6 | S15: 45469 | T15: =N15-P15 -> 0
A16: 2024 | B16: =UPPER(TEXT(C16,"MMM")) -> JUN | C16: 45473 | D16: OC013 | E16: Bogotá - Belencito | F16: Consorcio CTSA-INGERAL | G16: 01/6/2024 - 30/6/2024 | H16: Arriendo material rodante informe OC013 | I16: 5474.64 | J16: 16502529 | K16: 2634857.6 | L16: 13867672 | M16: =ROUND(L16*0.004,0) -> 55471 | N16: =L16-M16 -> 13812201 | O16: 13812201 | P16: =N16 -> 13812201 | Q16: 2024 | R16: 7 | S16: 45504 | T16: =N16-P16 -> 0
A17: 2024 | B17: =UPPER(TEXT(C17,"MMM")) -> JUL | C17: 45504 | D17: OC014 | E17: Bogotá - Belencito | F17: Consorcio CTSA-INGERAL | G17: 01/7/2024 - 31/7/2024 | H17: Arriendo material rodante informe OC014 | I17: 5660.16 | J17: 17043694 | K17: 2721262.1 | L17: 14322432 | M17: =ROUND(L17*0.004,0) -> 57290 | N17: 14322432 | O17: 14322432 | P17: =N17 -> 14322432 | Q17: 2024 | R17: 8 | S17: 45533 | T17: =N17-P17 -> 0
A18: 2024 | B18: =UPPER(TEXT(C18,"MMM")) -> AGO | C18: 45535 | D18: OC015 | E18: Bogotá - Belencito | F18: Consorcio CTSA-INGERAL | G18: 01/8/2024 - 31/8/2024 | H18: Arriendo material rodante informe OC015 | I18: 4295.28 | J18: 22022491 | K18: 3516196 | L18: 18506295 | M18: =ROUND(L18*0.004,0) -> 74025 | N18: =L18-M18 -> 18432270 | O18: 18432270 | P18: 18432270 | Q18: 2024 | R18: 9 | S18: 45565 | T18: =N18-P18 -> 0
A19: 2024 | B19: =UPPER(TEXT(C19,"MMM")) -> SEP | C19: 45565 | D19: OC016 | E19: Bogotá - Belencito | F19: Consorcio CTSA-INGERAL | G19: 01/9/2024 - 30/9/2024 | H19: Arriendo material rodante informe OC016 | I19: 5451.34 | J19: 21482032 | K19: 3429904.2 | L19: 18052127 | M19: =ROUND(L19*0.004,0) -> 72209 | N19: =L19-M19 -> 17979918 | O19: 17979918 | P19: 17979918 | Q19: 2024 | R19: 10 | S19: 45596 | T19: =N19-P19 -> 0
A20: 2024 | B20: =UPPER(TEXT(C20,"MMM")) -> OCT | C20: 45596 | D20: OC017 | E20: Bogotá - Belencito | F20: Consorcio CTSA-INGERAL | G20: 01/10/2024 - 31/10/2024 | H20: Arriendo material rodante informe OC017 | I20: 5365.159 | J20: 19497277 | K20: 3113010.6 | L20: 16384266 | M20: =ROUND(L20*0.004,0) -> 65537 | N20: =L20-M20 -> 16318729 | O20: 16318729 | P20: 16318729 | Q20: 2024 | R20: 11 | S20: 45623 | T20: =N20-P20 -> 0
A21: 2024 | B21: =UPPER(TEXT(C21,"MMM")) -> NOV | C21: 45626 | D21: OC018 | E21: Bogotá - Belencito | F21: Consorcio CTSA-INGERAL | G21: 01/11/2024 - 30/11/2024 | H21: Arriendo material rodante informe OC018 | I21: 2827.26 | J21: 22599152 | K21: 3608268 | L21: 18990884 | M21: =ROUND(L21*0.004,0) -> 75964 | N21: =L21-M21 -> 18914920 | O21: 18914920 | P21: 18914920 | Q21: 2025 | R21: 2 | S21: 45714 | T21: =N21-P21 -> 0
A22: 2024 | B22: =UPPER(TEXT(C22,"MMM")) -> DIC | C22: 45657 | D22: OC019 | E22: Bogotá - Belencito | F22: Consorcio CTSA-INGERAL | G22: 01/12/2024 - 31/12/2024 | H22: Arriendo material rodante informe OC019 | I22: 3153.53 | J22: 18793426 | K22: 3000631 | L22: 15792795 | M22: =ROUND(L22*0.004,0) -> 63171 | N22: =L22-M22 -> 15729624 | O22: 15729624 | P22: =Tabla2[[#This Row],[Valor a Consignar a la ANI]] -> 15729624 | Q22: 2025 | R22: 4 | S22: 45770 | T22: =N22-P22 -> 0
A23: 2025 | B23: =UPPER(TEXT(C23,"MMM")) -> ENE | C23: 45688 | D23: OC020 | E23: Bogotá - Belencito | F23: Consorcio CTSA-INGERAL | G23: 01/1/2025 - 31/1/2025 | H23: Arriendo material rodante informe OC020 | I23: 2693.64 | J23: 22914268 | K23: =J23-J23/1.19 -> 3658580.5 | L23: =J23-K23 -> 19255687 | M23: =ROUND(L23*0.004,0) -> 77023 | N23: =L23-M23 -> 19178664 | O23: =Tabla2[[#This Row],[Valor a Consignar a la ANI]] -> 19178664 | P23: =Tabla2[[#This Row],[Valor consignado]] -> 19178664 | Q23: 2025 | R23: 7 | S23: 45845 | T23: =N23-P23 -> 0
A24: 2025 | B24: =UPPER(TEXT(C24,"MMM")) -> FEB | C24: 45716 | D24: OC021 | E24: Bogotá - Belencito | F24: Consorcio CTSA-INGERAL | G24: 01/2/2025 - 28/2/2025 | H24: Arriendo material rodante informe OC021 | I24: 3918.32 | J24: 21676517 | K24: =J24-J24/1.19 -> 3460956.5 | L24: =J24-K24 -> 18215561 | M24: =ROUND(L24*0.004,0) -> 72862 | N24: =L24-M24 -> 18142699 | O24: =Tabla2[[#This Row],[Valor a Consignar a la ANI]] -> 18142699 | P24: =Tabla2[[#This Row],[Valor consignado]] -> 18142699 | Q24: 2025 | R24: 8 | S24: 45873 | T24: =N24-P24 -> 0
A25: 2025 | B25: =UPPER(TEXT(C25,"MMM")) -> MAR | C25: 45747 | D25: OC022 | E25: Bogotá - Belencito | F25: Consorcio CTSA-INGERAL | G25: 01/3/2025 - 31/3/2025 | H25: Arriendo material rodante informe OC022 | I25: 3878.57 | J25: 25340779 | K25: 4046006.7 | L25: =J25-K25 -> 21294772 | M25: =ROUND(L25*0.004,0) -> 85179 | N25: =L25-M25 -> 21209593 | O25: 21209593 | P25: 21209593 | Q25: 2025 | R25: 9 | S25: 45904 | T25: =N25-P25 -> 0
A26: 2025 | B26: =UPPER(TEXT(C26,"MMM")) -> ABR | C26: 45777 | D26: OC023 | E26: Bogotá - Belencito | F26: Consorcio CTSA-INGERAL | G26: 01/4/2025 - 30/4/2025 | H26: Arriendo material rodante informe OC023 | I26: 3101.91 | J26: 20272623 | K26: 3236805.4 | L26: =J26-K26 -> 17035818 | M26: =ROUND(L26*0.004,0) -> 68143 | N26: =L26-M26 -> 16967675 | O26: 16767675 | P26: 16967675 | Q26: 2025 | R26: 10 | S26: 45932 | T26: =N26-P26 -> 0
A27: 2025 | B27: =UPPER(TEXT(C27,"MMM")) -> MAY | C27: 45808 | D27: OC024 | E27: Bogotá - Belencito | F27: Consorcio CTSA-INGERAL | G27: 01/5/2025 - 31/5/2025 | H27: Arriendo material rodante informe OC024 | I27: 4128.11 | J27: 26462981 | K27: 4225181.9 | L27: =J27-K27 -> 22237799 | M27: =ROUND(L27*0.004,0) -> 88951 | N27: =L27-M27 -> 22148848 | O27: 22148848 | P27: 22148848 | Q27: 2025 | R27: 10 | S27: 45938 | T27: =N27-P27 -> 0
A28: 2025 | B28: =UPPER(TEXT(C28,"MMM")) -> JUN | C28: 45838 | D28: OC025 | E28: Bogotá - Belencito | F28: Consorcio CTSA-INGERAL | G28: 01/6/2025 - 30/6/2025 | H28: Arriendo material rodante informe OC025 | I28: 8022 | J28: 14642721 | K28: 2337913.4 | L28: =J28-K28 -> 12304808 | M28: =ROUND(L28*0.004,0) -> 49219 | N28: =L28-M28 -> 12255589 | O28: 12255589 | P28: 12255589 | Q28: 2025 | R28: 10 | S28: 45961 | T28: =N28-P28 -> 0
A29: 2025 | B29: =UPPER(TEXT(C29,"MMM")) -> JUL | C29: 45869 | D29: OC026 | E29: Bogotá - Belencito | F29: Consorcio CTSA-INGERAL | G29: 01/7/2025 - 31/7/2025 | H29: Arriendo material rodante informe OC026 | I29: 8071.19 | J29: 14064109 | K29: 2245529.9 | L29: =J29-K29 -> 11818579 | M29: =ROUND(L29*0.004,0) -> 47274 | N29: =L29-M29 -> 11771305 | O29: 11771305 | P29: 11771305 | Q29: 2025 | R29: 10 | S29: 45961 | T29: =N29-P29 -> 0
A30: 2025 | B30: =UPPER(TEXT(C30,"MMM")) -> AGO | C30: 45900 | D30: OC027 | E30: Bogotá - Belencito | F30: Consorcio CTSA-INGERAL | G30: 01/8/2025 - 31/8/2025 | H30: Arriendo material rodante informe OC027 | I30: 9566.4 | J30: 14222747 | K30: 2270858.7 | L30: =J30-K30 -> 11951888 | M30: =ROUND(L30*0.004,0) -> 47808 | N30: =L30-M30 -> 11904080 | T30: =N30-P30 -> 11904080
A31: 2025 | B31: =UPPER(TEXT(C31,"MMM")) -> SEP | C31: 45930 | D31: OC028 | E31: Bogotá - Belencito | F31: Consorcio CTSA-INGERAL | G31: 01/9/2025 - 30/9/2025 | H31: Arriendo material rodante informe OC028 | I31: 4338.15 | J31: 17867713 | K31: 2852828.1 | L31: 15014885 | M31: =ROUND(L31*0.004,0) -> 60060 | N31: =L31-M31 -> 14954825 | T31: =N31-P31 -> 14954825
N32: =SUBTOTAL(109,Tabla2[Valor a Consignar a la ANI]) -> 4.4168771e+08 | P32: =SUBTOTAL(109,Tabla2[Valor Pagado]) -> 4.1482881e+08 | T32: =SUM(T2:T31) -> 26858905
N34: Usuario de vía | O34: Facturado por CTSA-INGERAL | P34: Recaudado por CTSA-INGERAL | Q34: Consignado a la ANI | R34: Pendiente por cobro | S34: Observación
N35: CTSA | O35: =N31 -> 14954825 | P35: =P25 -> 21209593 | Q35: =P25 -> 21209593 | R35: =+T26+T27+T28+T29+T30+T31 -> 26858905 | S35: 1. Los fondos aún por cobrar están asociados a las facturas, OC023 del mes de abril, OC024 del mes de mayo, OC025 del mes de junio de 2025, OC026 del mes de julio del 2025; OC027 del mes de agosto del 2025 y OC028 del mes de septiembre 2. El importe consignado a la ANI pertenece a la factura OC022 de marzo de 2025
N36: Total | O36: =SUM(O35) -> 14954825 | P36: =SUM(P35) -> 21209593 | Q36: =Q35 -> 21209593 | R36: =R35 -> 26858905

Sheet Operacion comercial 
C2: Operación Comercial
A7: Los valores aquí presentados pertenecen a los valores brutos.

Sheet Base de datos O.P
A1: N° Servicio | B1: Mes | C1: AÑO | D1: Configuración Tren | E1: Fecha Salida | F1: Fecha llegada | G1: Días | H1: Cantidad Locomotoras | I1: V/r Alquiler locomotoras | J1: Cantidad plataformas | K1: V/r Alquiler plataformas | L1: V/r Alquiler Mat. Rodante | M1: Toneladas Transportad. | N1: Km recorridos | O1: Ton-km | P1: V/r Importe Uso de Vía | Q1: Remisión No. | R1: Recorrido Locomotras Trabajando | S1: Cantidad Combustible Consumido | T1: V/r Combustible | U1: Factura | V1: Columna1
A2: 1 | B2: =UPPER((TEXT(Tabla3[[#This Row],[Fecha llegada]],"MMM"))) -> ENE | C2: =YEAR(Tabla3[[#This Row],[Fecha llegada]]) -> 2024 | D2: Loc. 1034-1001 Plat. 4083,4071,4095,4069,4061,4003,4060,4146, 4124,4120,4151,4104,4162,4159 | E2: 45297 | F2: 45298 | G2: 2 | H2: 2 | I2: 1303630.7 | J2: 14 | K2: 720587.18 | L2: 2024217.9 | M2: 388 | N2: 257 | O2: =M2*N2 -> 99716 | P2: 871757.16 | Q2: REMISION ARGOS RPSM-00299788 | R2: 614 | S2: 491.2 | T2: 4015324.2 | U2: OC008
A3: 2 | B3: =UPPER((TEXT(Tabla3[[#This Row],[Fecha llegada]],"MMM"))) -> ENE | C3: =YEAR(Tabla3[[#This Row],[Fecha llegada]]) -> 2024 | D3: Loc. 1034-1012 Plat. 4003,4100,4079,4087,4068,405,4031,4007, 4002,4072,4061,4060,4069,4010 | E3: 45301 | F3: 45302 | G3: 2 | H3: 2 | I3: 1303630.7 | J3: 14 | K3: 720587.18 | L3: 2024217.9 | M3: 390.78 | N3: 257 | O3: =M3*N3 -> 100430.46 | P3: 878003.25 | Q3: REMISION ARGOS RPSM-00299890 | R3: 614 | S3: 491.2 | T3: 4015324.2 | U3: OC008
A4: 3 | B4: =UPPER((TEXT(Tabla3[[#This Row],[Fecha llegada]],"MMM"))) -> ENE | C4: =YEAR(Tabla3[[#This Row],[Fecha llegada]]) -> 2024 | D4: Loc. 1034-1012 Plat. 4072,4061,4060,4048,4083,4071,4095,4073, 4010,4007,4002,4018,4102,4001 | E4: 45303 | F4: 45304 | G4: 2 | H4: 2 | I4: 1303630.7 | J4: 14 | K4: 720587.18 | L4: 2024217.9 | M4: 389.55 | N4: 257 | O4: =M4*N4 -> 100114.35 | P4: 875239.69 | Q4: REMISION ARGOS RPSM-00300031 | R4: 614 | S4: 491.2 | T4: 4015324.2 | U4: OC008
A5: 4 | B5: =UPPER((TEXT(Tabla3[[#This Row],[Fecha llegada]],"MMM"))) -> ENE | C5: =YEAR(Tabla3[[#This Row],[Fecha llegada]]) -> 2024 | D5: Loc. 1034-1012 Plat. 4071,4095,4003,4100,4079,4087,4001,4002, 4018,4102,4083,408,4053,4069 | E5: 45306 | F5: 45307 | G5: 2 | H5: 2 | I5: 1303630.7 | J5: 14 | K5: 720587.18 | L5: 2024217.9 | M5: 389.55 | N5: 257 | O5: =M5*N5 -> 100114.35 | P5: 875239.69 | Q5: REMISION ARGOS RPSM-00300173 | R5: 614 | S5: 491.2 | T5: 4015324.2 | U5: OC008
A6: 5 | B6: =UPPER((TEXT(Tabla3[[#This Row],[Fecha llegada]],"MMM"))) -> ENE | C6: =YEAR(Tabla3[[#This Row],[Fecha llegada]]) -> 2024 | D6: Loc. 1034-1012 Plat. 4071,4095,4087,,4001,4072,4061,4060,4048, 4073,4010,4007,4003,4079,4100 | E6: 45308 | F6: 45309 | G6: 2 | H6: 2 | I6: 1303630.7 | J6: 14 | K6: 720587.18 | L6: 2024217.9 | M6: 387.1 | N6: 257 | O6: =M6*N6 -> 99484.7 | P6: 869735.04 | Q6: REMISION ARGOS RPSM-00300352 | R6: 614 | S6: 491.2 | T6: 4015324.2 | U6: OC008
A7: 6 | B7: =UPPER((TEXT(Tabla3[[#This Row],[Fecha llegada]],"MMM"))) -> ENE | C7: =YEAR(Tabla3[[#This Row],[Fecha llegada]]) -> 2024 | D7: Loc. 1001 Plat. 4173,4159,4162,4104,4151,4146,4120,4124 | E7: 45314 | F7: 45315 | G7: 1 | H7: 1 | I7: 438442.96 | J7: 8 | K7: 248558.43 | L7: 687001.39 | M7: 300.8 | N7: 18.75 | O7: =M7*N7 -> 5640 | P7: 49307.136 | Q7: T1 01 | R7: 37.5 | S7: 30 | T7: 245235.6 | U7: OC008
A8: 7 | B8: =UPPER((TEXT(Tabla3[[#This Row],[Fecha llegada]],"MMM"))) -> ENE | C8: =YEAR(Tabla3[[#This Row],[Fecha llegada]]) -> 2024 | D8: Loc. 1044-1012 Plat. 4061,4060,40002,4018,4102,4083,4068,4053,4001,4003,4079,4103,4072,4069 | E8: 45315 | F8: 45316 | G8: 2 | H8: 2 | I8: 1303630.7 | J8: 14 | K8: 720587.18 | L8: 2024217.9 | M8: 389.55 | N8: 257 | O8: =M8*N8 -> 100114.35 | P8: 875239.69 | Q8: REMISION ARGOS RPSM-00300803 | R8: 614 | S8: 491.2 | T8: 4015324.2 | U8: OC008
A9: 8 | B9: =UPPER((TEXT(Tabla3[[#This Row],[Fecha llegada]],"MMM"))) -> ENE | C9: =YEAR(Tabla3[[#This Row],[Fecha llegada]]) -> 2024 | D9: Loc. 1044-1001 Plat. 4072,4102,4083,4068,4087,4048,4073,4010, 4007,4053,4071,4095,4061,4060 | E9: 45317 | F9: 45318 | G9: 2 | H9: 2 | I9: 1303630.7 | J9: 14 | K9: 720587.18 | L9: 2024217.9 | M9: 388.33 | N9: 257 | O9: =M9*N9 -> 99800.81 | P9: 872498.6 | Q9: REMISION ARGOS RPSM-00300992 | R9: 614 | S9: 491.2 | T9: 4015324.2 | U9: OC008
A10: 9 | B10: =UPPER((TEXT(Tabla3[[#This Row],[Fecha llegada]],"MMM"))) -> ENE | C10: =YEAR(Tabla3[[#This Row],[Fecha llegada]]) -> 2024 | D10: Loc. 1044-1001 Plat. 4053,4071,4095,4061,4002,4018,4003,4079, 4060,4072,4102,4083,4068,4103 | E10: 45320 | F10: 45321 | G10: 2 | H10: 2 | I10: 1303630.7 | J10: 14 | K10: 720587.18 | L10: 2024217.9 | M10: 392 | N10: 257 | O10: =M10*N10 -> 100744 | P10: 880744.35 | Q10: REMISION ARGOS RPSM-00301142 | R10: 614 | S10: 491.2 | T10: 4015324.2 | U10: OC008
A11: 10 | B11: =UPPER((TEXT(Tabla3[[#This Row],[Fecha llegada]],"MMM"))) -> FEB | C11: =YEAR(Tabla3[[#This Row],[Fecha llegada]]) -> 2024 | D11: Loc. 1001-1044 Plat.4060,4102,4083,4068,4087,4048,4073,4010,4007,4103,4053,4071,4095,4061 | E11: 45323 | F11: 45324 | G11: 2 | H11: 2 | I11: 853498.11 | J11: 14 | K11: 571220.7 | L11: 1424718.8 | M11: 390.78 | N11: 257 | O11: =M11*N11 -> 100430.46 | P11: 878003.25 | Q11: REMISION ARGOS RPSM-00301406 | R11: 614 | S11: 491.2 | T11: 4015324.2 | U11: OC009
A12: 11 | B12: =UPPER((TEXT(Tabla3[[#This Row],[Fecha llegada]],"MMM"))) -> FEB | C12: =YEAR(Tabla3[[#This Row],[Fecha llegada]]) -> 2024 | D12: Loc. 1001-1044 Plat. 4159,4162,4104,4151,4146,4120,4124 | E12: 45333 | F12: 45334 | G12: 1 | H12: 0 | J12: 7 | K12: 316591.02 | L12: 316591.02 | M12: 246.78 | N12: 212.6 | O12: =M12*N12 -> 52465.428 | P12: 458673.76 | Q12: T1-67 | R12: 212.6 | S12: 170.08 | T12: 1390322.4 | U12: OC009
A13: 12 | B13: =UPPER((TEXT(Tabla3[[#This Row],[Fecha llegada]],"MMM"))) -> FEB | C13: =YEAR(Tabla3[[#This Row],[Fecha llegada]]) -> 2024 | D13: Loc. 1001-1044 Plat. 4060,4063,4068,4002,4018,4003,4049,4124,4120,4146, 4151,4104,4162,4159 | E13: 45334 | F13: 45335 | G13: 2 | H13: 2 | I13: 853498.11 | J13: 14 | K13: 571220.7 | L13: 1424718.8 | M13: 389.55 | N13: 257 | O13: =M13*N13 -> 100114.35 | P13: 875239.69 | Q13: REMISION ARGOS RPSM-00302182 | R13: 357 | S13: 285.6 | T13: 2334642.9 | U13: OC009
A14: 13 | B14: =UPPER((TEXT(Tabla3[[#This Row],[Fecha llegada]],"MMM"))) -> FEB | C14: =YEAR(Tabla3[[#This Row],[Fecha llegada]]) -> 2024 | D14: Loc. 1034-1044 Plat. 4072,4056,4060,4083,4073,4010,4007,4095,4068,4002, 4018,4003,4049,4100 | E14: 45336 | F14: 45337 | G14: 2 | H14: 2 | I14: 853498.11 | J14: 14 | K14: 571220.7 | L14: 1424718.8 | M14: 388.33 | N14: 257 | O14: =M14*N14 -> 99800.81 | P14: 872498.6 | Q14: REMISION ARGOS RPSM-00302340 | R14: 614 | S14: 491.2 | T14: 4015324.2 | U14: OC009
A15: 14 | B15: =UPPER((TEXT(Tabla3[[#This Row],[Fecha llegada]],"MMM"))) -> FEB | C15: =YEAR(Tabla3[[#This Row],[Fecha llegada]]) -> 2024 | D15: Loc. 1044-1034 Plat. 4159,4162,4104,4151,4146,4120,4124 | E15: 45337 | F15: 45338 | G15: 1 | H15: 0 | I15: 0 | J15: 7 | K15: 316591.02 | L15: 316591.02 | M15: 257.66 | N15: 212.6 | O15: =M15*N15 -> 54778.516 | P15: 478895.7 | Q15: T1-69 | R15: 212.6 | S15: 170.08 | T15: 1390322.4 | U15: OC009
A16: 15 | B16: =UPPER((TEXT(Tabla3[[#This Row],[Fecha llegada]],"MMM"))) -> FEB | C16: =YEAR(Tabla3[[#This Row],[Fecha llegada]]) -> 2024 | D16: Loc. 1034-1001 Plat. 4095,4068,4002,4018,4003,4049,4100,4151,4104,4162, 4159,4124,4120,4146 | E16: 45338 | F16: 45339 | G16: 2 | H16: 2 | I16: 853498.11 | J16: 14 | K16: 571220.7 | L16: 1424718.8 | M16: 389.55 | N16: 257 | O16: =M16*N16 -> 100114.35 | P16: 875239.69 | Q16: REMISION ARGOS RPSM-00302515 | R16: 357 | S16: 285.6 | T16: 2334642.9 | U16: OC009
A17: 16 | B17: =UPPER((TEXT(Tabla3[[#This Row],[Fecha llegada]],"MMM"))) -> FEB | C17: =YEAR(Tabla3[[#This Row],[Fecha llegada]]) -> 2024 | D17: Loc. 1012-1044 Plat. 4159,4162,4104,4151,4146,4120,4124 | E17: 45340 | F17: 45341 | G17: 1 | H17: 0 | I17: 0 | J17: 9 | K17: 407045.59 | L17: 407045.59 | M17: 355.11 | N17: 212.6 | O17: =M17*N17 -> 75496.386 | P17: 660019.6 | Q17: T1-70 | R17: 212.6 | S17: 170.08 | T17: 1390322.4 | U17: OC009
A18: 17 | B18: =UPPER((TEXT(Tabla3[[#This Row],[Fecha llegada]],"MMM"))) -> FEB | C18: =YEAR(Tabla3[[#This Row],[Fecha llegada]]) -> 2024 | D18: Loc. 1012-1034 Plat. 4010,4007,4056,4060,4083,4159,4124,4120,4146,4071, 4048,415134104,4162 | E18: 45341 | F18: 45342 | G18: 2 | H18: 2 | I18: 853498.11 | J18: 14 | K18: 571220.7 | L18: 1424718.8 | M18: 389.55 | N18: 257 | O18: =M18*N18 -> 100114.35 | P18: 875239.69 | Q18: REMISION ARGOS RPSM-00302684 | R18: 357 | S18: 285.6 | T18: 2334642.9 | U18: OC009
A19: 18 | B19: =UPPER((TEXT(Tabla3[[#This Row],[Fecha llegada]],"MMM"))) -> FEB | C19: =YEAR(Tabla3[[#This Row],[Fecha llegada]]) -> 2024 | D19: Loc. 1012-1044 Plat. 414,4151,4048,4071,4146,4120,4124,4159 | E19: 45342 | F19: 45343 | G19: 1 | H19: 0 | I19: 0 | J19: 8 | K19: 361818.3 | L19: 361818.3 | M19: 288.3 | N19: 212.6 | O19: =M19*N19 -> 61292.58 | P19: 535844.25 | Q19: T1-71 | R19: 212.6 | S19: 170.08 | T19: 1390322.4 | U19: OC009
A20: 19 | B20: =UPPER((TEXT(Tabla3[[#This Row],[Fecha llegada]],"MMM"))) -> FEB | C20: =YEAR(Tabla3[[#This Row],[Fecha llegada]]) -> 2024 | D20: Loc. 1012-1044 Plat. 4159,4124,4120,4146,4071,4048,4151,4104,4056,4060,4083,4060,4083,4049,4100,4073 | E20: 45343 | F20: 45344 | G20: 2 | H20: 2 | I20: 853498.11 | J20: 14 | K20: 571220.7 | L20: 1424718.8 | M20: 390.78 | N20: 257 | O20: =M20*N20 -> 100430.46 | P20: 878003.25 | Q20: REMISION ARGOS RPSM-00302883 | R20: 357 | S20: 285.6 | T20: 2334642.9 | U20: OC009
A21: 20 | B21: =UPPER((TEXT(Tabla3[[#This Row],[Fecha llegada]],"MMM"))) -> FEB | C21: =YEAR(Tabla3[[#This Row],[Fecha llegada]]) -> 2024 | D21: Loc. 1012-1044 Plat. 4104,4151,4048,4162,4146,4120,4124,4159 | E21: 45344 | F21: 45345 | G21: 1 | H21: 0 | I21: 0 | J21: 8 | K21: 361818.3 | L21: 361818.3 | M21: 277.84 | N21: 212.6 | O21: =M21*N21 -> 59068.784 | P21: 516402.94 | Q21: T1-72 | R21: 212.6 | S21: 170.08 | T21: 1390322.4 | U21: OC009
A22: 21 | B22: =UPPER((TEXT(Tabla3[[#This Row],[Fecha llegada]],"MMM"))) -> FEB | C22: =YEAR(Tabla3[[#This Row],[Fecha llegada]]) -> 2024 | D22: Loc. 1012-1044 Plat. 4049,4100,4073,4003,4010,4007,4048,4151,4104,4159, 4124,4120,4146,4162 | E22: 45345 | F22: 45346 | G22: 2 | H22: 2 | I22: 853498.11 | J22: 14 | K22: 571220.7 | L22: 1424718.8 | M22: 388.55 | N22: 257 | O22: =M22*N22 -> 99857.35 | P22: 872992.9 | Q22: REMISION ARGOS RPSM-00303052 | R22: 357 | S22: 285.6 | T22: 2334642.9 | U22: OC009
A23: 22 | B23: =UPPER((TEXT(Tabla3[[#This Row],[Fecha llegada]],"MMM"))) -> FEB | C23: =YEAR(Tabla3[[#This Row],[Fecha llegada]]) -> 2024 | D23: Loc. 1012-1044 Plat. 4159,4162,4104,4151,4048,4071,4120,4124 | E23: 45347 | F23: 45348 | G23: 1 | H23: 0 | I23: 0 | J23: 8 | K23: 361818.3 | L23: 361818.3 | M23: 331.99 | N23: 212.6 | O23: =M23*N23 -> 70581.074 | P23: 617047.98 | Q23: T1-73 | R23: 212.6 | S23: 170.08 | T23: 1390322.4 | U23: OC009
A24: 23 | B24: =UPPER((TEXT(Tabla3[[#This Row],[Fecha llegada]],"MMM"))) -> FEB | C24: =YEAR(Tabla3[[#This Row],[Fecha llegada]]) -> 2024 | D24: Loc. 1012-1044 Plat. 4100,4073,4003,4056,4060,4083,4071,4104,4159,4151, 4124,4120,4162,4048 | E24: 45348 | F24: 45349 | G24: 2 | H24: 2 | I24: 853498.11 | J24: 14 | K24: 571220.7 | L24: 1424718.8 | M24: 389.55 | N24: 257 | O24: =M24*N24 -> 100114.35 | P24: 875239.69 | Q24: REMISION ARGOS RPSM-00303204 | R24: 357 | S24: 285.6 | T24: 2334642.9 | U24: OC009
A25: 24 | B25: =UPPER((TEXT(Tabla3[[#This Row],[Fecha llegada]],"MMM"))) -> FEB | C25: =YEAR(Tabla3[[#This Row],[Fecha llegada]]) -> 2024 | D25: Loc. 1044 Plat. 4159,4162,4104,4151,4146,4120,4124,4048,4071,4001,4018 | E25: 45350 | F25: 45351 | G25: 1 | H25: 2 | I25: 426749.05 | J25: 11 | K25: 497500.17 | L25: 924249.22 | M25: 325.99 | N25: 212.6 | O25: =M25*N25 -> 69305.474 | P25: 605896.18 | Q25: T1-74 | R25: 212.6 | S25: 170.08 | T25: 1390322.4 | U25: OC009
A26: 25 | B26: =UPPER((TEXT(Tabla3[[#This Row],[Fecha llegada]],"MMM"))) -> MAR | C26: =YEAR(Tabla3[[#This Row],[Fecha llegada]]) -> 2024 | D26: Loc. 1012-1034 Plat. 4071.4048.4162.4120.4124.4151.4018.4146.4001.4159. 4104,4100,4003,4073 | E26: 45352 | F26: 45353 | G26: 1 | H26: 2 | I26: 426749.05 | J26: 14 | K26: 285610.35 | L26: 712359.4 | M26: 388.33 | N26: 257 | O26: 99800.81 | P26: 872498.6 | Q26: REMISION ARGOS RPSM-00303538 | R26: 614 | S26: 491.2 | T26: 4081302.2 | U26: OC010
A27: 26 | B27: =UPPER((TEXT(Tabla3[[#This Row],[Fecha llegada]],"MMM"))) -> MAR | C27: =YEAR(Tabla3[[#This Row],[Fecha llegada]]) -> 2024 | D27: Loc. 1012-1034 Plat. 4071.4048.4162.4120.4124.4151.4018.4146.4001.4159.4104 | E27: 45354 | F27: 45355 | G27: 1 | H27: 2 | I27: 426749.05 | J27: 11 | K27: 497500.17 | L27: 924249.22 | M27: 334.39 | N27: 212.6 | O27: 71091.314 | P27: 621508.7 | Q27: T1-75 | R27: 212.6 | S27: 170.08 | T27: 1413167.5 | U27: OC010
A28: 27 | B28: =UPPER((TEXT(Tabla3[[#This Row],[Fecha llegada]],"MMM"))) -> MAR | C28: =YEAR(Tabla3[[#This Row],[Fecha llegada]]) -> 2024 | D28: Loc. 1034-1012 Plat. 4100,4073,4003,4151,4124,4018,4071,4120,4162,4048,4104,4159,4001,4146 | E28: 45355 | F28: 45356 | G28: 1 | H28: 2 | I28: 426749.05 | J28: 14 | K28: 285610.35 | L28: 712359.4 | M28: 388.33 | N28: 257 | O28: 99800.81 | P28: 872498.6 | Q28: REMISION ARGOS RPSM-00303703 | R28: 357 | S28: 285.6 | T28: 2373004.7 | U28: OC010
A29: 28 | B29: =UPPER((TEXT(Tabla3[[#This Row],[Fecha llegada]],"MMM"))) -> MAR | C29: =YEAR(Tabla3[[#This Row],[Fecha llegada]]) -> 2024 | D29: Loc. 1012-1044 Plat. 4071,4018,4124,4151,4002,4060,4017,4146,4104,4159, 4001 | E29: 45356 | F29: 45357 | G29: 1 | H29: 2 | I29: 426749.05 | J29: 11 | K29: 497500.17 | L29: 924249.22 | M29: 381.53 | N29: 212.6 | O29: 81113.278 | P29: 709124.72 | Q29: T1-76 | R29: 212.6 | S29: 170.08 | T29: 1413167.5 | U29: OC010
A30: 29 | B30: =UPPER((TEXT(Tabla3[[#This Row],[Fecha llegada]],"MMM"))) -> MAR | C30: =YEAR(Tabla3[[#This Row],[Fecha llegada]]) -> 2024 | D30: Loc. 1012-1001 Plat. 4095,4056,4003,4104,4159,4001,4146,4137,4060,4002,4151,4124,4018,4071 | E30: 45357 | F30: 45358 | G30: 1 | H30: 2 | I30: 426749.05 | J30: 14 | K30: 285610.35 | L30: 712359.4 | M30: 388.33 | N30: 257 | O30: 99800.81 | P30: 872498.6 | Q30: REMISION ARGOS RPSM-00303881 | R30: 357 | S30: 285.6 | T30: 2373004.7 | U30: OC010
A31: 30 | B31: =UPPER((TEXT(Tabla3[[#This Row],[Fecha llegada]],"MMM"))) -> MAR | C31: =YEAR(Tabla3[[#This Row],[Fecha llegada]]) -> 2024 | D31: Loc. 1001-1012 Plat. 4071, 4018,4124,4001 | E31: 45358 | F31: 45359 | G31: 1 | H31: 2 | I31: 426749.05 | J31: 4 | K31: 180909.15 | L31: 607658.2 | M31: 116.17 | N31: 212.6 | O31: 24697.742 | P31: 215917.54 | Q31: T1-77 | R31: 212.6 | S31: 170.08 | T31: 1413167.5 | U31: OC010
A32: 31 | B32: =UPPER((TEXT(Tabla3[[#This Row],[Fecha llegada]],"MMM"))) -> MAR | C32: =YEAR(Tabla3[[#This Row],[Fecha llegada]]) -> 2024 | D32: Loc. 1012-1001 Plat. 4064,4087,4061,4079,4095,4056,4003,40834151,4104,41594048,4162,4120 | E32: 45359 | F32: 45360 | G32: 1 | H32: 2 | I32: 426749.05 | J32: 14 | K32: 633182.03 | L32: 1059931.1 | M32: 392 | N32: 257 | O32: 100744 | P32: 880744.35 | Q32: REMISION ARGOS RPSM-00304084 | R32: 357 | S32: 285.6 | T32: 2373004.7 | U32: OC010
A33: 32 | B33: =UPPER((TEXT(Tabla3[[#This Row],[Fecha llegada]],"MMM"))) -> MAR | C33: =YEAR(Tabla3[[#This Row],[Fecha llegada]]) -> 2024 | D33: Loc. 1034 Plat. 4001,4124,4018,4071,4137,4060,4002 | E33: 45360 | F33: 45361 | G33: 1 | H33: 1 | I33: 213374.53 | J33: 7 | K33: 142805.18 | L33: 356179.7 | M33: 196 | N33: 257 | O33: 50372 | P33: 440372.17 | Q33: REMISION ARGOS RPSM-00304140 | R33: 357 | S33: 285.6 | T33: 2373004.7 | U33: OC010
A34: 33 | B34: =UPPER((TEXT(Tabla3[[#This Row],[Fecha llegada]],"MMM"))) -> MAR | C34: =YEAR(Tabla3[[#This Row],[Fecha llegada]]) -> 2024 | D34: Loc. 1001-1012 Plat. 4007,4068,4104,4151,4120,4162,4048,4159 | E34: 45361 | F34: 45362 | G34: 1 | H34: 2 | I34: 426749.05 | J34: 8 | K34: 361818.3 | L34: 788567.36 | M34: 262.23 | N34: 212.6 | O34: 55750.098 | P34: 487389.66 | Q34: T1-78 | R34: 212.6 | S34: 170.08 | T34: 1413167.5 | U34: OC010
A35: 34 | B35: =UPPER((TEXT(Tabla3[[#This Row],[Fecha llegada]],"MMM"))) -> MAR | C35: =YEAR(Tabla3[[#This Row],[Fecha llegada]]) -> 2024 | D35: Loc. 1012-1001 Plat. 4095,4083,4056,4003,4010,4049,4159,4048,4162,4120,4151,4104,4068,4007 | E35: 45362 | F35: 45363 | G35: 1 | H35: 2 | I35: 426749.05 | J35: 14 | K35: 285610.35 | L35: 712359.4 | M35: 389.55 | N35: 257 | O35: 100114.35 | P35: 875239.69 | Q35: REMISION ARGOS RPSM-00304238 | R35: 357 | S35: 285.6 | T35: 2373004.7 | U35: OC010
A36: 35 | B36: =UPPER((TEXT(Tabla3[[#This Row],[Fecha llegada]],"MMM"))) -> MAR | C36: =YEAR(Tabla3[[#This Row],[Fecha llegada]]) -> 2024 | D36: Loc. 1001-1012 Plat. 4159,4120,4162,4048,4007,4068,4104,4151 | E36: 45363 | F36: 45364 | G36: 1 | H36: 2 | I36: 426749.05 | J36: 8 | K36: 361818.3 | L36: 788567.36 | M36: 278.54 | N36: 212.6 | O36: 59217.604 | P36: 517703.98 | Q36: T1-79 | R36: 212.6 | S36: 170.08 | T36: 1413167.5 | U36: OC010
A37: 36 | B37: =UPPER((TEXT(Tabla3[[#This Row],[Fecha llegada]],"MMM"))) -> MAR | C37: =YEAR(Tabla3[[#This Row],[Fecha llegada]]) -> 2024 | D37: Loc. 1012-1001 Plat. 4124,4018,4071,4137,4060,4002,4056,4061,4079,4151,4104,4068,4007,4048 | E37: 45364 | F37: 45365 | G37: 1 | H37: 2 | I37: 426749.05 | J37: 14 | K37: 285610.35 | L37: 712359.4 | M37: 388.33 | N37: 257 | O37: 99800.81 | P37: 872498.6 | Q37: REMISION ARGOS RPSM-00304448 | R37: 357 | S37: 285.6 | T37: 2373004.7 | U37: OC010
... A41: 40 | B41: =UPPER((TEXT(Tabla3[[#This Row],[Fecha llegada]],"MMM"))) -> MAR | C41: =YEAR(Tabla3[[#This Row],[Fecha llegada]]) -> 2024 | D41: Loc. 1044-1001 Plat. 4060,4062,4001,4018,4104,4151,4007,4068 | E41: 45381 | F41: 45382 | G41: 1 | H41: 2 | I41: 426749.05 | J41: 8 | K41: 361818.3 | L41: 788567.36 | M41: 286.37 | N41: 212.6 | O41: 60882.262 | P41: 532257.09 | Q41: T1-81 | R41: 212.6 | S41: 170.08 | T41: 1413167.5 | U41: OC010
A42: 41 | B42: =UPPER((TEXT(Tabla3[[#This Row],[Fecha llegada]],"MMM"))) -> ABR | C42: =YEAR(Tabla3[[#This Row],[Fecha llegada]]) -> 2024 | D42: Loc. 1001-1044 Plat. 4072,4064,4071,4124,4048,4056,4100,4087,4053,40684007,4151,4104,4018 | E42: 45382 | F42: 45383 | G42: 1 | H42: 2 | I42: 426749.05 | J42: 14 | K42: 285610.35 | L42: 712359.4 | M42: 380.98 | N42: 257 | O42: 97911.86 | P42: 855984.64 | R42: 357 | S42: 285.6 | T42: 2373004.7 | U42: OC011
A43: 42 | B43: =UPPER((TEXT(Tabla3[[#This Row],[Fecha llegada]],"MMM"))) -> ABR | C43: =YEAR(Tabla3[[#This Row],[Fecha llegada]]) -> 2024 | D43: Loc. 1001-1034 Plat. 4079,4061,4071,4072,4018,4104,4003,4083,4064,4048,4124,4137,4159,4120 | E43: 45389 | F43: 45390 | G43: 1 | H43: 2 | I43: 426749.05 | J43: 14 | K43: 633182.03 | L43: 1059931.1 | M43: 473.72 | N43: 212.6 | O43: 100712.87 | P43: 880472.21 | Q43: T1-82 | R43: 212.6 | S43: 170.08 | T43: 1413167.5 | U43: OC011
A44: 43 | B44: =UPPER((TEXT(Tabla3[[#This Row],[Fecha llegada]],"MMM"))) -> ABR | C44: =YEAR(Tabla3[[#This Row],[Fecha llegada]]) -> 2024 | D44: Loc. 1044-1001 Plat. 4007,4151,4031,4001,4162,4060,4068,4124,4048,4064,4083,4003,4104 | E44: 45391 | F44: 45392 | G44: 1 | H44: 2 | I44: 426749.05 | J44: 14 | K44: 285610.35 | L44: 712359.4 | M44: 387.1 | N44: 257 | O44: 99484.7 | P44: 869735.04 | R44: 357 | S44: 285.6 | T44: 2373004.7 | U44: OC011
A45: 44 | B45: =UPPER((TEXT(Tabla3[[#This Row],[Fecha llegada]],"MMM"))) -> ABR | C45: =YEAR(Tabla3[[#This Row],[Fecha llegada]]) -> 2024 | D45: Loc. 1001-1034 Plat. 4147,4056,4095,4049,4104,4003,4083,4031,4146,4151,4007 | E45: 45392 | F45: 45393 | G45: 1 | H45: 2 | I45: 426749.05 | J45: 11 | K45: 497500.17 | L45: 924249.22 | M45: 360.13 | N45: 212.6 | O45: 76563.638 | P45: 669349.95 | Q45: T1-83 | R45: 212.6 | S45: 170.08 | T45: 1413167.5 | U45: OC011
A46: 45 | B46: =UPPER((TEXT(Tabla3[[#This Row],[Fecha llegada]],"MMM"))) -> ABR | C46: =YEAR(Tabla3[[#This Row],[Fecha llegada]]) -> 2024 | D46: Loc. 1044-1001 Plat. 4120,4018,4001,4162,4060,4072,4071,4061,4079,4146,4031,4003,4104,4049 | E46: 45393 | F46: 45394 | G46: 1 | H46: 2 | I46: 426749.05 | J46: 14 | K46: 285610.35 | L46: 712359.4 | M46: 392 | N46: 257 | O46: 100744 | P46: 880744.35 | R46: 357 | S46: 285.6 | T46: 2373004.7 | U46: OC011
A47: 46 | B47: =UPPER((TEXT(Tabla3[[#This Row],[Fecha llegada]],"MMM"))) -> ABR | C47: =YEAR(Tabla3[[#This Row],[Fecha llegada]]) -> 2024 | D47: Loc. 1001-1044 Plat. 4064,4001,4018,4049,4104,4003,4031,4071,4072,4060,4162 | E47: 45394 | F47: 45395 | G47: 1 | H47: 2 | I47: 426749.05 | J47: 11 | K47: 497500.17 | L47: 924249.22 | M47: 370.94 | N47: 212.6 | O47: 78861.844 | P47: 689441.78 | Q47: T1-84 | R47: 212.6 | S47: 170.08 | T47: 1413167.5 | U47: OC011
A48: 47 | B48: =UPPER((TEXT(Tabla3[[#This Row],[Fecha llegada]],"MMM"))) -> ABR | C48: =YEAR(Tabla3[[#This Row],[Fecha llegada]]) -> 2024 | D48: Loc. 1044-1001 Plat. 4061,4079,4146,4159,4137,4095,4056,4147,4083,4001,4064,4031,4003,4162 | E48: 45395 | F48: 45396 | G48: 1 | H48: 2 | I48: 426749.05 | J48: 14 | K48: 285610.35 | L48: 712359.4 | M48: 389.55 | N48: 257 | O48: 100114.35 | P48: 875239.69 | R48: 357 | S48: 285.6 | T48: 2373004.7 | U48: OC011
A49: 48 | B49: =UPPER((TEXT(Tabla3[[#This Row],[Fecha llegada]],"MMM"))) -> ABR | C49: =YEAR(Tabla3[[#This Row],[Fecha llegada]]) -> 2024 | D49: Loc. 1034-1044 Plat. 4137,4048,4095,4162,4003,4031,4064,4001,4083,4147,4056 | E49: 45397 | F49: 45398 | G49: 1 | H49: 2 | I49: 426749.05 | J49: 11 | K49: 497500.17 | L49: 924249.22 | M49: 383.19 | N49: 212.6 | O49: 81466.194 | P49: 712210.05 | Q49: T1-85 | R49: 312.6 | S49: 250.08 | T49: 2077874.7 | U49: OC011
A50: 49 | B50: =UPPER((TEXT(Tabla3[[#This Row],[Fecha llegada]],"MMM"))) -> ABR | C50: =YEAR(Tabla3[[#This Row],[Fecha llegada]]) -> 2024 | D50: Loc. 1034-1044 Plat. 4079,4146,4104,4049,4018,4060,4072,4071,4007,4056,4002,4100,4061,4151 | E50: 45398 | F50: 45399 | G50: 1 | H50: 2 | I50: 426749.05 | J50: 14 | K50: 285610.35 | L50: 712359.4 | M50: 392 | N50: 257 | O50: 100744 | P50: 880744.35 | R50: 257 | S50: 205.6 | T50: 1708297.5 | U50: OC011
A51: 50 | B51: =UPPER((TEXT(Tabla3[[#This Row],[Fecha llegada]],"MMM"))) -> ABR | C51: =YEAR(Tabla3[[#This Row],[Fecha llegada]]) -> 2024 | D51: Loc. 1034-1044 Plat. 4146,4079,4151,4061,4072,4060,4018,4049,4104,4124,4068 | E51: 45399 | F51: 45400 | G51: 1 | H51: 2 | I51: 426749.05 | J51: 11 | K51: 497500.17 | L51: 924249.22 | M51: 378.98 | N51: 212.6 | O51: 80571.148 | P51: 704385.2 | Q51: T1-86 | R51: 312.6 | S51: 250.08 | T51: 2077874.7 | U51: OC011
A52: 51 | B52: =UPPER((TEXT(Tabla3[[#This Row],[Fecha llegada]],"MMM"))) -> ABR | C52: =YEAR(Tabla3[[#This Row],[Fecha llegada]]) -> 2024 | D52: Loc. 1044-1034 Plat. 4071,4007,4056,4048,4137,4068,4031,4003,4162,4095,4147,4083,4001,4064 | E52: 45400 | F52: 45401 | G52: 1 | H52: 2 | I52: 426749.05 | J52: 14 | K52: 285610.35 | L52: 712359.4 | M52: 388.33 | N52: 257 | O52: 99800.81 | P52: 872498.6 | R52: 257 | S52: 205.6 | T52: 1708297.5 | U52: OC011
A53: 52 | B53: =UPPER((TEXT(Tabla3[[#This Row],[Fecha llegada]],"MMM"))) -> ABR | C53: =YEAR(Tabla3[[#This Row],[Fecha llegada]]) -> 2024 | D53: Loc. 1044-1034 Plat. 4001,4083,4147,4031,4068,4137,4048,4056,4007,4071,4064 | E53: 45401 | F53: 45402 | G53: 1 | H53: 2 | I53: 426749.05 | J53: 11 | K53: 497500.17 | L53: 924249.22 | M53: 360.13 | N53: 212.6 | O53: 76563.638 | P53: 669349.95 | Q53: T1-87 | R53: 312.6 | S53: 250.08 | T53: 2077874.7 | U53: OC011
A54: 53 | B54: =UPPER((TEXT(Tabla3[[#This Row],[Fecha llegada]],"MMM"))) -> ABR | C54: =YEAR(Tabla3[[#This Row],[Fecha llegada]]) -> 2024 | D54: Loc. 1044-1034 Plat. 4162,4095,4124,4104,4049,4137,4003,4072,4061,4151,4018,4079,4146,4060 | E54: 45402 | F54: 45403 | G54: 1 | H54: 2 | I54: 426749.05 | J54: 14 | K54: 285610.35 | L54: 712359.4 | M54: 392 | N54: 257 | O54: 100744 | P54: 880744.35 | R54: 257 | S54: 205.6 | T54: 1708297.5 | U54: OC011
A55: 54 | B55: =UPPER((TEXT(Tabla3[[#This Row],[Fecha llegada]],"MMM"))) -> ABR | C55: =YEAR(Tabla3[[#This Row],[Fecha llegada]]) -> 2024 | D55: Loc. 1034-1044 Plat. 4146,4079,4018,4151,4104,4124,4095,4162,4061,4072,4003 | E55: 45404 | F55: 45405 | G55: 1 | H55: 2 | I55: 426749.05 | J55: 11 | K55: 497500.17 | L55: 924249.22 | M55: 343.04 | N55: 212.6 | O55: 72930.304 | P55: 637585.89 | Q55: T1-88 | R55: 312.6 | S55: 250.08 | T55: 2077874.7 | U55: OC011
A56: 55 | B56: =UPPER((TEXT(Tabla3[[#This Row],[Fecha llegada]],"MMM"))) -> ABR | C56: =YEAR(Tabla3[[#This Row],[Fecha llegada]]) -> 2024 | D56: Loc. 1044-1034 Plat. 4068,4031,4147,4064,4071,4007,4056,4073,4060,4049,4137,4048,4083,4001 | E56: 45406 | F56: 45407 | G56: 1 | H56: 2 | I56: 426749.05 | J56: 14 | K56: 285610.35 | L56: 712359.4 | M56: 389.55 | N56: 257 | O56: 100114.35 | P56: 875239.69 | R56: 257 | S56: 205.6 | T56: 1708297.5 | U56: OC011
A57: 56 | B57: =UPPER((TEXT(Tabla3[[#This Row],[Fecha llegada]],"MMM"))) -> ABR | C57: =YEAR(Tabla3[[#This Row],[Fecha llegada]]) -> 2024 | D57: Loc. 1034-1044 Plat. 4031,4068,4007,4071,4064,4147,4056,4001,4083,4048,4137 | E57: 45407 | F57: 45408 | G57: 1 | H57: 2 | I57: 426749.05 | J57: 11 | K57: 497500.17 | L57: 924249.22 | M57: 376.65 | N57: 212.6 | O57: 80075.79 | P57: 700054.59 | Q57: T1-89 | R57: 212.6 | S57: 170.08 | T57: 1413167.5 | U57: OC011
A58: 57 | B58: =UPPER((TEXT(Tabla3[[#This Row],[Fecha llegada]],"MMM"))) -> ABR | C58: =YEAR(Tabla3[[#This Row],[Fecha llegada]]) -> 2024 | D58: Loc. 1044-1034 Plat. 4068,4031,4147,4064,4071,4007,4056,4073,4060,4049,4137,4048,4083,4001 | E58: 45408 | F58: 45409 | G58: 1 | H58: 2 | I58: 426749.05 | J58: 14 | K58: 285610.35 | L58: 712359.4 | M58: 389.55 | N58: 257 | O58: 100114.35 | P58: 875239.69 | R58: 257 | S58: 205.6 | T58: 1708297.5 | U58: OC011
A59: 58 | B59: =UPPER((TEXT(Tabla3[[#This Row],[Fecha llegada]],"MMM"))) -> ABR | C59: =YEAR(Tabla3[[#This Row],[Fecha llegada]]) -> 2024 | D59: Loc. 1034-1044 Plat. 4049,4060,4146,4003,4018,4151,4104,4079,4095,4162,4087 | E59: 45411 | F59: 45412 | G59: 1 | H59: 2 | I59: 426749.05 | J59: 11 | K59: 497500.17 | L59: 924249.22 | M59: 340.66 | N59: 212.6 | O59: 72424.316 | P59: 633162.34 | Q59: T1-90 | R59: 212.6 | S59: 170.08 | T59: 1413167.5 | U59: OC011
A60: 59 | B60: =UPPER((TEXT(Tabla3[[#This Row],[Fecha llegada]],"MMM"))) -> MAY | C60: =YEAR(Tabla3[[#This Row],[Fecha llegada]]) -> 2024 | D60: Loc. 1044-1034 Plat. 4003,41374048,4083,4001,4064.4071.4007,4151,4162,4095,4079,4104,4061 | E60: 45412 | F60: 45413 | G60: 1 | H60: 2 | I60: 426749.05 | J60: 14 | K60: 285610.35 | L60: 712359.4 | M60: 388.33 | N60: 257 | O60: 99800.81 | P60: 872498.6 | Q60: REMISION ARGOS RPSM | R60: 357 | S60: 285.6 | T60: 2373004.7 | U60: OC012
A61: 60 | B61: =UPPER((TEXT(Tabla3[[#This Row],[Fecha llegada]],"MMM"))) -> MAY | C61: =YEAR(Tabla3[[#This Row],[Fecha llegada]]) -> 2024 | D61: Loc. 1034-1044 Plat. 4137,4061,4104,4064,4001,4083,4048,4151,4007,4071 | E61: 45414 | F61: 45415 | G61: 1 | H61: 2 | I61: 426749.05 | J61: 9 | K61: 407045.59 | L61: 833794.65 | M61: 348.55 | N61: 212.6 | O61: 74101.73 | P61: 647826.96 | Q61: T1-91 | R61: 212.6 | S61: 170.08 | T61: 1413167.5 | U61: OC012
A62: 61 | B62: =UPPER((TEXT(Tabla3[[#This Row],[Fecha llegada]],"MMM"))) -> MAY | C62: =YEAR(Tabla3[[#This Row],[Fecha llegada]]) -> 2024 | D62: Loc. 1044-1012 Plat. 4073,4162,4095,4147,4072,4068,4031,4001,404,4104,4061,4071,4056 | E62: 45415 | F62: 45416 | G62: 1 | H62: 2 | I62: 426749.05 | J62: 14 | K62: 285610.35 | L62: 712359.4 | M62: 387.1 | N62: 257 | O62: 99484.7 | P62: 869735.04 | Q62: REMISION ARGOS RPSM | R62: 357 | S62: 285.6 | T62: 2373004.7 | U62: OC012
A63: 62 | B63: =UPPER((TEXT(Tabla3[[#This Row],[Fecha llegada]],"MMM"))) -> MAY | C63: =YEAR(Tabla3[[#This Row],[Fecha llegada]]) -> 2024 | D63: Loc. 1012-1044 Plat.4072,4147,4079,4095,4162,4002,4071,4061,4104,4064 | E63: 45423 | F63: 45424 | G63: 1 | H63: 2 | I63: 426749.05 | J63: 10 | K63: 452272.88 | L63: 879021.93 | M63: 342.66 | N63: 212.6 | O63: 72849.516 | P63: 636879.61 | Q63: T1-92 | R63: 212.6 | S63: 170.08 | T63: 1413167.5 | U63: OC012
A64: 63 | B64: =UPPER((TEXT(Tabla3[[#This Row],[Fecha llegada]],"MMM"))) -> MAY | C64: =YEAR(Tabla3[[#This Row],[Fecha llegada]]) -> 2024 | D64: Loc. 1012-1044 Plat. 4073,4031,4001,4007,4051,4048,4083,4137,4018,4003,4146,4060,4049,4120 | E64: 45425 | F64: 45426 | G64: 1 | H64: 2 | I64: 426749.05 | J64: 14 | K64: 285610.35 | L64: 712359.4 | M64: 388.33 | N64: 257 | O64: 99800.81 | P64: 872498.6 | Q64: REMISION ARGOS RPSM | R64: 357 | S64: 285.6 | T64: 2373004.7 | U64: OC012
A65: 64 | B65: =UPPER((TEXT(Tabla3[[#This Row],[Fecha llegada]],"MMM"))) -> MAY | C65: =YEAR(Tabla3[[#This Row],[Fecha llegada]]) -> 2024 | D65: Loc. 1012-1044 Plat. 4120,4083,4046,4151,4007,4068,4001,4031 | E65: 45426 | F65: 45427 | G65: 1 | H65: 2 | I65: 426749.05 | J65: 8 | K65: 361818.3 | L65: 788567.36 | M65: 243.21 | N65: 212.6 | O65: 51706.446 | P65: 452038.43 | Q65: T1-93 | R65: 212.6 | S65: 170.08 | T65: 1413167.5 | U65: OC012
A66: 65 | B66: =UPPER((TEXT(Tabla3[[#This Row],[Fecha llegada]],"MMM"))) -> MAY | C66: =YEAR(Tabla3[[#This Row],[Fecha llegada]]) -> 2024 | D66: Loc. 1012-1044 Plat. 4073,4146,4060,4162,4095,40794147,4087,4072,4064,4104,4061,4071,4002 | E66: 45427 | F66: 45428 | G66: 1 | H66: 2 | I66: 426749.05 | J66: 14 | K66: 285610.35 | L66: 712359.4 | M66: 389.55 | N66: 257 | O66: 100114.35 | P66: 875239.69 | Q66: REMISION ARGOS RPSM | R66: 357 | S66: 285.6 | T66: 2373004.7 | U66: OC012
A67: 66 | B67: =UPPER((TEXT(Tabla3[[#This Row],[Fecha llegada]],"MMM"))) -> MAY | C67: =YEAR(Tabla3[[#This Row],[Fecha llegada]]) -> 2024 | D67: Loc. 1012-1044 Plat. 4061,4104,4064,4072,4087,4147,4079,4095,4162,4060,4146 | E67: 45428 | F67: 45429 | G67: 1 | H67: 2 | I67: 426749.05 | J67: 11 | K67: 497500.17 | L67: 924249.22 | M67: 367.07 | N67: 212.6 | O67: 78039.082 | P67: 682248.87 | Q67: T1-94 | R67: 212.6 | S67: 170.08 | T67: 1413167.5 | U67: OC012
A68: 67 | B68: =UPPER((TEXT(Tabla3[[#This Row],[Fecha llegada]],"MMM"))) -> MAY | C68: =YEAR(Tabla3[[#This Row],[Fecha llegada]]) -> 2024 | D68: Loc. 1012-1044 Plat. 4002,4031,4001,4068,4074051,4048,4083,4020,4137,4018,4003,4073,4071 | E68: 45429 | F68: 45430 | G68: 1 | H68: 2 | I68: 426749.05 | J68: 14 | K68: 285610.35 | L68: 712359.4 | M68: 389.55 | N68: 257 | O68: 100114.35 | P68: 875239.69 | Q68: REMISION ARGOS RPSM | R68: 357 | S68: 285.6 | T68: 2373004.7 | U68: OC012
A69: 68 | B69: =UPPER((TEXT(Tabla3[[#This Row],[Fecha llegada]],"MMM"))) -> MAY | C69: =YEAR(Tabla3[[#This Row],[Fecha llegada]]) -> 2024 | D69: Loc. 1012-1044 Plat. 4073,4071,4087,4072,4064,4104,4061,4079,4147,4146,4060,4062,4095,4083 | E69: 45433 | F69: 45434 | G69: 2 | H69: 2 | I69: 853498.11 | J69: 14 | K69: 571220.7 | L69: 1424718.8 | M69: 389.55 | N69: 257 | O69: 100114.35 | P69: 875239.69 | Q69: REMISION ARGOS RPSM | R69: 614 | S69: 491.2 | T69: 4081302.2 | U69: OC012
A70: 69 | B70: =UPPER((TEXT(Tabla3[[#This Row],[Fecha llegada]],"MMM"))) -> MAY | C70: =YEAR(Tabla3[[#This Row],[Fecha llegada]]) -> 2024 | D70: Loc. 1001-1012 Plat. 4071,4087,4007,4151,4048,4003,4120,4137,4018,4146,4060,4162,4095,4083 | E70: 45435 | F70: 45436 | G70: 2 | H70: 2 | I70: 853498.11 | J70: 14 | K70: 571220.7 | L70: 1424718.8 | M70: 392 | N70: 257 | O70: 100744 | P70: 880744.35 | Q70: REMISION ARGOS RPSM | R70: 614 | S70: 491.2 | T70: 4081302.2 | U70: OC012
... A104: 103 | B104: =UPPER((TEXT(Tabla3[[#This Row],[Fecha llegada]],"MMM"))) -> JUL | C104: =YEAR(Tabla3[[#This Row],[Fecha llegada]]) -> 2024 | D104: Loc. 1012-1034 Plat. 4067,4124,4003,4100,4018,4048,4071,4072,4031,4146,4162,4060,4095,4120 | E104: 45503 | F104: 45504 | G104: 1 | H104: 2 | I104: 426749.05 | J104: 14 | K104: 285610.35 | L104: 712359.4 | M104: 388.33 | N104: 257 | O104: 99800.81 | P104: 872498.6 | Q104: RPSM-00313542 | R104: 445 | S104: 356 | T104: 2957947 | U104: OC014
A105: 104 | B105: =UPPER((TEXT(Tabla3[[#This Row],[Fecha llegada]],"MMM"))) -> AGO | C105: =YEAR(Tabla3[[#This Row],[Fecha llegada]]) -> 2024 | E105: 45505 | F105: 45506 | G105: 1 | H105: 2 | I105: 651815.34 | J105: 11 | K105: 627556.81 | L105: 1279372.2 | M105: 365.57 | N105: 212.6 | O105: 77720.182 | P105: 679460.92 | Q105: T1-117 | R105: 400.6 | S105: 320.48 | T105: 2662868.3 | U105: OC015
A106: 105 | B106: =UPPER((TEXT(Tabla3[[#This Row],[Fecha llegada]],"MMM"))) -> AGO | C106: =YEAR(Tabla3[[#This Row],[Fecha llegada]]) -> 2024 | E106: 45506 | F106: 45507 | G106: 1 | H106: 2 | I106: 651815.34 | J106: 14 | K106: 360293.59 | L106: 1012108.9 | M106: 387.1 | N106: 257 | O106: 99484.7 | P106: 869735.04 | Q106: REMISION ARGOS RPSM- 00313744 T1-117 | R106: 445 | S106: 356 | T106: 2958004 | U106: OC015
A107: 106 | B107: =UPPER((TEXT(Tabla3[[#This Row],[Fecha llegada]],"MMM"))) -> AGO | C107: =YEAR(Tabla3[[#This Row],[Fecha llegada]]) -> 2024 | E107: 45507 | F107: 45508 | G107: 1 | H107: 2 | I107: 651815.34 | J107: 6 | K107: 342303.71 | L107: 994119.06 | M107: 174.79 | N107: 212.6 | O107: 37160.354 | P107: 324870.68 | Q107: T1-118 | R107: 400.6 | S107: 320.48 | T107: 2662868.3 | U107: OC015
A108: 107 | B108: =UPPER((TEXT(Tabla3[[#This Row],[Fecha llegada]],"MMM"))) -> AGO | C108: =YEAR(Tabla3[[#This Row],[Fecha llegada]]) -> 2024 | E108: 45508 | F108: 45509 | G108: 1 | H108: 2 | I108: 651815.34 | J108: 14 | K108: 360293.59 | L108: 1012108.9 | M108: 388.55 | N108: 257 | O108: 99857.35 | P108: 872992.9 | Q108: REMISION ARGOS RPSM-00313866 T1-118 | R108: 445 | S108: 356 | T108: 2958004 | U108: OC015
A109: 108 | B109: =UPPER((TEXT(Tabla3[[#This Row],[Fecha llegada]],"MMM"))) -> AGO | C109: =YEAR(Tabla3[[#This Row],[Fecha llegada]]) -> 2024 | E109: 45510 | F109: 45511 | G109: 2 | H109: 2 | I109: 1303630.7 | J109: 14 | K109: 720587.18 | L109: 2024217.9 | M109: 387.83 | N109: 257 | O109: 99672.31 | P109: 871375.2 | Q109: REMISION ARGOS RPSM-00313980 T1-119 | R109: 702 | S109: 561.6 | T109: 4666334.4 | U109: OC015
A110: 109 | B110: =UPPER((TEXT(Tabla3[[#This Row],[Fecha llegada]],"MMM"))) -> AGO | C110: =YEAR(Tabla3[[#This Row],[Fecha llegada]]) -> 2024 | E110: 45511 | F110: 45512 | G110: 1 | H110: 2 | I110: 651815.34 | J110: 7 | K110: 399354.33 | L110: 1051169.7 | M110: 254.9 | N110: 212.6 | O110: 54191.74 | P110: 473765.87 | Q110: T1 120 | R110: 400.6 | S110: 320.48 | T110: 2662868.3 | U110: OC015
A111: 110 | B111: =UPPER((TEXT(Tabla3[[#This Row],[Fecha llegada]],"MMM"))) -> AGO | C111: =YEAR(Tabla3[[#This Row],[Fecha llegada]]) -> 2024 | E111: 45512 | F111: 45513 | G111: 1 | H111: 2 | I111: 651815.34 | J111: 14 | K111: 360293.59 | L111: 1012108.9 | M111: 388.33 | N111: 257 | O111: 99800.81 | P111: 872498.6 | Q111: REMISION ARGOS RPSM-00314081 T1-120 | R111: 445 | S111: 356 | T111: 2958004 | U111: OC015
A112: 111 | B112: =UPPER((TEXT(Tabla3[[#This Row],[Fecha llegada]],"MMM"))) -> AGO | C112: =YEAR(Tabla3[[#This Row],[Fecha llegada]]) -> 2024 | E112: 45514 | F112: 45515 | G112: 2 | H112: 2 | I112: 1303630.7 | J112: 14 | K112: 720587.18 | L112: 2024217.9 | M112: 389.55 | N112: 257 | O112: 100114.35 | P112: 875239.69 | Q112: REMISION ARGOS RPSM-00314241 T1-121 | R112: 702 | S112: 561.6 | T112: 4666334.4 | U112: OC015
A113: 112 | B113: =UPPER((TEXT(Tabla3[[#This Row],[Fecha llegada]],"MMM"))) -> AGO | C113: =YEAR(Tabla3[[#This Row],[Fecha llegada]]) -> 2024 | E113: 45524 | F113: 45525 | G113: 2 | H113: 2 | I113: 1303630.7 | J113: 14 | K113: 720587.18 | L113: 2024217.9 | M113: 392 | N113: 257 | O113: 100744 | P113: 880744.35 | Q113: REMISION ARGOS RPSM-00314768 T1-122 | R113: 702 | S113: 561.6 | T113: 4666334.4 | U113: OC015
A114: 113 | B114: =UPPER((TEXT(Tabla3[[#This Row],[Fecha llegada]],"MMM"))) -> AGO | C114: =YEAR(Tabla3[[#This Row],[Fecha llegada]]) -> 2024 | E114: 45526 | F114: 45527 | G114: 2 | H114: 2 | I114: 1303630.7 | J114: 14 | K114: 720587.18 | L114: 2024217.9 | M114: 387.83 | N114: 257 | O114: 99672.31 | P114: 871375.2 | Q114: REMISION ARGOS RPSM-00314925 T1-123 | R114: 702 | S114: 561.6 | T114: 4666334.4 | U114: OC015
A115: 114 | B115: =UPPER((TEXT(Tabla3[[#This Row],[Fecha llegada]],"MMM"))) -> AGO | C115: =YEAR(Tabla3[[#This Row],[Fecha llegada]]) -> 2024 | E115: 45528 | F115: 45529 | G115: 2 | H115: 2 | I115: 1303630.7 | J115: 14 | K115: 720587.18 | L115: 2024217.9 | M115: 386.83 | N115: 257 | O115: 99415.31 | P115: 869128.41 | Q115: REMISION ARGOS RPSM-00315097 T1-124 | R115: 702 | S115: 561.6 | T115: 4666334.4 | U115: OC015
A116: 115 | B116: =UPPER((TEXT(Tabla3[[#This Row],[Fecha llegada]],"MMM"))) -> AGO | C116: =YEAR(Tabla3[[#This Row],[Fecha llegada]]) -> 2024 | E116: 45533 | F116: 45534 | G116: 2 | H116: 2 | I116: 1303630.7 | J116: 14 | K116: 720587.18 | L116: 2024217.9 | M116: 392 | N116: 257 | O116: 100744 | P116: 880744.35 | Q116: REMISION ARGOS RPSM-00315392 T1-125 | R116: 702 | S116: 561.6 | T116: 4666334.4 | U116: OC015
... A143: 142 | B143: =UPPER((TEXT(Tabla3[[#This Row],[Fecha llegada]],"MMM"))) -> OCT | C143: =YEAR(Tabla3[[#This Row],[Fecha llegada]]) -> 2024 | E143: 45589 | F143: 45589 | G143: 1 | H143: 1 | I143: 213374.53 | J143: 4 | K143: 81602.957 | L143: 580587.83 | M143: 110.775 | N143: 78 | O143: 8640.45 | P143: 75538.27 | Q143: (T1-147) | R143: 445 | S143: 356 | T143: 3356012 | U143: OC017
A144: 143 | B144: =UPPER((TEXT(Tabla3[[#This Row],[Fecha llegada]],"MMM"))) -> OCT | C144: =YEAR(Tabla3[[#This Row],[Fecha llegada]]) -> 2024 | E144: 45589 | F144: 45590 | J144: 7 | K144: 142805.18 | M144: 192.325 | N144: 257 | O144: 49427.525 | P144: 432115.19 | Q144: RPSM-00318990(T1-47) | U144: OC017
A145: 144 | B145: =UPPER((TEXT(Tabla3[[#This Row],[Fecha llegada]],"MMM"))) -> OCT | C145: =YEAR(Tabla3[[#This Row],[Fecha llegada]]) -> 2024 | E145: 45589 | F145: 45590 | J145: 7 | K145: 142805.18 | M145: 202.727 | N145: 257 | O145: 52100.839 | P145: 455486.37 | Q145: (T1-147) | U145: OC017
A146: 145 | B146: =UPPER((TEXT(Tabla3[[#This Row],[Fecha llegada]],"MMM"))) -> OCT | C146: =YEAR(Tabla3[[#This Row],[Fecha llegada]]) -> 2024 | E146: 45590 | F146: 45591 | G146: 1 | H146: 2 | I146: 426749.05 | J146: 8 | K146: 163205.91 | L146: 589954.97 | M146: 121.957 | N146: 169.13 | O146: 20626.587 | P146: 180325.88 | Q146: (T1-148) | R146: 296.13 | S146: 236.904 | T146: 2233294 | U146: OC017
A147: 146 | B147: =UPPER((TEXT(Tabla3[[#This Row],[Fecha llegada]],"MMM"))) -> OCT | C147: =YEAR(Tabla3[[#This Row],[Fecha llegada]]) -> 2024 | E147: 45591 | F147: 45592 | G147: 1 | H147: 2 | I147: 426749.05 | J147: 12 | K147: 244808.87 | L147: 671557.92 | M147: 345.126 | N147: 257 | O147: 88697.382 | P147: 775427.99 | Q147: (T1-148) | R147: 445 | S147: 356 | T147: 3356012 | U147: OC017
A148: 147 | B148: =UPPER((TEXT(Tabla3[[#This Row],[Fecha llegada]],"MMM"))) -> OCT | C148: =YEAR(Tabla3[[#This Row],[Fecha llegada]]) -> 2024 | E148: 45592 | F148: 45593 | G148: 1 | H148: 2 | I148: 426749.05 | J148: 9 | K148: 183606.65 | L148: 610355.71 | M148: 8.554 | N148: 225.85 | O148: 1931.9209 | P148: 16889.625 | Q148: (T1-149) | R148: 225.85 | S148: 180.68 | T148: 1703270.4 | U148: OC017
A149: 148 | B149: =UPPER((TEXT(Tabla3[[#This Row],[Fecha llegada]],"MMM"))) -> OCT | C149: =YEAR(Tabla3[[#This Row],[Fecha llegada]]) -> 2024 | E149: 45593 | F149: 45594 | G149: 1 | H149: 2 | I149: 426749.05 | J149: 15 | K149: 306011.09 | L149: 732760.14 | M149: 388.33 | N149: 257 | O149: 99800.81 | P149: 872498.6 | Q149: RPSM-00319133 (T1-149) | R149: 445 | S149: 356 | T149: 3356012 | U149: OC017
A150: 149 | B150: =UPPER((TEXT(Tabla3[[#This Row],[Fecha llegada]],"MMM"))) -> OCT | C150: =YEAR(Tabla3[[#This Row],[Fecha llegada]]) -> 2024 | E150: 45595 | F150: 45596 | G150: 2 | H150: 2 | I150: 853498.11 | J150: 14 | K150: 571220.7 | L150: 1424718.8 | M150: 386.33 | N150: 257 | O150: 99286.81 | P150: 868005.01 | Q150: RPSM-00319289 (T1-150) | R150: 702 | S150: 561.6 | T150: 5294203.2 | U150: OC017
A151: 150 | B151: =UPPER((TEXT(Tabla3[[#This Row],[Fecha llegada]],"MMM"))) -> NOV | C151: =YEAR(Tabla3[[#This Row],[Fecha llegada]]) -> 2024 | E151: 45597 | F151: 45598 | G151: 2 | H151: 2 | I151: 1753763.3 | J151: 14 | K151: 869954.51 | L151: 2623717.8 | M151: 389.55 | N151: 257 | O151: 100114.35 | P151: 875239.69 | Q151: RPSM-00319477 (T1-151) | R151: 702 | S151: 561.6 | T151: 5294203.2 | U151: OC018
A152: 151 | B152: =UPPER((TEXT(Tabla3[[#This Row],[Fecha llegada]],"MMM"))) -> NOV | C152: =YEAR(Tabla3[[#This Row],[Fecha llegada]]) -> 2024 | E152: 45600 | F152: 45601 | G152: 2 | H152: 2 | I152: 1753763.3 | J152: 14 | K152: 869954.51 | L152: 2623717.8 | M152: 392 | N152: 257 | O152: 100744 | P152: 880744.35 | Q152: RPSM-00319572(T1-152) | R152: 702 | S152: 561.6 | T152: 5294203.2 | U152: OC018
A153: 152 | B153: =UPPER((TEXT(Tabla3[[#This Row],[Fecha llegada]],"MMM"))) -> NOV | C153: =YEAR(Tabla3[[#This Row],[Fecha llegada]]) -> 2024 | E153: 45602 | F153: 45603 | G153: 2 | H153: 2 | I153: 1753763.3 | J153: 14 | K153: 869954.51 | L153: 2623717.8 | M153: 391 | N153: 257 | O153: 100487 | P153: 878497.55 | Q153: RPSM-00 319675(T1-153) | R153: 702 | S153: 561.6 | T153: 5294203.2 | U153: OC018
A154: 153 | B154: =UPPER((TEXT(Tabla3[[#This Row],[Fecha llegada]],"MMM"))) -> NOV | C154: =YEAR(Tabla3[[#This Row],[Fecha llegada]]) -> 2024 | E154: 45604 | F154: 45605 | G154: 2 | H154: 2 | I154: 1753763.3 | J154: 14 | K154: 869954.51 | L154: 2623717.8 | M154: 389.55 | N154: 257 | O154: 100114.35 | P154: 875239.69 | Q154: RPSM-00 319844(T1-154) | R154: 702 | S154: 561.6 | T154: 5294203.2 | U154: OC018
A155: 154 | B155: =UPPER((TEXT(Tabla3[[#This Row],[Fecha llegada]],"MMM"))) -> NOV | C155: =YEAR(Tabla3[[#This Row],[Fecha llegada]]) -> 2024 | E155: 45611 | F155: 45611 | G155: 1 | H155: 1 | I155: 438440.82 | J155: 8 | K155: 248558.43 | L155: 686999.25 | M155: 126 | N155: 44.45 | O155: 5600.7 | P155: 48963.56 | Q155: (T1-155) | R155: 88.9 | S155: 71.12 | T155: 670448.24 | U155: OC018
A156: 155 | B156: =UPPER((TEXT(Tabla3[[#This Row],[Fecha llegada]],"MMM"))) -> NOV | C156: =YEAR(Tabla3[[#This Row],[Fecha llegada]]) -> 2024 | E156: 45986 | F156: 45622 | G156: 2 | H156: 2 | I156: 1753763.3 | J156: 14 | K156: 869954.51 | L156: 2623717.8 | M156: 388.33 | N156: 257 | O156: 99800.81 | P156: 872498.6 | Q156: RPSM-00320952(T1-156) | R156: 702 | S156: 561.6 | T156: 5294203.2 | U156: OC018
A157: 156 | B157: =UPPER((TEXT(Tabla3[[#This Row],[Fecha llegada]],"MMM"))) -> NOV | C157: =YEAR(Tabla3[[#This Row],[Fecha llegada]]) -> 2024 | E157: 45623 | F157: 45624 | G157: 2 | H157: 2 | I157: 1753763.3 | J157: 14 | K157: 869954.51 | L157: 2623717.8 | M157: 392 | N157: 257 | O157: 100744 | P157: 880744.35 | Q157: RPSM-00321121(T1-157) | R157: 702 | S157: 561.6 | T157: 5294203.2 | U157: OC018
... A213: 212 | B213: =UPPER((TEXT(Tabla3[[#This Row],[Fecha llegada]],"MMM"))) -> MAY | C213: =YEAR(Tabla3[[#This Row],[Fecha llegada]]) -> 2025 | E213: 45807 | F213: 45807 | G213: 1 | H213: 1 | I213: 342854.87 | J213: 10 | K213: 600172.55 | L213: 943027.42 | M213: 250 | N213: 18.47 | O213: 4617.5 | P213: 42467.17 | Q213: T1-001 | R213: 36.94 | S213: 29.552 | T213: 300573.39 | U213: OC024
A214: 213 | B214: =UPPER((TEXT(Tabla3[[#This Row],[Fecha llegada]],"MMM"))) -> JUN | C214: =YEAR(Tabla3[[#This Row],[Fecha llegada]]) -> 2025 | E214: 45809 | F214: 45809 | G214: 1 | H214: 1 | I214: 106085.13 | J214: 8 | K214: 281127.62 | L214: 387212.75 | M214: 204.47 | N214: 30 | O214: 6134.1 | P214: 56415.347 | Q214: T1-001 | R214: 60 | S214: 48 | U214: OC025
A215: 214 | B215: =UPPER((TEXT(Tabla3[[#This Row],[Fecha llegada]],"MMM"))) -> JUN | C215: =YEAR(Tabla3[[#This Row],[Fecha llegada]]) -> 2025 | E215: 45811 | F215: 45811 | G215: 1 | H215: 1 | I215: 106085.13 | J215: 10 | K215: 351409.52 | L215: 457494.65 | M215: 250 | N215: 18.65 | O215: 4662.5 | P215: 42881.035 | Q215: T1-002 | R215: 37.3 | S215: 29.84 | U215: OC025
A216: 215 | B216: =UPPER((TEXT(Tabla3[[#This Row],[Fecha llegada]],"MMM"))) -> JUN | C216: =YEAR(Tabla3[[#This Row],[Fecha llegada]]) -> 2025 | E216: 45811 | F216: 45812 | G216: 2 | H216: 2 | I216: 424340.5 | J216: 14 | K216: 443789.75 | L216: 868130.25 | M216: 390.78 | N216: 257 | O216: 100430.46 | P216: 923659.42 | Q216: REMISION ARGOS RPSM-00332279 T1-209 | R216: 702 | S216: 561.6 | U216: OC025
A217: 216 | B217: =UPPER((TEXT(Tabla3[[#This Row],[Fecha llegada]],"MMM"))) -> JUN | C217: =YEAR(Tabla3[[#This Row],[Fecha llegada]]) -> 2025 | E217: 45812 | F217: 45812 | G217: 1 | H217: 1 | I217: 106085.13 | J217: 10 | K217: 351409.52 | L217: 457494.65 | M217: 250 | N217: 18.8 | O217: 4700 | P217: 43225.923 | Q217: T1-003 | R217: 37.6 | S217: 30.08 | U217: OC025
...

Sheet Tablas dinamicas O.P
C1: Etiquetas de fila | D1: Suma de V/r Alquiler Mat. Rodante | G1: Etiquetas de fila | H1: Suma de Toneladas Transportad. | K1: Etiquetas de fila | L1: Suma de V/r Alquiler locomotoras | M1: Suma de V/r Alquiler plataformas | P1: Etiquetas de fila | Q1: Suma de Km recorridos | T1: Etiquetas de fila | U1: Suma de Ton-km | X1: Etiquetas de fila | Y1: Suma de V/r Importe Uso de Vía | AA1: Etiquetas de fila | AB1: Suma de PASAJEROS
C2: SEP | D2: 15014885 | G2: OC028 | H2: 4338.15 | K2: SEP | L2: 9257081.6 | M2: 5757802.9 | P2: SEP | Q2: 2149.362 | T2: SEP | U2: 717230.05 | X2: SEP | Y2: 6596368.2 | AA2: 2024 | AB2: 514284
C3: Total general | D3: 15014885 | G3: SEP | H3: 4338.15 | K3: Total general | L3: 9257081.6 | M3: 5757802.9 | P3: Total general | Q3: 2149.362 | T3: Total general | U3: 717230.05 | X3: Total general | Y3: 6596368.2 | AA3: Turistren | AB3: 514284
G4: Total general | H4: 4338.15 | AA4: 2025 | AB4: 353368
AA5: APDR | AB5: 848
A6: Total general | B6: =VLOOKUP(A6,C:D,2,TRUE) -> 15014885 | E6: Total general | F6: =VLOOKUP(E6,G:H,2,TRUE) -> 4338.15 | I6: Total general | J6: =VLOOKUP(I6,K:M,2,TRUE) -> 9257081.6 | AA6: Turistren | AB6: 352520
I7: Total general | J7: =VLOOKUP(I7,K:M,3,TRUE) -> 5757802.9 | N7: Total general | O7: =VLOOKUP(N7,P:Q,2,TRUE) -> 2149.362 | R7: Total general | S7: =VLOOKUP(R7,T:U,2,TRUE) -> 717230.05 | V7: Total general | W7: =VLOOKUP(V7,X:Y,2,TRUE) -> 6596368.2 | AA7: Total general | AB7: 867652

Sheet Turistren.
F1: Turistren
B3: Los valores aquí presentados pertenecen a los valores brutos.

Sheet Turistren base de datos
A1: FECHA | B1: IDA | C1: REGRESO | D1: TRAYECTO | E1: KM- REC | F1: N° COCHES | G1: VL CH KM | H1: VALOR TOTAL | I1: PASAJEROS | J1: Ch-Km | K1: MES | L1: AÑO | M1: Factura | N1: Usuario | O1: Columna1 | P1: Empresa prestadora de servicios
A2: 45297 | B2: 21301 LOC 723 | C2: 22300 LOC 723 | D2: KM-5 - ZIPAQUIRA - KM - 5 | E2: 96 | F2: 18 | G2: 929.93 | H2: =E2*F2*G2 -> 1606919 | I2: 1552 | J2: =E2*F2 -> 1728 | K2: =UPPER((TEXT(Tabla5[[#This Row],[FECHA]],"MMM"))) -> ENE | L2: =YEAR(Tabla5[[#This Row],[FECHA]]) -> 2024 | M2: 142 | N2: Turístico | O2: Turistico | P2: Turistren
A3: 45298 | B3: 21301 LOC 752 | C3: 22300 LOC 752 | D3: KM-5 - ZIPAQUIRA - KM - 5 | E3: 96 | F3: 18 | G3: 929.93 | H3: =E3*F3*G3 -> 1606919 | I3: 1564 | J3: =E3*F3 -> 1728 | K3: =UPPER((TEXT(Tabla5[[#This Row],[FECHA]],"MMM"))) -> ENE | L3: =YEAR(Tabla5[[#This Row],[FECHA]]) -> 2024 | M3: 142 | N3: Turístico | O3: Turistico | P3: Turistren
A4: 45299 | B4: 21301 LOC 723 | C4: 22300 LOC 723 | D4: KM-5 - ZIPAQUIRA - KM - 5 | E4: 96 | F4: 18 | G4: 929.93 | H4: =E4*F4*G4 -> 1606919 | I4: 1572 | J4: =E4*F4 -> 1728 | K4: =UPPER((TEXT(Tabla5[[#This Row],[FECHA]],"MMM"))) -> ENE | L4: =YEAR(Tabla5[[#This Row],[FECHA]]) -> 2024 | M4: 142 | N4: Turístico | O4: Turistico | P4: Turistren
A5: 45304 | B5: 21301 LOC 752 | C5: 22300 LOC 752 | D5: KM-5 - ZIPAQUIRA - KM - 5 | E5: 96 | F5: 17 | G5: 929.93 | H5: =E5*F5*G5 -> 1517645.8 | I5: 1420 | J5: =E5*F5 -> 1632 | K5: =UPPER((TEXT(Tabla5[[#This Row],[FECHA]],"MMM"))) -> ENE | L5: =YEAR(Tabla5[[#This Row],[FECHA]]) -> 2024 | M5: 142 | N5: Turístico | O5: Turistico | P5: Turistren
A6: 45305 | B6: 21301 LOC 723 | C6: 22300 LOC 723 | D6: KM-5 - ZIPAQUIRA - KM - 5 | E6: 96 | F6: 17 | G6: 929.93 | H6: =E6*F6*G6 -> 1517645.8 | I6: 1476 | J6: =E6*F6 -> 1632 | K6: =UPPER((TEXT(Tabla5[[#This Row],[FECHA]],"MMM"))) -> ENE | L6: =YEAR(Tabla5[[#This Row],[FECHA]]) -> 2024 | M6: 142 | N6: Turístico | O6: Turistico | P6: Turistren
A7: 45308 | B7: 21301 LOC 752 | C7: 21300 LOC 752 | D7: KM - 5 - LA CARO - KM - 5 | E7: 58 | F7: 3 | G7: 929.93 | H7: =E7*F7*G7 -> 161807.82 | I7: 40 | J7: =E7*F7 -> 174 | K7: =UPPER((TEXT(Tabla5[[#This Row],[FECHA]],"MMM"))) -> ENE | L7: =YEAR(Tabla5[[#This Row],[FECHA]]) -> 2024 | M7: 142 | N7: Universidad de la Sabana | O7: universidad | P7: Turistren
A8: 45311 | B8: 21301 LOC 752 | C8: 22300 LOC 752 | D8: KM-5 - ZIPAQUIRA - KM - 5 | E8: 96 | F8: 12 | G8: 929.93 | H8: =E8*F8*G8 -> 1071279.4 | I8: 982 | J8: =E8*F8 -> 1152 | K8: =UPPER((TEXT(Tabla5[[#This Row],[FECHA]],"MMM"))) -> ENE | L8: =YEAR(Tabla5[[#This Row],[FECHA]]) -> 2024 | M8: 142 | N8: Turístico | O8: Turistico | P8: Turistren
A9: 45312 | B9: 21301 LOC 723 | C9: 22300 LOC 723 | D9: KM-5 - ZIPAQUIRA - KM - 5 | E9: 96 | F9: 13 | G9: 929.93 | H9: =E9*F9*G9 -> 1160552.6 | I9: 1148 | J9: =E9*F9 -> 1248 | K9: =UPPER((TEXT(Tabla5[[#This Row],[FECHA]],"MMM"))) -> ENE | L9: =YEAR(Tabla5[[#This Row],[FECHA]]) -> 2024 | M9: 142 | N9: Turístico | O9: Turistico | P9: Turistren
A10: 45313 | B10: 21301 AUT 1676 | C10: 21300 AUT 1676 | D10: KM - 5 - LA CARO - KM - 5 | E10: 58 | F10: 4 | G10: 929.93 | H10: =E10*F10*G10 -> 215743.76 | I10: 136 | J10: =E10*F10 -> 232 | K10: =UPPER((TEXT(Tabla5[[#This Row],[FECHA]],"MMM"))) -> ENE | L10: =YEAR(Tabla5[[#This Row],[FECHA]]) -> 2024 | M10: 142 | N10: Universidad de la Sabana | O10: universidad | P10: Turistren
A11: 45313 | B11: 21303 LOC 711 | C11: 22300 LOC 711 | D11: KM - 5- PK-43 U MIL - KM - 5 | E11: 76 | F11: 9 | G11: 929.93 | H11: =E11*F11*G11 -> 636072.12 | I11: 991 | J11: =E11*F11 -> 684 | K11: =UPPER((TEXT(Tabla5[[#This Row],[FECHA]],"MMM"))) -> ENE | L11: =YEAR(Tabla5[[#This Row],[FECHA]]) -> 2024 | M11: 142 | N11: Universidad militar | O11: universidad | P11: Turistren
A12: 45314 | B12: 21301 AUT 1676 | C12: 21302 AUT 1676 | D12: KM - 5 - LA CARO - KM - 5 | E12: 58 | F12: 4 | G12: 929.93 | H12: =E12*F12*G12 -> 215743.76 | I12: 175 | J12: =E12*F12 -> 232 | K12: =UPPER((TEXT(Tabla5[[#This Row],[FECHA]],"MMM"))) -> ENE | L12: =YEAR(Tabla5[[#This Row],[FECHA]]) -> 2024 | M12: 142 | N12: Universidad de la Sabana | O12: universidad | P12: Turistren
A13: 45314 | B13: 21303 LOC 711 | C13: 22300 LOC 711 | D13: KM - 5- PK-43 U MIL - KM - 5 | E13: 76 | F13: 10 | G13: 929.93 | H13: =E13*F13*G13 -> 706746.8 | I13: 1232 | J13: =E13*F13 -> 760 | K13: =UPPER((TEXT(Tabla5[[#This Row],[FECHA]],"MMM"))) -> ENE | L13: =YEAR(Tabla5[[#This Row],[FECHA]]) -> 2024 | M13: 142 | N13: Universidad militar | O13: universidad | P13: Turistren
... A1072: 45853 | B1072: 31300 LOC 61 | C1072: 31301 LOC 61 | D1072: CHICAMOCHA-SOGAM-CHIC | E1072: 12 | F1072: 4 | G1072: 978.29 | H1072: =E1072*F1072*G1072 -> 46957.92 | I1072: 25 | J1072: =E1072*F1072 -> 48 | K1072: =UPPER((TEXT(Tabla5[[#This Row],[FECHA]],"MMM"))) -> JUL | L1072: =YEAR(Tabla5[[#This Row],[FECHA]]) -> 2025 | M1072: 475 | N1072: Turístico | O1072: Turístico | P1072: APDR
A1073: 45856 | B1073: 31300 LOC 61 | D1073: CHICAMOCHA - SOGAMOSO | E1073: 6 | F1073: 3 | G1073: 978.29 | H1073: =E1073*F1073*G1073 -> 17609.22 | I1073: 0 | J1073: =E1073*F1073 -> 18 | K1073: =UPPER((TEXT(Tabla5[[#This Row],[FECHA]],"MMM"))) -> JUL | L1073: =YEAR(Tabla5[[#This Row],[FECHA]]) -> 2025 | M1073: 475 | N1073: Turístico | O1073: Turístico | P1073: APDR
A1074: 45856 | B1074: 31302 LOC 61 | D1074: CHICAMOCHA - SOGAMOSO | E1074: 6 | F1074: 1 | G1074: 978.29 | H1074: =E1074*F1074*G1074 -> 5869.74 | I1074: 0 | J1074: =E1074*F1074 -> 6 | K1074: =UPPER((TEXT(Tabla5[[#This Row],[FECHA]],"MMM"))) -> JUL | L1074: =YEAR(Tabla5[[#This Row],[FECHA]]) -> 2025 | M1074: 475 | N1074: Turístico | O1074: Turístico | P1074: APDR
A1075: 45856 | B1075: 31303 LOC 61 | D1075: SOGAMOSO - CHICAMOCHA | E1075: 6 | F1075: 4 | G1075: 978.29 | H1075: =E1075*F1075*G1075 -> 23478.96 | I1075: 92 | J1075: =E1075*F1075 -> 24 | K1075: =UPPER((TEXT(Tabla5[[#This Row],[FECHA]],"MMM"))) -> JUL | L1075: =YEAR(Tabla5[[#This Row],[FECHA]]) -> 2025 | M1075: 475 | N1075: Turístico | O1075: Turístico | P1075: APDR
A1076: 45857 | B1076: 31300 LOC 61 | C1076: 31301 LOC 61 | D1076: CHICAM- DUITAMA- SOGAMOSO | E1076: 40 | F1076: 4 | G1076: 978.29 | H1076: =E1076*F1076*G1076 -> 156526.4 | I1076: 69 | J1076: =E1076*F1076 -> 160 | K1076: =UPPER((TEXT(Tabla5[[#This Row],[FECHA]],"MMM"))) -> JUL | L1076: =YEAR(Tabla5[[#This Row],[FECHA]]) -> 2025 | M1076: 475 | N1076: Turístico | O1076: Turístico | P1076: APDR
A1077: 45857 | B1077: 31302 LOC 61 | C1077: 31301 LOC 61 | D1077: SOGAMOSO - DUITAMA- CHICAM | E1077: 40 | F1077: 4 | G1077: 978.29 | H1077: =E1077*F1077*G1077 -> 156526.4 | I1077: 38 | J1077: =E1077*F1077 -> 160 | K1077: =UPPER((TEXT(Tabla5[[#This Row],[FECHA]],"MMM"))) -> JUL | L1077: =YEAR(Tabla5[[#This Row],[FECHA]]) -> 2025 | M1077: 475 | N1077: Turístico | O1077: Turístico | P1077: APDR
A1078: 45870 | B1078: 21301 AUT 1696 | C1078: 21302 AUT 1696 | D1078: KM - 5 - LA CARO - KM - 5 | E1078: 58 | F1078: 4 | G1078: 978.29 | H1078: =E1078*F1078*G1078 -> 226963.28 | I1078: 158 | J1078: =E1078*F1078 -> 232 | K1078: =UPPER((TEXT(Tabla5[[#This Row],[FECHA]],"MMM"))) -> AGO | L1078: =YEAR(Tabla5[[#This Row],[FECHA]]) -> 2025 | M1078: 508 | N1078: Universidad de la Sabana | O1078: universidad | P1078: Turistren
A1079: 45870 | B1079: 21301 LOC 711 | C1079: 22300 LOC 711 | D1079: KM - 5-PK-43 UNI MIL-KM - 5 | E1079: 76 | F1079: 9 | G1079: 978.29 | H1079: =E1079*F1079*G1079 -> 669150.36 | I1079: 1355 | J1079: =E1079*F1079 -> 684 | K1079: =UPPER((TEXT(Tabla5[[#This Row],[FECHA]],"MMM"))) -> AGO | L1079: =YEAR(Tabla5[[#This Row],[FECHA]]) -> 2025 | M1079: 508 | N1079: Universidad militar | O1079: universidad | P1079: Turistren
A1080: 45870 | B1080: 21303 LOC 723 | C1080: 21300 LOC 723 | D1080: KM - 5 - LA CARO - KM - 5 | E1080: 58 | F1080: 5 | G1080: 978.29 | H1080: =E1080*F1080*G1080 -> 283704.1 | I1080: 631 | J1080: =E1080*F1080 -> 290 | K1080: =UPPER((TEXT(Tabla5[[#This Row],[FECHA]],"MMM"))) -> AGO | L1080: =YEAR(Tabla5[[#This Row],[FECHA]]) -> 2025 | M1080: 508 | N1080: Universidad del Bosque | O1080: universidad | P1080: Turistren
A1081: 45871 | B1081: 21301 AUT 1696 | C1081: 22300 AUT 1696 | D1081: KM - 5-PK-43 UNI MIL-KM - 5 | E1081: 76 | F1081: 4 | G1081: 978.29 | H1081: =E1081*F1081*G1081 -> 297400.16 | I1081: 529 | J1081: =E1081*F1081 -> 304 | K1081: =UPPER((TEXT(Tabla5[[#This Row],[FECHA]],"MMM"))) -> AGO | L1081: =YEAR(Tabla5[[#This Row],[FECHA]]) -> 2025 | M1081: 508 | N1081: Universidad militar | O1081: universidad | P1081: Turistren
A1082: 45871 | B1082: 21303 LOC 711 | C1082: 22302 AUT 1696 | D1082: KM - 5 - ZIPAQUIRA - KM - 5 | E1082: 96 | F1082: 15 | G1082: 978.29 | H1082: =E1082*F1082*G1082 -> 1408737.6 | I1082: 1122 | J1082: =E1082*F1082 -> 1440 | K1082: =UPPER((TEXT(Tabla5[[#This Row],[FECHA]],"MMM"))) -> AGO | L1082: =YEAR(Tabla5[[#This Row],[FECHA]]) -> 2025 | M1082: 508 | N1082: Turístico | O1082: Turistico | P1082: Turistren
A1083: 45872 | B1083: 21301 LOC 711 | C1083: 22300 LOC 711 | D1083: KM - 5 - ZIPAQUIRA - KM - 5 | E1083: 96 | F1083: 16 | G1083: 978.29 | H1083: =E1083*F1083*G1083 -> 1502653.4 | I1083: 1336 | J1083: =E1083*F1083 -> 1536 | K1083: =UPPER((TEXT(Tabla5[[#This Row],[FECHA]],"MMM"))) -> AGO | L1083: =YEAR(Tabla5[[#This Row],[FECHA]]) -> 2025 | M1083: 508 | N1083: Turístico | O1083: Turistico | P1083: Turistren
A1084: 45873 | B1084: 21301 AUT 1696 | C1084: 21300 AUT 1696 | D1084: KM - 5 - LA CARO - KM - 5 | E1084: 58 | F1084: 4 | G1084: 978.29 | H1084: =E1084*F1084*G1084 -> 226963.28 | I1084: 192 | J1084: =E1084*F1084 -> 232 | K1084: =UPPER((TEXT(Tabla5[[#This Row],[FECHA]],"MMM"))) -> AGO | L1084: =YEAR(Tabla5[[#This Row],[FECHA]]) -> 2025 | M1084: 508 | N1084: Universidad de la Sabana | O1084: universidad | P1084: Turistren
A1085: 45873 | B1085: 21303 LOC 723 | C1085: 22300 LOC 723 | D1085: KM - 5-PK-43 UNI MIL-KM - 5 | E1085: 76 | F1085: 9 | G1085: 978.29 | H1085: =E1085*F1085*G1085 -> 669150.36 | I1085: 1322 | J1085: =E1085*F1085 -> 684 | K1085: =UPPER((TEXT(Tabla5[[#This Row],[FECHA]],"MMM"))) -> AGO | L1085: =YEAR(Tabla5[[#This Row],[FECHA]]) -> 2025 | M1085: 508 | N1085: Universidad militar | O1085: universidad | P1085: Turistren
A1086: 45874 | B1086: 21301 AUT 1696 | C1086: 21302 AUT 1696 | D1086: KM - 5 - LA CARO - KM - 5 | E1086: 58 | F1086: 4 | G1086: 978.29 | H1086: =E1086*F1086*G1086 -> 226963.28 | I1086: 190 | J1086: =E1086*F1086 -> 232 | K1086: =UPPER((TEXT(Tabla5[[#This Row],[FECHA]],"MMM"))) -> AGO | L1086: =YEAR(Tabla5[[#This Row],[FECHA]]) -> 2025 | M1086: 508 | N1086: Universidad de la Sabana | O1086: universidad | P1086: Turistren
A1087: 45874 | B1087: 21303 LOC 350 | C1087: 22300 LOC 350 | D1087: KM - 5-PK-43 UNI MIL-KM - 5 | E1087: 76 | F1087: 9 | G1087: 978.29 | H1087: =E1087*F1087*G1087 -> 669150.36 | I1087: 1333 | J1087: =E1087*F1087 -> 684 | K1087: =UPPER((TEXT(Tabla5[[#This Row],[FECHA]],"MMM"))) -> AGO | L1087: =YEAR(Tabla5[[#This Row],[FECHA]]) -> 2025 | M1087: 508 | N1087: Universidad militar | O1087: universidad | P1087: Turistren
... A1148: 45899 | B1148: 21303 LOC 711 | C1148: 22302 LOC 711 | D1148: KM - 5 - ZIPAQUIRA - KM - 5 | E1148: 96 | F1148: 13 | G1148: 978.29 | H1148: =E1148*F1148*G1148 -> 1220905.9 | I1148: 974 | J1148: =E1148*F1148 -> 1248 | K1148: =UPPER((TEXT(Tabla5[[#This Row],[FECHA]],"MMM"))) -> AGO | L1148: =YEAR(Tabla5[[#This Row],[FECHA]]) -> 2025 | M1148: 508 | N1148: Turístico | O1148: Turistico | P1148: Turistren
A1149: 45900 | B1149: 21301 LOC 723 | C1149: 22300 LOC 723 | D1149: KM - 5 - ZIPAQUIRA - KM - 5 | E1149: 96 | F1149: 15 | G1149: 978.29 | H1149: 1408737.6 | I1149: 1132 | J1149: =E1149*F1149 -> 1440 | K1149: =UPPER((TEXT(Tabla5[[#This Row],[FECHA]],"MMM"))) -> AGO | L1149: =YEAR(Tabla5[[#This Row],[FECHA]]) -> 2025 | M1149: 508 | N1149: Turístico | O1149: Turistico | P1149: Turistren
A1150: 45886 | B1150: 31300 LOC 61 | C1150: 31302 LOC 61 | D1150: CHICAMOCHA-SOGAMOSO-CHICAMOCHA | E1150: 12 | F1150: 4 | G1150: 978.29 | H1150: =E1150*F1150*G1150 -> 46957.92 | I1150: 120 | J1150: =E1150*F1150 -> 48 | K1150: =UPPER((TEXT(Tabla5[[#This Row],[FECHA]],"MMM"))) -> AGO | L1150: =YEAR(Tabla5[[#This Row],[FECHA]]) -> 2025 | M1150: 509 | N1150: Turístico | O1150: Turístico | P1150: APDR
A1151: 45886 | B1151: 31301 LOC 61 | C1151: 31304 LOC 61 | D1151: CHICAMOCHA-SOGAMOSO-CHICAMOCHA | E1151: 12 | F1151: 4 | G1151: 978.29 | H1151: =E1151*F1151*G1151 -> 46957.92 | I1151: 120 | J1151: =E1151*F1151 -> 48 | K1151: =UPPER((TEXT(Tabla5[[#This Row],[FECHA]],"MMM"))) -> AGO | L1151: =YEAR(Tabla5[[#This Row],[FECHA]]) -> 2025 | M1151: 509 | N1151: Turístico | O1151: Turístico | P1151: APDR
A1152: 45901 | B1152: 21301 AUT 1696 | C1152: 21302 AUT 1696 | D1152: KM - 5 - LA CARO - KM - 5 | E1152: 58 | F1152: 4 | G1152: 978.29 | H1152: 226963.28 | I1152: 202 | J1152: 232 | K1152: =UPPER((TEXT(Tabla5[[#This Row],[FECHA]],"MMM"))) -> SEP | L1152: =YEAR(Tabla5[[#This Row],[FECHA]]) -> 2025 | M1152: 526 | N1152: Universidad de la Sabana | O1152: universidad | P1152: Turistren
A1153: 45901 | B1153: 21301 LOC 711 | C1153: 22300 LOC 711 | D1153: KM - 5-PK-43 UNI MIL-KM - 5 | E1153: 76 | F1153: 9 | G1153: 978.29 | H1153: 669150.36 | I1153: 1256 | J1153: 684 | K1153: =UPPER((TEXT(Tabla5[[#This Row],[FECHA]],"MMM"))) -> SEP | L1153: =YEAR(Tabla5[[#This Row],[FECHA]]) -> 2025 | M1153: 526 | N1153: Universidad militar | O1153: universidad | P1153: Turistren
A1154: 45902 | B1154: 21301 AUT 1696 | C1154: 21302 AUT 1696 | D1154: KM - 5 - LA CARO - KM - 5 | E1154: 58 | F1154: 4 | G1154: 978.29 | H1154: 226963.28 | I1154: 220 | J1154: 232 | K1154: =UPPER((TEXT(Tabla5[[#This Row],[FECHA]],"MMM"))) -> SEP | L1154: =YEAR(Tabla5[[#This Row],[FECHA]]) -> 2025 | M1154: 526 | N1154: Universidad de la Sabana | O1154: universidad | P1154: Turistren
A1155: 45902 | B1155: 21303 LOC 350 | C1155: 22300 LOC 350 | D1155: KM - 5-PK-43 UNI MIL-KM - 5 | E1155: 76 | F1155: 9 | G1155: 978.29 | H1155: 669150.36 | I1155: 1276 | J1155: 684 | K1155: =UPPER((TEXT(Tabla5[[#This Row],[FECHA]],"MMM"))) -> SEP | L1155: =YEAR(Tabla5[[#This Row],[FECHA]]) -> 2025 | M1155: 526 | N1155: Universidad militar | O1155: universidad | P1155: Turistren
A1156: 45902 | B1156: 21305 AUT 1723 | C1156: 21300 AUT 1723 | D1156: KM - 5 - LA CARO - KM - 5 | E1156: 58 | F1156: 4 | G1156: 978.29 | H1156: 226963.28 | I1156: 405 | J1156: 232 | K1156: =UPPER((TEXT(Tabla5[[#This Row],[FECHA]],"MMM"))) -> SEP | L1156: =YEAR(Tabla5[[#This Row],[FECHA]]) -> 2025 | M1156: 526 | N1156: Universidad del Bosque | O1156: universidad | P1156: Turistren
A1157: 45903 | B1157: 21301 AUT 1696 | C1157: 21302 AUT 1696 | D1157: KM - 5 - LA CARO - KM - 5 | E1157: 58 | F1157: 4 | G1157: 978.29 | H1157: 226963.28 | I1157: 239 | J1157: 232 | K1157: =UPPER((TEXT(Tabla5[[#This Row],[FECHA]],"MMM"))) -> SEP | L1157: =YEAR(Tabla5[[#This Row],[FECHA]]) -> 2025 | M1157: 526 | N1157: Universidad de la Sabana | O1157: universidad | P1157: Turistren
A1158: 45903 | B1158: 21303 LOC 350 | C1158: 22300 LOC 350 | D1158: KM - 5-PK-43 UNI MIL-KM - 5 | E1158: 76 | F1158: 9 | G1158: 978.29 | H1158: 669150.36 | I1158: 1167 | J1158: 684 | K1158: =UPPER((TEXT(Tabla5[[#This Row],[FECHA]],"MMM"))) -> SEP | L1158: =YEAR(Tabla5[[#This Row],[FECHA]]) -> 2025 | M1158: 526 | N1158: Universidad militar | O1158: universidad | P1158: Turistren
A1159: 45903 | B1159: 21305 LOC 723 | C1159: 21300 LOC 723 | D1159: KM - 5 - LA CARO - KM - 5 | E1159: 58 | F1159: 5 | G1159: 978.29 | H1159: 283704.1 | I1159: 512 | J1159: 290 | K1159: =UPPER((TEXT(Tabla5[[#This Row],[FECHA]],"MMM"))) -> SEP | L1159: =YEAR(Tabla5[[#This Row],[FECHA]]) -> 2025 | M1159: 526 | N1159: Universidad del Bosque | O1159: universidad | P1159: Turistren
A1160: 45904 | B1160: 21301 AUT 1696 | C1160: 21302 AUT 1696 | D1160: KM - 5 - LA CARO - KM - 5 | E1160: 58 | F1160: 4 | G1160: 978.29 | H1160: 226963.28 | I1160: 203 | J1160: 232 | K1160: =UPPER((TEXT(Tabla5[[#This Row],[FECHA]],"MMM"))) -> SEP | L1160: =YEAR(Tabla5[[#This Row],[FECHA]]) -> 2025 | M1160: 526 | N1160: Universidad de la Sabana | O1160: universidad | P1160: Turistren
A1161: 45904 | B1161: 21303 LOC 350 | C1161: 22300 LOC 350 | D1161: KM - 5-PK-43 UNI MIL-KM - 5 | E1161: 76 | F1161: 9 | G1161: 978.29 | H1161: 669150.36 | I1161: 954 | J1161: 684 | K1161: =UPPER((TEXT(Tabla5[[#This Row],[FECHA]],"MMM"))) -> SEP | L1161: =YEAR(Tabla5[[#This Row],[FECHA]]) -> 2025 | M1161: 526 | N1161: Universidad militar | O1161: universidad | P1161: Turistren
A1162: 45904 | B1162: 21305 AUT 1723 | C1162: 21300 AUT 1723 | D1162: KM - 5 - LA CARO - KM - 5 | E1162: 58 | F1162: 4 | G1162: 978.29 | H1162: 226963.28 | I1162: 475 | J1162: 232 | K1162: =UPPER((TEXT(Tabla5[[#This Row],[FECHA]],"MMM"))) -> SEP | L1162: =YEAR(Tabla5[[#This Row],[FECHA]]) -> 2025 | M1162: 526 | N1162: Universidad del Bosque | O1162: universidad | P1162: Turistren
A1163: 45905 | B1163: 21301 AUT 1696 | C1163: 21302 AUT 1696 | D1163: KM - 5 - LA CARO - KM - 5 | E1163: 58 | F1163: 4 | G1163: 978.29 | H1163: 226963.28 | I1163: 197 | J1163: 232 | K1163: =UPPER((TEXT(Tabla5[[#This Row],[FECHA]],"MMM"))) -> SEP | L1163: =YEAR(Tabla5[[#This Row],[FECHA]]) -> 2025 | M1163: 526 | N1163: Universidad de la Sabana | O1163: universidad | P1163: Turistren
... A1225: 45930 | B1225: 21307 LOC 723 | C1225: 21304 LOC 723 | D1225: KM 5 / SUESCA / KM / 5 | E1225: 138 | F1225: 9 | G1225: 978.29 | H1225: 1215036.2 | I1225: 50 | J1225: 1242 | K1225: =UPPER((TEXT(Tabla5[[#This Row],[FECHA]],"MMM"))) -> SEP | L1225: =YEAR(Tabla5[[#This Row],[FECHA]]) -> 2025 | M1225: 526 | N1225: Turístico | O1225: Turístico | P1225: Turistren
A1226: 45906 | B1226: 31300 LOC 61 | C1226: 31302 LOC 61 | D1226: CHICAMOCHA-SOGAMOSO-CHICAMOCHA | E1226: 12 | F1226: 4 | G1226: 978.29 | H1226: 46957.92 | I1226: 170 | J1226: =E1226*F1226 -> 48 | K1226: =UPPER((TEXT(Tabla5[[#This Row],[FECHA]],"MMM"))) -> SEP | L1226: =YEAR(Tabla5[[#This Row],[FECHA]]) -> 2025 | M1226: 525 | N1226: Turístico | O1226: Turístico | P1226: APDR
A1227: 45906 | B1227: 31301 LOC 61 | C1227: 31304 LOC 61 | D1227: CHICAMOCHA-SOGAMOSO-CHICAMOCHA | E1227: 12 | F1227: 4 | G1227: 978.29 | H1227: 46957.92 | I1227: 170 | J1227: =E1227*F1227 -> 48 | K1227: =UPPER((TEXT(Tabla5[[#This Row],[FECHA]],"MMM"))) -> SEP | L1227: =YEAR(Tabla5[[#This Row],[FECHA]]) -> 2025 | M1227: 525 | N1227: Turístico | O1227: Turístico | P1227: APDR
A1228: 45927 | B1228: 21300 LOC 61 | C1228: 31301 LOC 61 | D1228: CHICAMOCHA-PAIPA-CHICAMOCHA | E1228: 74 | F1228: 4 | G1228: 978.29 | H1228: 289573.84 | I1228: 44 | J1228: =E1228*F1228 -> 296 | K1228: =UPPER((TEXT(Tabla5[[#This Row],[FECHA]],"MMM"))) -> SEP | L1228: =YEAR(Tabla5[[#This Row],[FECHA]]) -> 2025 | M1228: 525 | N1228: Turístico | O1228: Turístico | P1228: APDR
I1229: =SUBTOTAL(109,Tabla5[PASAJEROS]) -> 867652

Sheet Tablas Turistren
V1: AÑO | W1: 2024
C2: Etiquetas de fila | D2: Suma de VALOR TOTAL | G2: Etiquetas de fila | H2: Suma de N° COCHES | K2: Etiquetas de fila | L2: Suma de PASAJEROS | O2: Etiquetas de fila | P2: Suma de Ch-Km
C3: SEP | D3: 35020825 | G3: SEP | H3: 509 | K3: SEP | L3: 48324 | O3: SEP | P3: 35798 | S3: Etiquetas de fila | T3: Suma de PASAJEROS | V3: Etiquetas de fila | W3: Suma de PASAJEROS
C4: APDR | D4: 383489.68 | G4: APDR | H4: 12 | K4: APDR | L4: 384 | O4: Total general | P4: 35798 | S4: Turístico | T4: 101821 | V4: Turistico | W4: 199795
A5: Total general | B5: =VLOOKUP(A5,C:D,2,TRUE) -> 35020825 | C5: Turistren | D5: 34637336 | E5: Total general | F5: =VLOOKUP(E5,G:H,2,TRUE) -> 509 | G5: Turistren | H5: 497 | I5: Total general | J5: =VLOOKUP(I5,K:L,2,TRUE) -> 48324 | K5: Turistren | L5: 47940 | M5: Total general | N5: =VLOOKUP(M5,O:P,2,TRUE) -> 35798 | S5: 2025 | T5: 101821 | V5: ene | W5: 11630 | Y5: 18431
C6: Total general | D6: 35020825 | G6: Total general | H6: 509 | K6: Total general | L6: 48324 | S6: Universidad de la Sabana | T6: 26804 | V6: feb | W6: 6610
S7: 2025 | T7: 26804 | V7: mar | W7: 18062
S8: Universidad del Bosque | T8: 58305 | V8: abr | W8: 6328
S9: 2025 | T9: 58305 | V9: may | W9: 9096
S10: Universidad militar | T10: 166438 | V10: jun | W10: 15560
S11: 2025 | T11: 166438 | V11: jul | W11: 12492
S12: Total general | T12: 353368 | V12: ago | W12: 12392
V13: sep | W13: 8142
V14: oct | W14: 10956
V15: nov | W15: 15963
V16: dic | W16: 72564
V17: universidad | W17: 314489 | Y17: 11342
V18: ene | W18: 15389
V19: feb | W19: 43493
V20: mar | W20: 33941
V21: abr | W21: 43283
V22: may | W22: 29937
V23: jun | W23: 17
V24: jul | W24: 16190
V25: ago | W25: 42084
V26: sep | W26: 33235
V27: oct | W27: 32653
V28: nov | W28: 23812
V29: dic | W29: 455 | Y29: 26207
V30: Total general | W30: 514284
